Workbook

Sheet Hypothesis Tests
A1: Task 5 – Statistical Validation
A2: Hypothesis 1 – Win Rate Comparison
A3: H₀ (Null Hypothesis): | B3: Product-Led Signup + Inbound Organic deals do not have a higher win rate than Cold Outreach + Paid Search deals.
A5: H₁ (Alternative Hypothesis): | B5: Product-Led Signup + Inbound Organic deals have a higher win rate than Cold Outreach + Paid Search deals.
A7: Test: | B7: Two-Proportion Z-Test
A9: Confidence Level: | B9: 0.95
A11: Significance Level (α): | B11: 0.05
A14: Group | B14: Won | C14: Lost | D14: Closed Deals | E14: Win Rate
A15: Product-Led Signup + Inbound Organic | B15: 158 | C15: 119 | D15: =B15+C15 -> 277 | E15: =B15/D15 -> 0.57039711
A16: Cold Outreach + Paid Search | B16: 163 | C16: 152 | D16: =B16+C16 -> 315 | E16: =B16/D16 -> 0.51746032
A18: Pooled Win Rate | B18: =(B15+B16)/(D15+D16) -> 0.54222973
A19: Standard Error | B19: =SQRT(B18*(1-B18)*(1/D15+1/D16)) -> 0.041037524
A20: Z-Statistic | B20: =(E15-E16)/B19 -> 1.2899607
A21: One-Tailed P-Value | B21: =1-_xlfn.NORM.S.DIST(B20,TRUE) -> 0.098532145
A22: Decision | B22: =IF(B21<B11,"Reject H0","Fail to Reject H0") -> Fail to Reject H0
A24: Business Interpretation: | B24: Although Product-Led Signup + Inbound Organic had a higher observed win rate (57.04% vs. 51.75%), the difference is not statistically significant (p = 0.099 > 0.05). Therefore, there is not enough evidence to conclude that these channels have a higher win rate.
A27: Hypothesis 2 – LTV/CAC Comparison
A29: H₀ (Null Hypothesis): | B29: The mean LTV/CAC ratio is the same across all acquisition channels.
A30: H₁ (Alternative Hypothesis): | B30: At least one acquisition channel has a different mean LTV/CAC ratio.
A31: Test: | B31: One-Way ANOVA
A32: Confidence Level: | B32: 0.95
A33: Significance Level (α): | B33: 0.05
A37: Anova: Single Factor
A39: SUMMARY
A40: Groups | B40: Count | C40: Sum | D40: Average | E40: Variance
A41: Product-Led Signup | B41: 143 | C41: 253763.52 | D41: 1774.5701 | E41: 1866592.9
A42: Inbound Organic | B42: 169 | C42: 155221.12 | D42: 918.46817 | E42: 549954.68
A43: Webinar | B43: 137 | C43: 67312.32 | D43: 491.3308 | E43: 152373.7
A44: Partner Referral | B44: 137 | C44: 52959.95 | D44: 386.56898 | E44: 96986.407
A45: Cold Outreach | B45: 147 | C45: 45511.4 | D45: 309.60136 | E45: 62332.778
A46: Paid Search | B46: 122 | C46: 31436.36 | D46: 257.67508 | E46: 44953.233
A47: LinkedIn Ads | B47: 139 | C47: 28727.43 | D47: 206.67216 | E47: 24091.831
A50: ANOVA
A51: Source of Variation | B51: SS | C51: df | D51: MS | E51: F | F51: P-value | G51: F crit
A52: Between Groups | B52: 2.6898781e+08 | C52: 6 | D52: 44831301 | E52: 108.12724 | F52: 1.0280954e-104 | G52: 2.1077505
A53: Within Groups | B53: 4.0922615e+08 | C53: 987 | D53: 414616.16
A55: Total | B55: 6.7821396e+08 | C55: 993
A58: ANOVA Assumption Check
A59: Variance Equality | B59: Unequal variances (Levene p < 0.001) | C59: =MEDIAN(H2_ANOVA_Data!V2:V144) -> 1401.53 | D59: =MEDIAN(H2_ANOVA_Data!W2:W170) -> 731.3 | E59: =MEDIAN(H2_ANOVA_Data!X2:X138) -> 405.35 | F59: =MEDIAN(H2_ANOVA_Data!Y2:Y138) -> 314.73 | G59: =MEDIAN(H2_ANOVA_Data!Z2:Z148) -> 238.63 | H59: =MEDIAN(H2_ANOVA_Data!AA2:AA123) -> 204.955 | I59: =MEDIAN(H2_ANOVA_Data!AB2:AB140) -> 173.09
A60: Normality / Distribution | B60: Strongly right-skewed; normality assumption is questionable
A61: Conclusion | B61: ANOVA assumptions are not fully met; use Kruskal-Wallis as the primary test
A63: Levene's Test (Variance Equality) | B63: F Statistic | C63: 81.8704 | D63: p-value | E63: 3.66e-83
A64: Kruskal-Wallis Test (Non-Parametric Alternative) | B64: H Statistic | C64: 334.8933 | D64: p-value | E64: 2.696e-69
A65: Anova: Single Factor
B66: Decision | C66: Reject H0
A67: SUMMARY
A68: Groups | B68: Count | C68: Sum | D68: Average | E68: Variance
A69: Column 1 | B69: 143 | C69: 150556.73 | D69: 1052.8443 | E69: 890444.55
A70: Column 2 | B70: 169 | C70: 97750.3 | D70: 578.40414 | E70: 248652.39
A71: Column 3 | B71: 137 | C71: 41683.79 | D71: 304.26124 | E71: 66565.152
A72: Column 4 | B72: 137 | C72: 32599.8 | D72: 237.95474 | E72: 45146.391
A73: Column 5 | B73: 147 | C73: 28809.07 | D73: 195.98007 | E73: 28732.955
A74: Column 6 | B74: 122 | C74: 18460.1 | D74: 151.3123 | E74: 24670.981
A75: Column 7 | B75: 139 | C75: 16743.26 | D75: 120.45511 | E75: 10613.191
A78: ANOVA
A79: Source of Variation | B79: SS | C79: df | D79: MS | E79: F | F79: P-value | G79: F crit
A80: Between Groups | B80: 95583959 | C80: 6 | D80: 15930660 | E80: 81.870386 | F80: 3.6621113e-83 | G80: 2.1077505
A81: Within Groups | B81: 1.9205432e+08 | C81: 987 | D81: 194583.91
A83: Total | B83: 2.8763828e+08 | C83: 993
A86: Hypothesis 3 – SLA Breach and Churn Risk
A87: H₀ (Null Hypothesis): | B87: Customers with and without first-90-day SLA breaches have the same distribution of Churn_Risk_Flag.
A88: H₁ (Alternative Hypothesis): | B88: Customers with first-90-day SLA breaches have a different distribution of Churn_Risk_Flag.
A89: Test: | B89: Chi-Square Test of Independence
A90: Confidence Level | B90: 0.95
A91: Significance Level (α) | B91: 0.05
A93: Observed Frequencies
A94: SLA Breach | B94: Churn Risk = 0 | C94: Churn Risk = 1
A95: No | B95: =COUNTIFS('Customers'!$O:$O,0,'Customers'!$N:$N,0) -> 856 | C95: =COUNTIFS('Customers'!$O:$O,0,'Customers'!$N:$N,1) -> 416
A96: Yes | B96: =COUNTIFS('Customers'!$O:$O,1,'Customers'!$N:$N,0) -> 152 | C96: =COUNTIFS('Customers'!$O:$O,1,'Customers'!$N:$N,1) -> 76
A98: Expected Frequencies
A99: SLA Breach | B99: Churn Risk = 0 | C99: Churn Risk = 1
A100: No | B100: =SUM(B95:C95)*SUM(B95:B96)/SUM(B95:C96) -> 854.784 | C100: =SUM(B95:C95)*SUM(C95:C96)/SUM(B95:C96) -> 417.216
A101: Yes | B101: =SUM(B96:C96)*SUM(B95:B96)/SUM(B95:C96) -> 153.216 | C101: =SUM(B96:C96)*SUM(C95:C96)/SUM(B95:C96) -> 74.784
A103: Chi-Square Statistic | B103: {=SUM((B95:B96-B100:B101)^2/B100:B101)+SUM((C95:C96-C100:C101)^2/C100:C101)} -> 0.034697112
A104: Degrees of Freedom | B104: =1 -> 1
A105: p-value | B105: =_xlfn.CHISQ.DIST.RT(B103,B104) -> 0.85223177
A106: Decision | B106: =IF(B105<B91,"Reject H₀","Fail to Reject H₀") -> Fail to Reject H₀
A108: Business Interpretation | B108: Customers with first-90-day SLA breaches do not show a statistically significant difference in Churn Risk Flag compared with customers without SLA breaches (χ² = 0.035, p = 0.852 > 0.05).
A111: Hypothesis 4 – Activation Rate Comparison
A112: H₀ (Null Hypothesis): | B112: In-App Nudge campaigns do not have a higher Activation Rate than non-In-App campaigns.
A113: H₁ (Alternative Hypothesis): | B113: In-App Nudge campaigns have a higher Activation Rate than non-In-App campaigns.
A114: Test: | B114: Independent Samples t-Test (Welch's t-test)
A115: Confidence Level | B115: 0.95
A116: Significance Level (α) | B116: 0.05
A118: Campaign Group | B118: n | C118: Mean Activation Rate
A119: In-App Nudge | B119: 46 | C119: 0.243333
A120: Non-In-App | B120: 361 | C120: 0.160893
A122: Test Statistic (t) | B122: =4.688024288 -> 4.6880243
A123: p-value | B123: 1.0653618e-05
A124: Decision | B124: =IF(B123<B116,"Reject H₀","Fail to Reject H₀") -> Reject H₀
A126: Business Interpretation | B126: In-App Nudge campaigns have a statistically significantly higher Activation Rate than non-In-App campaigns (p < 0.001).

Sheet H2_ANOVA_Data
A1: Record_ID | B1: Customer_ID | C1: Cohort | D1: Service_Line | E1: Acquisition_Channel | F1: Scenario | G1: MRR_USD | H1: ARR_USD | I1: CAC_USD | J1: LTV_USD | K1: LTV_CAC_Ratio | L1: Monthly_Churn_Rate_Pct | M1: Expansion_MRR_USD | N1: Contraction_MRR_USD | O1: Burn_Rate_USD | P1: Cash_Balance_USD | Q1: Runway_Months | R1: Gross_Margin_Pct | S1: Budget_Variance_Pct | T1: Period_Start_Date | U1: Period_End_Date | V1: Product-Led Signup | W1: Inbound Organic | X1: Webinar | Y1: Partner Referral | Z1: Cold Outreach | AA1: Paid Search | AB1: LinkedIn Ads | AC1: Product-Led Signup | AD1: Inbound Organic | AE1: Webinar | AF1: Partner Referral | AG1: Cold Outreach | AH1: Paid Search | AI1: LinkedIn Ads
A2: FIN-0001 | B2: CUST-0712 | C2: 2023-Q2 | D2: WorkHub Enterprise | E2: Webinar | F2: Optimistic | G2: 7113.63 | H2: 85363.56 | I2: 253.1 | J2: 251970.96 | K2: 995.54 | L2: 6.58 | M2: 52.12 | N2: 0 | O2: 343848.6 | P2: 19239355 | Q2: 56 | R2: 78.09 | S2: 6.98 | T2: 2022-04-10 | U2: 2022-05-15 | V2: {=_xlfn._xlws.FILTER($K$2:$K$1101,($E$2:$E$1101=V$1)*($I$2:$I$1101<>"")*($J$2:$J$1101<>"")*($K$2:$K$1101<>"")*($K$2:$K$1101>=0),"")} -> 557.48 | W2: {=_xlfn._xlws.FILTER($K$2:$K$1101,($E$2:$E$1101=W$1)*($I$2:$I$1101<>"")*($J$2:$J$1101<>"")*($K$2:$K$1101<>"")*($K$2:$K$1101>=0),"")} -> 467 | X2: {=_xlfn._xlws.FILTER($K$2:$K$1101,($E$2:$E$1101=X$1)*($I$2:$I$1101<>"")*($J$2:$J$1101<>"")*($K$2:$K$1101<>"")*($K$2:$K$1101>=0),"")} -> 995.54 | Y2: {=_xlfn._xlws.FILTER($K$2:$K$1101,($E$2:$E$1101=Y$1)*($I$2:$I$1101<>"")*($J$2:$J$1101<>"")*($K$2:$K$1101<>"")*($K$2:$K$1101>=0),"")} -> 122.87 | Z2: {=_xlfn._xlws.FILTER($K$2:$K$1101,($E$2:$E$1101=Z$1)*($I$2:$I$1101<>"")*($J$2:$J$1101<>"")*($K$2:$K$1101<>"")*($K$2:$K$1101>=0),"")} -> 155.17 | AA2: {=_xlfn._xlws.FILTER($K$2:$K$1101,($E$2:$E$1101=AA$1)*($I$2:$I$1101<>"")*($J$2:$J$1101<>"")*($K$2:$K$1101<>"")*($K$2:$K$1101>=0),"")} -> 279.82 | AB2: {=_xlfn._xlws.FILTER($K$2:$K$1101,($E$2:$E$1101=AB$1)*($I$2:$I$1101<>"")*($J$2:$J$1101<>"")*($K$2:$K$1101<>"")*($K$2:$K$1101>=0),"")} -> 234.03 | AC2: 844.05 | AD2: 264.3 | AE2: 590.19 | AF2: 191.86 | AG2: 83.46 | AH2: 74.865 | AI2: 60.94
A3: FIN-0002 | B3: CUST-1099 | C3: 2024-Q2 | D3: API Access | E3: Cold Outreach | F3: Optimistic | G3: 15000.1 | H3: 180001.2 | I3: 589.51 | J3: 91476.66 | K3: 155.17 | L3: 53.17 | M3: 2947.43 | N3: 0 | O3: 622565.27 | P3: 17374897 | Q3: 27.9 | R3: 55.54 | S3: -26.66 | T3: 2023-06-08 | U3: 2023-08-13 | V3: 910.35 | W3: 124.75 | X3: 128.03 | Y3: 337.06 | Z3: 85.18 | AA3: 221.1 | AB3: 90.12 | AC3: 491.18 | AD3: 606.55 | AE3: 277.32 | AF3: 22.33 | AG3: 153.45 | AH3: 16.145 | AI3: 82.97
A4: FIN-0003 | B4: CUST-1110 | C4: 2024-Q4 | D4: API Access | E4: Paid Search | F4: Optimistic | G4: 9439.01 | H4: 113268.12 | I4: 651.79 | J4: 182382.51 | K4: 279.82 | L4: 6.06 | M4: 0 | N4: 1229.11 | O4: 832270.77 | P4: 17697570 | Q4: 21.3 | R4: 75.11 | S4: 128.11 | T4: 2022-11-23 | U4: 2022-12-30 | V4: 3869.04 | W4: 1659.74 | X4: 1209.53 | Y4: 374.9 | Z4: 33.74 | AA4: 287.93 | AB4: 56.8 | AC4: 2467.51 | AD4: 928.44 | AE4: 804.18 | AF4: 60.17 | AG4: 204.89 | AH4: 82.975 | AI4: 116.29
A5: FIN-0004 | B5: CUST-1349 | C5: 2022-Q3 | D5: WorkHub Pro | E5: Product-Led Signup | F5: Pessimistic | G5: 5601.95 | H5: 67223.4 | I5: 148.92 | J5: 83020.66 | K5: 557.48 | L5: 2.94 | M5: 0 | N5: 0 | O5: 645226.89 | P5: 13541223 | Q5: 21 | R5: 72.22 | S5: 24 | T5: 2024-05-29 | U5: 2024-08-06 | V5: 2264.6 | W5: 590.52 | X5: 78.28 | Y5: 365.85 | Z5: 278.76 | AA5: 398.97 | AB5: 248.34 | AC5: 863.07 | AD5: 140.78 | AE5: 327.07 | AF5: 51.12 | AG5: 40.13 | AH5: 194.015 | AI5: 75.25
A6: FIN-0005 | B6: CUST-0073 | C6: 2022-Q3 | D6: WorkHub Pro | E6: Inbound Organic | F6: Pessimistic | G6: 1862.58 | H6: 22350.96 | I6: 129.42 | J6: 60438.76 | K6: 467 | L6: 1.56 | M6: 0 | N6: 208.31 | O6: 246750.63 | P6: 22808993 | Q6: 92.4 | R6: 73.04 | S6: 21.48 | T6: 2024-01-22 | U6: 2024-03-08 | V6: 1049.61 | W6: 457.96 | X6: 1489.4 | Y6: 272.65 | Z6: 625.8 | AA6: 111.23 | AB6: 49.35 | AC6: 351.92 | AD6: 273.34 | AE6: 1084.05 | AF6: 42.08 | AG6: 387.17 | AH6: 93.725 | AI6: 123.74
A7: FIN-0006 | B7: CUST-0447 | C7: 2022-Q4 | D7: WorkHub Pro | E7: Inbound Organic | F7: Base | G7: 10385.63 | H7: 124627.56 | I7: 243.86 | J7: 365196.36 | L7: 7.78 | M7: 0 | N7: 0 | O7: 676775.72 | P7: 1678992.8 | Q7: 2.5 | R7: 78.79 | S7: 9.7 | T7: 2024-03-08 | U7: 2024-04-30 | V7: 2462.23 | W7: 2749.23 | X7: 46.13 | Y7: 26.43 | Z7: 101.33 | AA7: 52.94 | AB7: 323.99 | AC7: 1060.7 | AD7: 2017.93 | AE7: 359.22 | AF7: 288.3 | AG7: 137.3 | AH7: 152.015 | AI7: 150.9
A8: FIN-0007 | B8: CUST-1084 | C8: 2022-Q3 | D8: WorkHub Enterprise | E8: LinkedIn Ads | F8: Base | G8: 9546.76 | H8: 114561.12 | I8: 875.81 | J8: 204966.82 | K8: 234.03 | L8: 2.22 | M8: 2995.36 | N8: 456.95 | O8: 327811.8 | P8: 22740840 | Q8: 69.4 | R8: 79.65 | S8: -5.27 | T8: 2023-12-18 | U8: 2024-03-05 | V8: 989.7 | W8: 1458.38 | X8: 316.12 | Y8: 597.67 | Z8: 124.84 | AA8: 184.76 | AB8: 593.33 | AC8: 411.83 | AD8: 727.08 | AE8: 89.23 | AF8: 282.94 | AG8: 113.79 | AH8: 20.195 | AI8: 420.24
A9: FIN-0008 | B9: CUST-0237 | C9: 2024-Q2 | D9: WorkHub Pro | E9: Cold Outreach | F9: Pessimistic | G9: 9060.92 | H9: 108731.04 | I9: 430.09 | J9: 84562.82 | K9: -196.62 | L9: 52.17 | M9: 510.84 | N9: 0 | O9: 659347.52 | P9: 8135544.3 | Q9: 12.3 | R9: 76.16 | S9: 39.09 | T9: 2022-04-22 | U9: 2022-06-22 | V9: 1465 | W9: 46.08 | X9: 507.94 | Y9: 206.5 | Z9: 373.7 | AA9: 70.33 | AB9: 51.83 | AC9: 63.47 | AD9: 685.22 | AE9: 102.59 | AF9: 108.23 | AG9: 135.07 | AH9: 134.625 | AI9: 121.26
A10: FIN-0009 | B10: CUST-1344 | C10: 2023-Q1 | D10: WorkHub Core | E10: Webinar | F10: Pessimistic | G10: 5275.89 | H10: 63310.68 | I10: 470.36 | J10: 60218.87 | K10: 128.03 | L10: 9.74 | M10: 630.57 | N10: 56.33 | O10: 508790.47 | P10: 4743902.5 | Q10: 9.3 | R10: 70.5 | S10: 35.62 | T10: 2022-07-28 | U10: 30/09/2022 | V10: 2185.03 | W10: 385.3 | X10: 616.89 | Y10: 2.12 | Z10: 508.58 | AA10: 397.78 | AB10: 153.13 | AC10: 783.5 | AD10: 346 | AE10: 211.54 | AF10: 312.61 | AG10: 269.95 | AH10: 192.825 | AI10: 19.96
A11: FIN-0010 | B11: CUST-1213 | C11: 2024-Q3 | D11: WorkHub Pro | E11: Cold Outreach | F11: Base | G11: 7491.05 | H11: 89892.6 | I11: 702.58 | J11: 59845.71 | K11: 85.18 | L11: 11.1 | M11: 650.39 | N11: 0 | O11: 828711.77 | P11: 21544627 | Q11: 26 | R11: 81.13 | S11: -28.21 | T11: 2022-06-09 | U11: 2022-08-25 | V11: 1140.24 | W11: 1006.28 | X11: 37.33 | Y11: 108.69 | Z11: 1002.46 | AA11: 105.28 | AB11: 330.21 | AC11: 261.29 | AD11: 274.98 | AE11: 368.02 | AF11: 206.04 | AG11: 763.83 | AH11: 99.675 | AI11: 157.12
A12: FIN-0011 | B12: CUST-0701 | C12: 2024-Q2 | D12: WorkHub Pro | E12: Cold Outreach | F12: Base | G12: 851.27 | H12: 10215.24 | I12: 735.6 | J12: 24822.02 | K12: 33.74 | L12: 11.04 | M12: 0 | N12: 0 | O12: 853289.81 | P12: 11970922 | Q12: 14 | R12: 78.4 | S12: -15.69 | T12: 2023-01-06 | U12: 17/02/2023 | V12: 2056.63 | W12: 2188.34 | X12: 993.49 | Y12: 140.93 | Z12: 223.89 | AA12: 226.15 | AB12: 312.7 | AC12: 655.1 | AD12: 1457.04 | AE12: 588.14 | AF12: 173.8 | AG12: 14.74 | AH12: 21.195 | AI12: 139.61
A13: FIN-0012 | B13: CUST-0389 | C13: 2024-Q2 | D13: WorkHub Pro | E13: Webinar | F13: Optimistic | G13: 15497.5 | H13: 185970 | I13: 435.4 | J13: 526630.55 | K13: 1209.53 | L13: 8.31 | M13: 0 | N13: 0 | O13: 245993.77 | P13: 18344697 | Q13: 74.6 | R13: 75.97 | S13: -16.2 | T13: 2023-09-20 | U13: 2023-11-19 | V13: 161.62 | W13: 1583.11 | X13: 114.46 | Y13: 130.1 | Z13: 418.58 | AA13: 623.42 | AB13: 343.11 | AC13: 1239.91 | AD13: 851.81 | AE13: 290.89 | AF13: 184.63 | AG13: 179.95 | AH13: 418.465 | AI13: 170.02
A14: FIN-0013 | B14: CUST-0851 | C14: 2022-Q2 | D14: Analytics Add-on | E14: Inbound Organic | F14: Pessimistic | G14: 895.38 | H14: 10744.56 | I14: 236.97 | J14: 29562.37 | K14: 124.75 | L14: 11.14 | M14: 68.19 | N14: 0 | O14: 860962.14 | P14: 14815813 | Q14: 17.2 | R14: 80.26 | S14: 17.59 | T14: 2022-07-27 | U14: 2022-09-18 | V14: 459.75 | W14: 497.84 | X14: 405.35 | Y14: 179.6 | Z14: 177.35 | AA14: 72.84 | AB14: 226.62 | AC14: 941.78 | AD14: 233.46 | AE14: 0 | AF14: 135.13 | AG14: 61.28 | AH14: 132.115 | AI14: 53.53
A15: FIN-0014 | B15: CUST-1413 | C15: 2022-Q3 | D15: WorkHub Pro | E15: Cold Outreach | F15: Pessimistic | G15: 5575.79 | H15: 66909.48 | I15: 573.34 | J15: 159823.55 | K15: 278.76 | L15: 8.57 | M15: 1555.84 | N15: 0 | O15: 603892.7 | P15: 10968489 | Q15: 18.2 | R15: 76.79 | S15: 29.03 | T15: 2022-11-09 | U15: 2022-12-17 | V15: 1355.08 | W15: 2385.37 | X15: 187.35 | Y15: 210.77 | Z15: 106.4 | AA15: 181.11 | AB15: 180.01 | AC15: 46.45 | AD15: 1654.07 | AE15: 218 | AF15: 103.96 | AG15: 132.23 | AH15: 23.845 | AI15: 6.92
A16: FIN-0015 | B16: CUST-0822 | C16: 2023-Q3 | D16: API Access | E16: Product-Led Signup | F16: Base | G16: 4437.82 | H16: 53253.84 | I16: 112.75 | J16: 102641.61 | K16: 910.35 | L16: 11.71 | M16: 0 | N16: 0 | O16: 779065.88 | P16: 20163204 | Q16: 25.9 | R16: 58.48 | S16: -34.46 | T16: 2023-03-02 | U16: 2023-05-09 | V16: 2705.72 | W16: 1010.99 | X16: 786.77 | Y16: 1112.29 | Z16: 33.2 | AA16: 176.77 | AB16: 250.77 | AC16: 1304.19 | AD16: 279.69 | AE16: 381.42 | AF16: 797.56 | AG16: 205.43 | AH16: 28.185 | AI16: 77.68
A17: FIN-0016 | B17: CUST-0940 | C17: 2023-Q1 | D17: Analytics Add-on | E17: Partner Referral | F17: Base | G17: 1815.61 | H17: 21787.32 | I17: 364.56 | J17: 44794.74 | K17: 122.87 | L17: 3.93 | M17: 468.76 | N17: 0 | O17: 197096.07 | P17: 702560.57 | R17: 76.72 | S17: 42.55 | T17: 2024-02-27 | U17: 2024-04-23 | V17: 2613.32 | W17: 3456.92 | X17: 855.92 | Y17: 1190.6 | Z17: 512.91 | AA17: 605.57 | AB17: 56.53 | AC17: 1211.79 | AD17: 2725.62 | AE17: 450.57 | AF17: 875.87 | AG17: 274.28 | AH17: 400.615 | AI17: 116.56
A18: FIN-0017 | B18: CUST-1432 | C18: 2025-Q1 | D18: API Access | E18: Partner Referral | F18: Base | G18: 5321.82 | H18: 63861.84 | I18: 495.6 | J18: 120485.97 | K18: -243.11 | L18: 5.41 | M18: 742.93 | N18: 0 | O18: 591929.99 | P18: 5921593.8 | Q18: 10 | R18: 72.38 | S18: 7.52 | T18: 2024-06-05 | U18: 2024-07-28 | V18: 669.28 | W18: 1386.45 | X18: 97.17 | Y18: 308.37 | Z18: 455.35 | AA18: 400.3 | AB18: 115.02 | AC18: 732.25 | AD18: 655.15 | AE18: 308.18 | AF18: 6.36 | AG18: 216.72 | AH18: 195.345 | AI18: 58.07
A19: FIN-0018 | B19: CUST-1414 | C19: 2023-Q4 | D19: Analytics Add-on | E19: Partner Referral | F19: Base | G19: 4988.93 | H19: 59867.16 | I19: 427.31 | J19: 144029.93 | K19: 337.06 | L19: 32.88 | M19: 1533.1 | N19: 0 | O19: 308799.03 | P19: 19720929 | Q19: 63.9 | R19: 72.44 | S19: -2.18 | T19: 2022-02-17 | U19: 2022-05-01 | V19: 3621.26 | W19: 930.46 | X19: 94.66 | Y19: 109.29 | Z19: 35.33 | AA19: 50.79 | AB19: 444.46 | AC19: 2219.73 | AD19: 199.16 | AE19: 310.69 | AF19: 205.44 | AG19: 203.3 | AH19: 154.165 | AI19: 271.37
A20: FIN-0019 | B20: CUST-1014 | C20: 2022-Q2 | D20: WorkHub Enterprise | E20: Inbound Organic | F20: Base | G20: 9541.85 | H20: 114502.2 | I20: 159.32 | J20: 132143.04 | L20: 3.37 | M20: 0 | N20: 0 | O20: 284518.26 | P20: 14629896 | Q20: 51.4 | R20: 72 | S20: 34.84 | T20: 2022-10-15 | U20: 2022-12-17 | V20: 1941.74 | W20: 456.66 | X20: 15.01 | Y20: 318.04 | Z20: 333.54 | AA20: 202.29 | AB20: 29.82 | AC20: 540.21 | AD20: 274.64 | AE20: 390.34 | AF20: 3.31 | AG20: 94.91 | AH20: 2.665 | AI20: 143.27
A21: FIN-0020 | B21: CUST-1426 | C21: 2022-Q4 | D21: API Access | E21: Partner Referral | F21: Optimistic | G21: 9053.25 | H21: 108639 | I21: 583.37 | J21: 218704.05 | K21: 374.9 | L21: 9.28 | M21: 713.19 | N21: 0 | O21: 289950.19 | P21: 16675600 | Q21: 57.5 | R21: 67.19 | S21: -5.04 | T21: 2023-12-10 | U21: 15/02/2024 | V21: 2069.57 | W21: 927.14 | X21: 735.12 | Y21: 303.33 | Z21: 887.14 | AA21: 570.27 | AB21: 646.91 | AC21: 668.04 | AD21: 195.84 | AE21: 329.77 | AF21: 11.4 | AG21: 648.51 | AH21: 365.315 | AI21: 473.82
A22: FIN-0021 | B22: CUST-0368 | C22: 2023-Q1 | D22: Analytics Add-on | E22: Paid Search | F22: Optimistic | G22: 8211.66 | H22: 98539.92 | I22: 540.05 | J22: 119403.83 | K22: 221.1 | L22: 3.77 | M22: 1514.7 | N22: 0 | O22: 768244.55 | P22: 23659607 | Q22: 30.8 | R22: 78.31 | S22: -22.92 | T22: 2024-05-25 | U22: 27/07/2024 | V22: 722.36 | W22: 178.31 | X22: 246.06 | Y22: 434.55 | Z22: 87.21 | AA22: 135.94 | AB22: 470.65 | AC22: 679.17 | AD22: 552.99 | AE22: 159.29 | AF22: 119.82 | AG22: 151.42 | AH22: 69.015 | AI22: 297.56
A23: FIN-0022 | B23: CUST-0411 | C23: 2022-Q3 | D23: WorkHub Core | E23: Cold Outreach | F23: Pessimistic | G23: 16864.1 | H23: 202369.2 | I23: 677.02 | J23: 423679.28 | K23: 625.8 | L23: 5.76 | M23: 4877.79 | N23: 0 | O23: 664242.58 | P23: 1828201 | Q23: 2.8 | R23: 74.58 | S23: 20.36 | T23: 2023-09-09 | U23: 2023-11-09 | V23: 1205.92 | W23: 2179.79 | X23: 1252 | Y23: 103.34 | Z23: 273.92 | AA23: 271.95 | AB23: 504.66 | AC23: 195.61 | AD23: 1448.49 | AE23: 846.65 | AF23: 211.39 | AG23: 35.29 | AH23: 66.995 | AI23: 331.57
A24: FIN-0023 | B24: CUST-0201 | C24: 2023-Q2 | D24: WorkHub Core | E24: Product-Led Signup | F24: Optimistic | G24: 17629.52 | H24: 211554.24 | I24: 139.08 | J24: 538105.58 | K24: 3869.04 | L24: 1.82 | M24: 454.05 | N24: 1744.64 | O24: 687265.01 | P24: 8302248.3 | R24: 66.37 | S24: 6.64 | T24: 2022-11-05 | U24: 2023-01-19 | V24: 1961.63 | W24: 408.17 | X24: 244.55 | Y24: 120.05 | Z24: 128.83 | AA24: 18.03 | AB24: 119.83 | AC24: 560.1 | AD24: 323.13 | AE24: 160.8 | AF24: 194.68 | AG24: 109.8 | AH24: 186.925 | AI24: 53.26
A25: FIN-0024 | B25: CUST-1319 | C25: 2022-Q3 | D25: Analytics Add-on | E25: Webinar | F25: Base | G25: 1882.93 | H25: 22595.16 | I25: 535.76 | J25: 41940.12 | K25: 78.28 | L25: 2.16 | M25: 0 | N25: 0 | O25: 463287.36 | P25: 22007196 | Q25: 47.5 | R25: 57.06 | S25: -12.03 | T25: 2022-02-18 | U25: 14/05/2022 | V25: 64.01 | W25: 40.85 | X25: 308.59 | Y25: 1063.31 | Z25: 95.6 | AA25: 220.5 | AB25: 154.83 | AC25: 1337.52 | AD25: 690.45 | AE25: 96.76 | AF25: 748.58 | AG25: 143.03 | AH25: 15.545 | AI25: 18.26
A26: FIN-0025 | B26: CUST-0330 | C26: 2024-Q4 | D26: WorkHub Core | E26: Inbound Organic | F26: Pessimistic | G26: 12258.83 | H26: 147105.96 | I26: 180.1 | J26: 298919.48 | K26: 1659.74 | L26: 5.25 | M26: 3037.24 | N26: 0 | O26: 922575.87 | P26: 21497432 | Q26: 23.3 | R26: 62.79 | S26: 19.47 | T26: 2024-06-30 | U26: 2024-08-27 | V26: 2221.5 | W26: 317.34 | X26: 384.85 | Y26: 215.99 | Z26: 1122.76 | AA26: 174.72 | AB26: 2.52 | AC26: 819.97 | AD26: 413.96 | AE26: 20.5 | AF26: 98.74 | AG26: 884.13 | AH26: 30.235 | AI26: 170.57
A27: FIN-0026 | B27: CUST-1492 | C27: 2022-Q1 | D27: API Access | E27: Product-Led Signup | F27: Pessimistic | G27: 16803.09 | H27: 201637.08 | I27: 101.92 | J27: 248980.83 | L27: 2 | M27: 751.33 | N27: 2509.24 | O27: 459579.31 | P27: 1064102.4 | Q27: 2.3 | R27: 61.7 | S27: -4.75 | T27: 2024-05-20 | U27: 2024-07-31 | V27: 1581.08 | W27: 2219.54 | X27: 1656.87 | Y27: 208.68 | Z27: 418.84 | AA27: 49.18 | AB27: 203.43 | AC27: 179.55 | AD27: 1488.24 | AE27: 1251.52 | AF27: 106.05 | AG27: 180.21 | AH27: 155.775 | AI27: 30.34
A28: FIN-0027 | B28: CUST-0752 | C28: 2022-Q1 | D28: API Access | E28: LinkedIn Ads | F28: Optimistic | G28: 11131.3 | H28: 133575.6 | I28: 1160.55 | J28: 104589.11 | K28: 90.12 | L28: 3.14 | M28: 1311.78 | N28: 657.22 | O28: 183782.27 | P28: 8069544.9 | Q28: 43.9 | R28: 77.76 | S28: 37.11 | T28: 2022-04-27 | U28: 2022-06-06 | V28: 1431.68 | W28: 376.63 | X28: 144.04 | Y28: 780.51 | Z28: 116.17 | AA28: 88.85 | AB28: 595.96 | AC28: 30.15 | AD28: 354.67 | AE28: 261.31 | AF28: 465.78 | AG28: 122.46 | AH28: 116.105 | AI28: 422.87
A29: FIN-0028 | B29: CUST-1077 | C29: 2024-Q3 | D29: WorkHub Core | E29: Paid Search | F29: Optimistic | G29: 9015.44 | H29: 108185.28 | I29: 966.12 | J29: 278171.77 | K29: 287.93 | L29: 1.83 | M29: 0 | N29: 1739.96 | O29: 776905.7 | P29: 1686770.2 | Q29: 2.2 | R29: 73.33 | S29: 17.78 | T29: 2023-02-16 | U29: 2023-04-30 | V29: 213.78 | W29: 821.85 | X29: 17.74 | Y29: 26.28 | Z29: 211.26 | AA29: 203.7 | AB29: 186.11 | AC29: 1187.75 | AD29: 90.55 | AE29: 387.61 | AF29: 288.45 | AG29: 27.37 | AH29: 1.255 | AI29: 13.02
A30: FIN-0029 | B30: CUST-1447 | C30: 2024-Q2 | D30: WorkHub Enterprise | E30: LinkedIn Ads | F30: Pessimistic | G30: 5412.71 | H30: 64952.52 | I30: 985.9 | J30: 55996.67 | K30: 56.8 | L30: 7.41 | M30: 664.22 | N30: 0 | O30: 265177.25 | P30: 10241995 | Q30: 38.6 | R30: 58.44 | S30: 58.61 | T30: 2022-11-26 | U30: 2023-01-14 | V30: 1559.15 | W30: 834.28 | X30: 82.54 | Y30: 655.98 | Z30: 176.42 | AA30: 101.09 | AB30: 600.21 | AC30: 157.62 | AD30: 102.98 | AE30: 322.81 | AF30: 341.25 | AG30: 62.21 | AH30: 103.865 | AI30: 427.12
A31: FIN-0030 | B31: CUST-1431 | C31: 2022-Q3 | D31: Analytics Add-on | E31: Webinar | F31: Pessimistic | G31: 17945.13 | H31: 215341.56 | I31: 406.14 | J31: 604905.19 | K31: 1489.4 | L31: 4.62 | M31: 0 | N31: 0 | O31: 659760.04 | P31: 12425999 | Q31: 18.8 | R31: 77.13 | S31: -10.64 | T31: 2022-07-26 | U31: 2022-10-07 | V31: 2572.82 | W31: 1088.2 | X31: 212.09 | Y31: 574.79 | Z31: 688.68 | AA31: 525.42 | AB31: 308.85 | AC31: 1171.29 | AD31: 356.9 | AE31: 193.26 | AF31: 260.06 | AG31: 450.05 | AH31: 320.465 | AI31: 135.76
A32: FIN-0031 | B32: CUST-1407 | C32: 2022-Q1 | D32: WorkHub Core | E32: Partner Referral | F32: Base | G32: 14311.18 | H32: 171734.16 | I32: 611.2 | J32: 223610.52 | K32: 365.85 | L32: 9.86 | M32: 0 | N32: 1748.14 | O32: 793865.09 | P32: 3039146.9 | Q32: 3.8 | R32: 59.82 | S32: 54.26 | T32: 2022-11-11 | U32: 2022-12-28 | V32: 1345.55 | W32: 1492.18 | X32: 1272.07 | Y32: 384.35 | Z32: 255.68 | AA32: 569.39 | AB32: 655.44 | AC32: 55.98 | AD32: 760.88 | AE32: 866.72 | AF32: 69.62 | AG32: 17.05 | AH32: 364.435 | AI32: 482.35
A33: FIN-0032 | B33: CUST-1121 | C33: 2022-Q4 | D33: WorkHub Pro | E33: Product-Led Signup | F33: Optimistic | G33: 17491.21 | H33: 209894.52 | I33: 111.94 | J33: 253499.86 | K33: 2264.6 | L33: 6.35 | M33: 825.73 | N33: 0 | O33: 836855.78 | P33: 9340990.8 | Q33: 11.2 | R33: 63.15 | S33: -24.96 | T33: 02/07/2024 | U33: 2024-09-13 | V33: 721.9 | W33: 732.02 | X33: 329.23 | Y33: 421.02 | Z33: 232.46 | AA33: 118.96 | AB33: 139.51 | AC33: 679.63 | AD33: 0.72 | AE33: 76.12 | AF33: 106.29 | AG33: 6.17 | AH33: 85.995 | AI33: 33.58
A34: FIN-0033 | B34: CUST-1371 | C34: 2022-Q3 | D34: Analytics Add-on | E34: Product-Led Signup | F34: Base | G34: 5494.88 | H34: 65938.56 | I34: 102.59 | J34: 107679.71 | K34: 1049.61 | L34: 4.58 | M34: 0 | N34: 0 | O34: 508599.64 | P34: 12598498 | Q34: 24.8 | R34: 71.94 | S34: 154.57 | T34: 2023-10-31 | U34: 2024-01-07 | V34: 2984.77 | W34: 93.48 | X34: 586.63 | Y34: 31.37 | Z34: 203.95 | AA34: 274 | AB34: 6.17 | AC34: 1583.24 | AD34: 637.82 | AE34: 181.28 | AF34: 283.36 | AG34: 34.68 | AH34: 69.045 | AI34: 166.92
A35: FIN-0034 | B35: CUST-1438 | C35: 2022-Q1 | D35: Analytics Add-on | E35: Cold Outreach | F35: Optimistic | G35: 10560.95 | H35: 126731.4 | I35: 700.59 | J35: 70994.18 | K35: 101.33 | L35: 11.7 | M35: 1265.04 | N35: 1431.23 | O35: 720930.67 | P35: 6840180.1 | Q35: 9.5 | R35: 74.37 | S35: 28.28 | T35: 2023-02-23 | U35: 2023-05-23 | V35: 3188.62 | W35: 597.14 | X35: 100.2 | Y35: 220.85 | Z35: 122.69 | AA35: 89.22 | AB35: 11.74 | AC35: 1787.09 | AD35: 134.16 | AE35: 305.15 | AF35: 93.88 | AG35: 115.94 | AH35: 115.735 | AI35: 161.35
A36: FIN-0035 | B36: CUST-0408 | C36: 2022-Q4 | D36: WorkHub Pro | E36: Partner Referral | F36: Pessimistic | G36: 4372.29 | H36: 52467.48 | I36: 308.95 | J36: 84234.29 | K36: 272.65 | L36: 6.39 | M36: 1156.21 | N36: 328.4 | O36: 936320.17 | P36: 17318191 | Q36: 18.5 | R36: -40.13 | S36: -38.5 | T36: 2022-12-15 | U36: 2023-01-28 | V36: 794.88 | W36: 1863.85 | X36: 192.32 | Y36: 164 | Z36: 583.53 | AA36: 450.46 | AB36: 224.89 | AC36: 606.65 | AD36: 1132.55 | AE36: 213.03 | AF36: 150.73 | AG36: 344.9 | AH36: 245.505 | AI36: 51.8
A37: FIN-0036 | B37: CUST-0203 | C37: 2023-Q2 | D37: WorkHub Core | E37: Webinar | F37: Pessimistic | G37: 729.49 | H37: 8753.88 | I37: 353.03 | J37: 16286.84 | K37: 46.13 | L37: 2.42 | M37: 66.16 | N37: 0 | O37: 281667.75 | P37: 20032956 | Q37: 71.1 | R37: 55.46 | S37: -27.16 | T37: 2024-03-27 | U37: 2024-06-13 | V37: 2561.83 | W37: 216.82 | X37: 468.82 | Y37: 22.76 | Z37: 145.81 | AA37: 62.97 | AB37: 87.02 | AC37: 1160.3 | AD37: 514.48 | AE37: 63.47 | AF37: 291.97 | AG37: 92.82 | AH37: 141.985 | AI37: 86.07
A38: FIN-0037 | B38: CUST-0238 | C38: 2024-Q4 | D38: Analytics Add-on | E38: LinkedIn Ads | F38: Base | G38: 11972.67 | H38: 143672.04 | I38: 1180.66 | J38: 293204.98 | K38: 248.34 | L38: 9.39 | M38: 4159.69 | N38: 1455.97 | O38: 798837 | P38: 16114380 | Q38: 20.2 | R38: 70.99 | S38: -35.13 | T38: 2023-08-17 | U38: 2023-11-03 | V38: 250.57 | W38: 31.6 | X38: 481.65 | Y38: 867.91 | Z38: 248.31 | AA38: 339.92 | AB38: 133.77 | AC38: 1150.96 | AD38: 699.7 | AE38: 76.3 | AF38: 553.18 | AG38: 9.68 | AH38: 134.965 | AI38: 39.32
A39: FIN-0038 | B39: CUST-0516 | C39: 2024-Q3 | D39: Analytics Add-on | E39: Inbound Organic | F39: Optimistic | G39: 6101.88 | H39: 73222.56 | I39: 214.34 | J39: 126571.64 | K39: 590.52 | L39: 37.91 | M39: 1028.87 | N39: 0 | O39: 813563.56 | P39: 24046614 | Q39: 29.6 | R39: 63.13 | S39: 5.88 | T39: 2024-04-03 | U39: 2024-07-01 | V39: 1318.84 | W39: 241.38 | X39: 347.23 | Y39: 246.68 | Z39: 207.06 | AA39: 245.5 | AB39: 195.9 | AC39: 82.69 | AD39: 489.92 | AE39: 58.12 | AF39: 68.05 | AG39: 31.57 | AH39: 40.545 | AI39: 22.81
... A60: FIN-0059 | B60: CUST-1175 | C60: 2022-Q1 | D60: WorkHub Pro | E60: Partner Referral | F60: Optimistic | G60: 15950.82 | H60: 191409.84 | I60: 579.47 | J60: 346330.69 | K60: 597.67 | L60: 9.62 | M60: 0 | N60: 0 | O60: 384769.33 | P60: 19367813 | Q60: 50.3 | R60: 57.91 | S60: 17.18 | T60: 2023-10-11 | U60: 2023-11-23 | V60: 3025.07 | W60: 7.48 | X60: 620.4 | Y60: 1229.18 | Z60: 719.15 | AA60: 748.56 | AB60: 484.23 | AC60: 1623.54 | AD60: 723.82 | AE60: 215.05 | AF60: 914.45 | AG60: 480.52 | AH60: 543.605 | AI60: 311.14
A61: FIN-0060 | B61: CUST-0045 | C61: 2023-Q1 | D61: WorkHub Pro | E61: Partner Referral | F61: Optimistic | G61: 6316.38 | H61: 75796.56 | I61: 622.38 | J61: 128524.53 | K61: 206.5 | L61: 9.33 | M61: 1279.77 | N61: 0 | O61: 416881.36 | P61: 20365790 | R61: 55.17 | S61: -25.89 | T61: 2023-06-08 | U61: 2023-08-20 | V61: 2443.24 | W61: 777.23 | X61: 554.12 | Y61: 90.61 | Z61: 597.51 | AA61: 68.27 | AB61: 15.87 | AC61: 1041.71 | AD61: 45.93 | AE61: 148.77 | AF61: 224.12 | AG61: 358.88 | AH61: 136.685 | AI61: 157.22
A62: FIN-0061 | B62: CUST-1443 | C62: 2022-Q3 | D62: Analytics Add-on | E62: Paid Search | F62: Pessimistic | G62: 7623.87 | H62: 91486.44 | I62: 989.1 | J62: 104129.55 | K62: 105.28 | L62: 3.46 | M62: 0 | N62: 1803.63 | O62: 916280.04 | P62: 14882874 | Q62: 16.2 | R62: 60.21 | S62: 35.37 | T62: 09/10/2022 | U62: 2022-11-12 | V62: 2226.36 | W62: 1260.86 | X62: 128.82 | Y62: 3.7 | Z62: 753.14 | AA62: 243.66 | AB62: 243.76 | AC62: 824.83 | AD62: 529.56 | AE62: 276.53 | AF62: 311.03 | AG62: 514.51 | AH62: 38.705 | AI62: 70.67
A63: FIN-0062 | B63: CUST-1354 | C63: 2023-Q4 | D63: Analytics Add-on | E63: Partner Referral | F63: Optimistic | G63: 100.29 | H63: 1203.48 | I63: 378.92 | J63: 804.81 | K63: 2.12 | L63: 2.15 | M63: 1.35 | N63: 0 | O63: 761166.59 | P63: 17460711 | Q63: 22.9 | R63: 75.86 | S63: 6.27 | T63: 2022-06-22 | U63: 2022-09-14 | V63: 2569.1 | W63: 73.74 | X63: 203.23 | Y63: 458.11 | Z63: 185.3 | AA63: 157.89 | AB63: 106.73 | AC63: 1167.57 | AD63: 657.56 | AE63: 202.12 | AF63: 143.38 | AG63: 53.33 | AH63: 47.065 | AI63: 66.36
A64: FIN-0063 | B64: CUST-0310 | C64: 2023-Q4 | D64: API Access | E64: Cold Outreach | F64: Base | G64: 15928.15 | H64: 191137.8 | I64: 413.32 | J64: 210208.05 | K64: 508.58 | L64: 3.91 | M64: 0 | N64: 0 | O64: 500414.3 | P64: 2751193.9 | Q64: 5.5 | R64: 60.47 | S64: -6.4 | T64: 2022-04-13 | U64: 2022-06-26 | V64: 3605.71 | W64: 136.08 | X64: 378.48 | Y64: 387.9 | Z64: 224.59 | AA64: 291.77 | AB64: 56.69 | AC64: 2204.18 | AD64: 595.22 | AE64: 26.87 | AF64: 73.17 | AG64: 14.04 | AH64: 86.815 | AI64: 116.4
A65: FIN-0064 | B65: CUST-0677 | C65: 2025-Q1 | D65: Analytics Add-on | E65: Inbound Organic | F65: Optimistic | G65: 10766.16 | H65: 129193.92 | I65: 275.42 | J65: 401667.94 | K65: 1458.38 | L65: 10.55 | M65: 2217.33 | N65: 770.93 | O65: 431105.91 | P65: 11290384 | Q65: 26.2 | R65: 78.69 | S65: -30.54 | T65: 2022-02-08 | U65: 2022-04-17 | V65: 1480.03 | W65: 1405.09 | X65: 505.24 | Y65: 509.69 | Z65: 447.51 | AA65: 522.69 | AB65: 142.24 | AC65: 78.5 | AD65: 673.79 | AE65: 99.89 | AF65: 194.96 | AG65: 208.88 | AH65: 317.735 | AI65: 30.85
A66: FIN-0065 | B66: CUST-0071 | C66: 2024-Q2 | D66: Analytics Add-on | E66: Webinar | F66: Base | G66: 14463.02 | H66: 173556.24 | I66: 380.05 | J66: 377574.96 | K66: 993.49 | L66: 2.5 | M66: 631.6 | N66: 0 | O66: 340062.29 | P66: 10748797 | Q66: 31.6 | R66: 68.09 | S66: 46.75 | T66: 2023-09-07 | U66: 2023-10-30 | V66: 317.3 | W66: 929.87 | X66: 204.91 | Y66: 451.04 | Z66: 100.96 | AA66: 398.52 | AB66: 155.47 | AC66: 1084.23 | AD66: 198.57 | AE66: 200.44 | AF66: 136.31 | AG66: 137.67 | AH66: 193.565 | AI66: 17.62
A67: FIN-0066 | B67: CUST-1379 | C67: 2023-Q1 | D67: WorkHub Enterprise | E67: Partner Referral | F67: Base | G67: 3111.89 | H67: 37342.68 | I67: 383.05 | J67: 41632.73 | K67: 108.69 | L67: 11.12 | M67: 0 | N67: 98.11 | O67: 200618.37 | P67: 3588329.5 | Q67: 17.9 | R67: 78.52 | S67: 32.19 | T67: 2024-10-03 | U67: 2024-12-13 | V67: 610.18 | W67: 819.79 | X67: 104.62 | Y67: 132.6 | Z67: 801.94 | AA67: 268.45 | AB67: 46.44 | AC67: 791.35 | AD67: 88.49 | AE67: 300.73 | AF67: 182.13 | AG67: 563.31 | AH67: 63.495 | AI67: 126.65
A68: FIN-0067 | B68: CUST-0581 | C68: 2023-Q3 | D68: WorkHub Pro | E68: Partner Referral | F68: Base | G68: 17375.87 | H68: 208510.44 | I68: 599.22 | J68: 84446.65 | K68: 140.93 | L68: 9.92 | M68: 5585.73 | N68: 0 | O68: 235351.39 | P68: 13545434 | Q68: 57.6 | R68: 57.13 | S68: 38.71 | T68: 2023-05-02 | U68: 2023-08-02 | V68: 947.29 | W68: 855.06 | X68: 587.66 | Y68: 1265.97 | Z68: 230.17 | AA68: 119.6 | AB68: 109.62 | AC68: 454.24 | AD68: 123.76 | AE68: 182.31 | AF68: 951.24 | AG68: 8.46 | AH68: 85.355 | AI68: 63.47
A69: FIN-0068 | B69: CUST-0159 | C69: 2024-Q1 | D69: WorkHub Core | E69: Product-Led Signup | F69: Pessimistic | G69: 7569.88 | H69: 90838.56 | I69: 121.64 | J69: 274650.31 | K69: -2257.89 | L69: 7.15 | M69: 939.69 | N69: 0 | O69: 606190.35 | P69: 10481635 | Q69: 17.3 | R69: 75.87 | S69: 46.96 | T69: 2023-01-06 | U69: 2023-03-03 | V69: 3530.16 | W69: 272.78 | X69: 933.96 | Y69: 248.35 | Z69: 43.02 | AA69: 295.09 | AB69: 214.25 | AC69: 2128.63 | AD69: 458.52 | AE69: 528.61 | AF69: 66.38 | AG69: 195.61 | AH69: 90.135 | AI69: 41.16
A70: FIN-0069 | B70: CUST-1128 | C70: 2025-Q1 | D70: WorkHub Enterprise | E70: Inbound Organic | F70: Base | G70: 745.13 | H70: 8941.56 | I70: 173.18 | J70: 7980.27 | K70: 46.08 | L70: 0.56 | M70: 99.79 | N70: 0 | O70: 478639.57 | P70: 16885593 | Q70: 35.3 | R70: 72.09 | S70: 55.03 | T70: 2024-02-26 | U70: 2024-05-25 | V70: 1174.79 | W70: 515.52 | X70: 641.65 | Y70: 324.29 | Z70: 367.09 | AA70: 209.45 | AB70: 62.08 | AC70: 226.74 | AD70: 215.78 | AE70: 236.3 | AF70: 9.56 | AG70: 128.46 | AH70: 4.495 | AI70: 111.01
A71: FIN-0070 | B71: CUST-0560 | C71: 2025-Q1 | D71: Analytics Add-on | E71: Paid Search | F71: Base | G71: 16952.11 | H71: 203425.32 | I71: 828.13 | J71: 187279.61 | K71: 226.15 | L71: 8.32 | M71: 0 | N71: 0 | O71: 393155.84 | P71: 24810069 | Q71: 63.1 | R71: 79.69 | S71: 47.72 | T71: 2023-01-16 | U71: 2023-02-15 | V71: 1641.34 | W71: 1583.3 | X71: 204.74 | Y71: 192.2 | Z71: 171.59 | AA71: 3.25 | AB71: 350.26 | AC71: 239.81 | AD71: 852 | AE71: 200.61 | AF71: 122.53 | AG71: 67.04 | AH71: 201.705 | AI71: 177.17
A72: FIN-0071 | B72: CUST-0897 | C72: 2025-Q1 | D72: WorkHub Enterprise | E72: LinkedIn Ads | F72: Pessimistic | G72: 3449.73 | H72: 41396.76 | I72: 988.97 | J72: 48802.88 | K72: 49.35 | L72: 1.78 | M72: 931.18 | N72: 0 | O72: 886673.36 | P72: 3322239.9 | Q72: 3.7 | R72: 74.17 | S72: 26.23 | T72: 2023-03-25 | U72: 2023-06-12 | V72: 2010.64 | W72: 1031.4 | X72: 1.49 | Y72: 574.6 | Z72: 110.85 | AA72: 157.77 | AB72: 103.39 | AC72: 609.11 | AD72: 300.1 | AE72: 403.86 | AF72: 259.87 | AG72: 127.78 | AH72: 47.185 | AI72: 69.7
A73: FIN-0072 | B73: CUST-1342 | C73: 2022-Q3 | D73: Analytics Add-on | E73: Product-Led Signup | F73: Optimistic | G73: 12280.96 | H73: 147371.52 | I73: 117.79 | J73: 242249.93 | K73: 2056.63 | L73: 0.57 | M73: 3355.62 | N73: 0 | O73: 461000.37 | P73: 10101941 | Q73: 21.9 | R73: 61.86 | S73: -21 | T73: 2023-12-12 | U73: 2024-02-08 | V73: 72.96 | W73: 2099.17 | X73: 799.67 | Y73: 196.12 | Z73: 147.17 | AA73: 935.52 | AB73: 246.1 | AC73: 1328.57 | AD73: 1367.87 | AE73: 394.32 | AF73: 118.61 | AG73: 91.46 | AH73: 730.565 | AI73: 73.01
... A76: FIN-0075 | B76: CUST-1039 | C76: 2022-Q1 | D76: Analytics Add-on | E76: Inbound Organic | F76: Base | G76: 3512.92 | H76: 42155.04 | I76: 267.36 | J76: 103012.52 | K76: 385.3 | L76: 4.92 | M76: 0 | N76: 0 | O76: 463483.3 | P76: 23373309 | Q76: 50.4 | R76: 61.75 | S76: -24.37 | T76: 2022-04-16 | U76: 21/05/2022 | V76: 2834.2 | W76: 725.47 | X76: 156.09 | Y76: 752.27 | Z76: 230.92 | AA76: 20.79 | AB76: 94.42 | AC76: 1432.67 | AD76: 5.83 | AE76: 249.26 | AF76: 437.54 | AG76: 7.71 | AH76: 184.165 | AI76: 78.67
A77: FIN-0076 | B77: CUST-0870 | C77: 2022-Q4 | D77: API Access | E77: LinkedIn Ads | F77: Base | G77: 16349.63 | H77: 196195.56 | I77: 761.55 | J77: 246732.84 | K77: 323.99 | L77: 10.05 | M77: 4117.2 | N77: 0 | O77: 560913.11 | P77: 18323089 | R77: 72.66 | S77: 49.3 | T77: 2024-07-12 | U77: 2024-08-15 | V77: 985.45 | W77: 1549.91 | X77: 1239.36 | Y77: 419.92 | Z77: 534.04 | AA77: 170.61 | AB77: 398.39 | AC77: 416.08 | AD77: 818.61 | AE77: 834.01 | AF77: 105.19 | AG77: 295.41 | AH77: 34.345 | AI77: 225.3
A78: FIN-0077 | B78: CUST-1384 | C78: 2022-Q2 | D78: Analytics Add-on | E78: Product-Led Signup | F78: Optimistic | G78: 991.62 | H78: 11899.44 | I78: 73.68 | J78: 11908.06 | K78: 161.62 | L78: 3.56 | M78: 96.43 | N78: 216.32 | O78: 664239.21 | P78: 14397452 | R78: 56.4 | S78: 6.6 | T78: 2023-05-27 | U78: 2023-08-04 | V78: 464.32 | W78: 924.1 | X78: 56.53 | Y78: 362.74 | Z78: 19.54 | AA78: 158.81 | AB78: 142.08 | AC78: 937.21 | AD78: 192.8 | AE78: 348.82 | AF78: 48.01 | AG78: 219.09 | AH78: 46.145 | AI78: 31.01
A79: FIN-0078 | B79: CUST-0962 | C79: 2023-Q1 | D79: WorkHub Core | E79: Partner Referral | F79: Pessimistic | G79: 2679.78 | H79: 32157.36 | I79: 320.28 | J79: 57522.27 | K79: 179.6 | L79: 11.49 | M79: 203 | N79: 0 | O79: 831637.49 | P79: 23204502 | Q79: 27.9 | R79: 58.53 | S79: -36.69 | T79: 2022-03-26 | U79: 2022-05-26 | V79: 510.49 | W79: 1440.09 | X79: 559.75 | Y79: 258.79 | Z79: 238.63 | AA79: 81.45 | AB79: 294.15 | AC79: 891.04 | AD79: 708.79 | AE79: 154.4 | AF79: 55.94 | AG79: 0 | AH79: 123.505 | AI79: 121.06
A80: FIN-0079 | B80: CUST-0597 | C80: 2022-Q1 | D80: WorkHub Pro | E80: Webinar | F80: Optimistic | G80: 7462.59 | H80: 89551.08 | I80: 491.89 | J80: 199389.8 | K80: 405.35 | L80: 11.34 | M80: 615.05 | N80: 0 | O80: 312423.39 | P80: 18049081 | Q80: 57.8 | R80: 69.51 | S80: -35.19 | T80: 2024-03-27 | U80: 2024-06-19 | V80: 3513.45 | W80: 2314.55 | X80: 192.65 | Y80: 364.08 | Z80: 494.5 | AA80: 154.51 | AB80: 173.09 | AC80: 2111.92 | AD80: 1583.25 | AE80: 212.7 | AF80: 49.35 | AG80: 255.87 | AH80: 50.445 | AI80: 0
A81: FIN-0080 | B81: CUST-1347 | C81: 2023-Q1 | D81: WorkHub Core | E81: Webinar | F81: Pessimistic | G81: 4490.3 | H81: 53883.6 | I81: 522.19 | J81: 97833.56 | K81: 187.35 | L81: 1.95 | M81: 41.63 | N81: 921.72 | O81: 914676.41 | P81: 4765350 | Q81: 5.2 | R81: 65.85 | S81: 41.1 | T81: 2024-10-24 | U81: 2025-01-11 | V81: 460.72 | W81: 2215 | X81: 858.55 | Y81: 754.49 | Z81: 187.57 | AA81: 37.25 | AB81: 240.02 | AC81: 940.81 | AD81: 1483.7 | AE81: 453.2 | AF81: 439.76 | AG81: 51.06 | AH81: 167.705 | AI81: 66.93
A82: FIN-0081 | B82: CUST-1297 | C82: 2024-Q1 | D82: API Access | E82: Partner Referral | F82: Pessimistic | G82: 9262 | H82: 111144 | I82: 448.62 | J82: 94554.67 | K82: 210.77 | L82: 8.66 | M82: 2691.3 | N82: 0 | O82: 588782.75 | P82: 3803783.6 | Q82: 6.5 | R82: 80.35 | S82: 53.82 | T82: 2023-08-29 | U82: 2023-11-26 | V82: 6201.37 | W82: 655.48 | X82: 67.8 | Y82: 392.37 | Z82: 555.74 | AA82: 486.92 | AB82: 109.17 | AC82: 4799.84 | AD82: 75.82 | AE82: 337.55 | AF82: 77.64 | AG82: 317.11 | AH82: 281.965 | AI82: 63.92
A83: FIN-0082 | B83: CUST-0118 | C83: 2022-Q2 | D83: WorkHub Pro | E83: Cold Outreach | F83: Optimistic | G83: 16919.24 | H83: 203030.88 | I83: 389.58 | J83: 390537.46 | K83: 1002.46 | L83: 6.72 | M83: 0 | N83: 2412.99 | O83: 846743.85 | P83: 1877131.6 | Q83: 2.2 | R83: 78.67 | S83: -38.1 | T83: 2022-11-15 | U83: 2023-02-15 | V83: 432.59 | W83: 474.67 | X83: 355.13 | Y83: 624.51 | Z83: 340.47 | AA83: 253.63 | AB83: 94.68 | AC83: 968.94 | AD83: 256.63 | AE83: 50.22 | AF83: 309.78 | AG83: 101.84 | AH83: 48.675 | AI83: 78.41
A84: FIN-0083 | B84: CUST-1371 | C84: 2023-Q4 | D84: WorkHub Core | E84: Partner Referral | F84: Base | G84: 16399.46 | H84: 196793.52 | I84: 537.55 | J84: 597912.29 | K84: 1112.29 | L84: 10.18 | M84: 0 | N84: 112.5 | O84: 889181.04 | P84: 16323075 | Q84: 18.4 | R84: 76.74 | S84: 14.38 | T84: 2022-03-01 | U84: 2022-04-09 | V84: 1819.82 | W84: 390.03 | X84: 564.54 | Y84: 496.13 | Z84: 94.61 | AA84: 112.52 | AB84: 195.66 | AC84: 418.29 | AD84: 341.27 | AE84: 159.19 | AF84: 181.4 | AG84: 144.02 | AH84: 92.435 | AI84: 22.57
A85: FIN-0084 | B85: CUST-0001 | C85: 2023-Q3 | D85: API Access | E85: Inbound Organic | F85: Pessimistic | G85: 12811.03 | H85: 153732.36 | I85: 236.4 | J85: 147145.38 | K85: -622.44 | L85: 5.66 | M85: 1570.82 | N85: 0 | O85: 918365.71 | P85: 4187271.8 | Q85: 4.6 | R85: 76.22 | S85: 3.85 | T85: 2022-07-06 | U85: 2022-10-03 | V85: 2494.46 | W85: 1272.52 | X85: 596.77 | Y85: 423.51 | Z85: 481.74 | AA85: 426.51 | AB85: 106.02 | AC85: 1092.93 | AD85: 541.22 | AE85: 191.42 | AF85: 108.78 | AG85: 243.11 | AH85: 221.555 | AI85: 67.07
A86: FIN-0085 | B86: CUST-0807 | C86: 2023-Q4 | D86: Analytics Add-on | E86: Product-Led Signup | F86: Base | G86: 2063.49 | H86: 24761.88 | I86: 117.99 | J86: 54246.38 | K86: 459.75 | L86: 10.04 | M86: 0 | N86: 0 | O86: 611522.9 | P86: 16530641 | Q86: 27 | R86: 60.55 | S86: 48.99 | T86: 2022-07-12 | U86: 2022-08-27 | V86: 4932.49 | W86: 331.93 | X86: 1596.78 | Y86: 715.03 | Z86: 364.33 | AA86: 1037.96 | AB86: 382.01 | AC86: 3530.96 | AD86: 399.37 | AE86: 1191.43 | AF86: 400.3 | AG86: 125.7 | AH86: 833.005 | AI86: 208.92
A87: FIN-0086 | B87: CUST-0930 | C87: 2023-Q3 | D87: WorkHub Pro | E87: LinkedIn Ads | F87: Optimistic | G87: 15826.8 | H87: 189921.6 | I87: 680.76 | J87: 403914.94 | K87: 593.33 | L87: 11 | M87: 0 | N87: 0 | O87: 227549.08 | P87: 16347369 | Q87: 71.8 | R87: 62.52 | S87: 19.75 | T87: 2023-12-29 | U87: 2024-02-22 | V87: 1271.56 | W87: 1026.47 | X87: 595.69 | Y87: 33.33 | Z87: 584.77 | AA87: 160.36 | AB87: 179.65 | AC87: 129.97 | AD87: 295.17 | AE87: 190.34 | AF87: 281.4 | AG87: 346.14 | AH87: 44.595 | AI87: 6.56
A88: FIN-0087 | B88: CUST-0323 | C88: 2024-Q1 | D88: API Access | E88: LinkedIn Ads | F88: Base | G88: 1994.4 | H88: 23932.8 | I88: 1170.59 | J88: 60675.49 | K88: 51.83 | L88: 3.7 | M88: 0 | N88: 409.38 | O88: 204861.07 | P88: 4452841.5 | Q88: 21.7 | R88: 75.69 | S88: 154.08 | T88: 2023-01-05 | U88: 2023-04-03 | V88: 5199.1 | W88: 2254.83 | X88: 284.49 | Y88: 121.6 | Z88: 267.96 | AA88: 314.69 | AB88: 137.89 | AC88: 3797.57 | AD88: 1523.53 | AE88: 120.86 | AF88: 193.13 | AG88: 29.33 | AH88: 109.735 | AI88: 35.2
A89: FIN-0088 | B89: CUST-0984 | C89: 2023-Q4 | D89: API Access | E89: Webinar | F89: Base | G89: 14605.39 | H89: 175264.68 | I89: 366.01 | J89: 287964.19 | K89: 786.77 | L89: 9.99 | M89: 0 | N89: 0 | O89: 444967.58 | P89: 14556233 | R89: 56.96 | S89: 37.15 | T89: 2022-12-23 | U89: 2023-01-20 | V89: 347.11 | W89: 1013.4 | X89: 378.54 | Y89: 135.07 | Z89: 43.45 | AA89: 20.85 | AB89: 43.09 | AC89: 1054.42 | AD89: 282.1 | AE89: 26.81 | AF89: 179.66 | AG89: 195.18 | AH89: 184.105 | AI89: 130
A90: FIN-0089 | B90: CUST-0741 | C90: 2023-Q4 | D90: Analytics Add-on | E90: Inbound Organic | F90: Optimistic | G90: 6425.9 | H90: 77110.8 | I90: 127.87 | J90: 128673.3 | K90: 1006.28 | L90: 9.39 | M90: 0 | N90: 0 | O90: 372050.75 | P90: 13069524 | Q90: 35.1 | R90: 79.21 | S90: -1.97 | T90: 2024-11-04 | U90: 2025-01-27 | V90: 973.7 | W90: 649.65 | X90: 257.19 | Y90: 138.67 | Z90: 250.24 | AA90: 25.91 | AB90: 259.28 | AC90: 427.83 | AD90: 81.65 | AE90: 148.16 | AF90: 176.06 | AG90: 11.61 | AH90: 179.045 | AI90: 86.19
A91: FIN-0090 | B91: CUST-0240 | C91: 2022-Q1 | D91: WorkHub Enterprise | E91: Cold Outreach | F91: Base | G91: 12825.83 | H91: 153909.96 | I91: 425.32 | J91: 95224.62 | K91: 223.89 | L91: 5.9 | M91: 2167.99 | N91: 0 | O91: 416866.42 | P91: 10803841 | Q91: 25.9 | R91: 60.84 | S91: -33.9 | T91: 2023-06-13 | U91: 2023-07-14 | V91: 2538.13 | W91: 750.99 | X91: 538.91 | Y91: 566.56 | Z91: 8.46 | AA91: 271.23 | AB91: 186.8 | AC91: 1136.6 | AD91: 19.69 | AE91: 133.56 | AF91: 251.83 | AG91: 230.17 | AH91: 66.275 | AI91: 13.71
A92: FIN-0091 | B92: CUST-0932 | C92: 2024-Q4 | D92: WorkHub Core | E92: Inbound Organic | F92: Optimistic | G92: 12634.33 | H92: 151611.96 | I92: 159.98 | J92: 350091.15 | K92: 2188.34 | L92: 9.88 | M92: 0 | N92: 711.1 | O92: 463970.95 | P92: 23118572 | Q92: 49.8 | R92: 65.85 | S92: 30.95 | T92: 12/08/2022 | U92: 2022-10-13 | V92: 5109.84 | W92: 345.3 | X92: 333.98 | Y92: 112.32 | Z92: 119.69 | AA92: 773 | AB92: 367.16 | AC92: 3708.31 | AD92: 386 | AE92: 71.37 | AF92: 202.41 | AG92: 118.94 | AH92: 568.045 | AI92: 194.07
A93: FIN-0092 | B93: CUST-0746 | C93: 2023-Q4 | D93: Analytics Add-on | E93: LinkedIn Ads | F93: Pessimistic | G93: 5651.03 | H93: 67812.36 | I93: 1005.41 | J93: 153956.03 | K93: 153.13 | L93: 9.43 | M93: 0 | N93: 1109.22 | O93: 707719.25 | P93: 20599339 | Q93: 29.1 | R93: 74.67 | S93: 8.77 | T93: 2023-07-25 | U93: 2023-10-21 | V93: 1401.53 | W93: 191.47 | X93: 725.75 | Y93: 293.32 | Z93: 260.22 | AA93: 440.3 | AB93: 112 | AC93: 0 | AD93: 539.83 | AE93: 320.4 | AF93: 21.41 | AG93: 21.59 | AH93: 235.345 | AI93: 61.09
A94: FIN-0093 | B94: CUST-0230 | C94: 2023-Q1 | D94: WorkHub Pro | E94: LinkedIn Ads | F94: Base | G94: 15011.34 | H94: 180136.08 | I94: 1097.72 | J94: 362482.83 | K94: 330.21 | L94: 11.38 | M94: 0 | N94: 0 | O94: 719389.97 | P94: 11090226 | Q94: 15.4 | R94: 67.93 | S94: 24.77 | T94: 2024-06-23 | U94: 2024-07-25 | V94: 6200.18 | W94: 1427.69 | X94: 124.86 | Y94: 129.63 | Z94: 4.84 | AA94: 425.09 | AB94: 64.36 | AC94: 4798.65 | AD94: 696.39 | AE94: 280.49 | AF94: 185.1 | AG94: 233.79 | AH94: 220.135 | AI94: 108.73
A95: FIN-0094 | B95: CUST-0454 | C95: 2024-Q1 | D95: WorkHub Pro | E95: Cold Outreach | F95: Pessimistic | G95: 4800.94 | H95: 57611.28 | I95: 414.94 | J95: 173685.62 | K95: 418.58 | L95: 1.87 | M95: 1678.47 | N95: 1115.77 | O95: 299618.68 | P95: 1387736.9 | Q95: 4.6 | R95: 81.21 | S95: 31.02 | T95: 2023-11-27 | U95: 2024-01-02 | V95: 2976.68 | W95: 637.42 | X95: 146.65 | Y95: 1109.42 | Z95: 363.81 | AA95: 19.93 | AB95: 53.54 | AC95: 1575.15 | AD95: 93.88 | AE95: 258.7 | AF95: 794.69 | AG95: 125.18 | AH95: 185.025 | AI95: 119.55
A96: FIN-0095 | B96: CUST-0129 | C96: 2024-Q4 | D96: WorkHub Enterprise | E96: Product-Led Signup | F96: Pessimistic | G96: 1878.45 | H96: 22541.4 | I96: 122.41 | J96: 27040.53 | L96: 2.34 | M96: 0 | N96: 0 | O96: 813848.71 | P96: 23275247 | Q96: 28.6 | R96: 56.54 | S96: 3.7 | T96: 2022-08-30 | U96: 2022-11-02 | V96: 309.82 | W96: 970.47 | X96: 63.93 | Y96: 739.78 | Z96: 624.34 | AA96: 141.3 | AB96: 146.06 | AC96: 1091.71 | AD96: 239.17 | AE96: 341.42 | AF96: 425.05 | AG96: 385.71 | AH96: 63.655 | AI96: 27.03
A97: FIN-0096 | B97: CUST-0989 | C97: 2023-Q1 | D97: WorkHub Core | E97: LinkedIn Ads | F97: Pessimistic | G97: 7012.91 | H97: 84154.92 | I97: 639.33 | J97: 199918.18 | K97: 312.7 | L97: 5.21 | M97: 702.15 | N97: 274.73 | O97: 296416.21 | P97: 4680790.9 | Q97: 15.8 | R97: 79.65 | S97: 8.72 | T97: 2023-07-14 | U97: 2023-10-07 | V97: 3031.07 | W97: 2208.56 | X97: 515.09 | Y97: 698.42 | Z97: 145.81 | AA97: 246.56 | AB97: 64.75 | AC97: 1629.54 | AD97: 1477.26 | AE97: 109.74 | AF97: 383.69 | AG97: 92.82 | AH97: 41.605 | AI97: 108.34
A98: FIN-0097 | B98: CUST-0970 | C98: 2022-Q3 | D98: Analytics Add-on | E98: Webinar | F98: Base | G98: 9597.88 | H98: 115174.56 | I98: 357.32 | J98: 305836.22 | K98: 855.92 | L98: 11.08 | M98: 0 | N98: 0 | O98: 679989.23 | P98: 5829854.1 | Q98: 8.6 | R98: 80.02 | S98: 23.29 | T98: 2022-06-23 | U98: 2022-07-22 | V98: 676.09 | W98: 339.99 | X98: 607.36 | Y98: 255.08 | Z98: 736.05 | AA98: 74.85 | AB98: 74.95 | AC98: 725.44 | AD98: 391.31 | AE98: 202.01 | AF98: 59.65 | AG98: 497.42 | AH98: 130.105 | AI98: 98.14
A99: FIN-0098 | B99: CUST-0904 | C99: 2022-Q3 | D99: WorkHub Pro | E99: LinkedIn Ads | F99: Pessimistic | G99: 17012.15 | H99: 204145.8 | I99: 1200.29 | J99: 411837.49 | K99: 343.11 | L99: 9.53 | M99: 0 | N99: 744.26 | O99: 213743.43 | P99: 15861525 | Q99: 74.2 | R99: 66.08 | S99: 107.63 | T99: 2022-10-22 | U99: 2023-01-18 | V99: 4246.17 | W99: 2018.85 | X99: 1736.62 | Y99: 264.55 | Z99: 13.92 | AA99: 126.88 | AB99: 37.04 | AC99: 2844.64 | AD99: 1287.55 | AE99: 1331.27 | AF99: 50.18 | AG99: 224.71 | AH99: 78.075 | AI99: 136.05
A100: FIN-0099 | B100: CUST-0513 | C100: 2023-Q1 | D100: WorkHub Pro | E100: Product-Led Signup | F100: Pessimistic | G100: 8909.87 | H100: 106918.44 | I100: 111.65 | J100: 151295.15 | K100: 1355.08 | L100: 0.96 | M100: 0 | N100: 1940.78 | O100: 757310.47 | P100: 15514362 | Q100: 20.5 | R100: 55.41 | S100: 27.4 | T100: 2023-06-12 | U100: 26/07/2023 | V100: 840.13 | W100: 1647.33 | X100: 575.97 | Y100: 89.01 | Z100: 604.36 | AA100: 175.38 | AB100: 242.12 | AC100: 561.4 | AD100: 916.03 | AE100: 170.62 | AF100: 225.72 | AG100: 365.73 | AH100: 29.575 | AI100: 69.03
A101: FIN-0100 | B101: CUST-1481 | C101: 2022-Q2 | D101: Analytics Add-on | E101: LinkedIn Ads | F101: Base | G101: 7292.19 | H101: 87506.28 | I101: 601.63 | J101: 136338.9 | K101: 226.62 | L101: 5.56 | M101: 1470.85 | N101: 0 | O101: 549128.9 | P101: 12567566 | Q101: 22.9 | R101: 71.36 | S101: 26.36 | T101: 2022-07-22 | U101: 2022-08-29 | V101: 1026.77 | W101: 1078.82 | X101: 696.47 | Y101: 121.89 | Z101: 531.93 | AA101: 92.97 | AB101: 75.2 | AC101: 374.76 | AD101: 347.52 | AE101: 291.12 | AF101: 192.84 | AG101: 293.3 | AH101: 111.985 | AI101: 97.89
A102: FIN-0101 | B102: CUST-0801 | C102: 2025-Q1 | D102: WorkHub Core | E102: Webinar | F102: Optimistic | G102: 10532.62 | H102: 126391.44 | I102: 259.95 | J102: 255216.6 | K102: -981.79 | L102: 1.67 | M102: 0 | N102: 0 | O102: 365456.06 | P102: 16147177 | Q102: 44.2 | R102: 67.43 | S102: -7.2 | T102: 23/03/2022 | U102: 2022-05-18 | V102: 2109.43 | W102: 979.23 | X102: 778.51 | Y102: 1125.77 | Z102: 644.67 | AA102: 691.13 | AB102: 201.47 | AC102: 707.9 | AD102: 247.93 | AE102: 373.16 | AF102: 811.04 | AG102: 406.04 | AH102: 486.175 | AI102: 28.38
A103: FIN-0102 | B103: CUST-0650 | C103: 2023-Q4 | D103: WorkHub Enterprise | E103: Webinar | F103: Base | G103: 6563.16 | H103: 78757.92 | I103: 424.35 | J103: 41233.28 | K103: 97.17 | L103: 7.15 | M103: 1154 | N103: 1014.62 | O103: 684426.77 | P103: 16871074 | Q103: 24.6 | R103: 59.14 | S103: 2.59 | T103: 2024-03-30 | U103: 2024-06-15 | V103: 2543.03 | W103: 566.92 | X103: 643.68 | Y103: 155.82 | Z103: 499.16 | AA103: 275.77 | AB103: 252.29 | AC103: 1141.5 | AD103: 164.38 | AE103: 238.33 | AF103: 158.91 | AG103: 260.53 | AH103: 70.815 | AI103: 79.2
A104: FIN-0103 | B104: CUST-1265 | C104: 2022-Q2 | D104: WorkHub Enterprise | E104: Cold Outreach | F104: Base | G104: 8916.7 | H104: 107000.4 | I104: 600.55 | J104: 106508.02 | K104: 177.35 | L104: 6.86 | M104: 268.18 | N104: 0 | O104: 552722.51 | P104: 14412768 | Q104: 26.1 | R104: 72.81 | S104: 27.61 | T104: 2024-05-11 | U104: 2024-06-18 | V104: 2387.3 | W104: 652.4 | X104: 471.52 | Y104: 776.65 | Z104: 838.22 | AA104: 127.95 | AB104: 93.09 | AC104: 985.77 | AD104: 78.9 | AE104: 66.17 | AF104: 461.92 | AG104: 599.59 | AH104: 77.005 | AI104: 80
A105: FIN-0104 | B105: CUST-0945 | C105: 2025-Q1 | D105: WorkHub Enterprise | E105: Webinar | F105: Optimistic | G105: 7173.06 | H105: 86076.72 | I105: 499.14 | J105: 47247.24 | K105: 94.66 | L105: 5.17 | M105: 0 | N105: 0 | O105: 616261.75 | P105: 9541410.8 | Q105: 15.5 | R105: 68.52 | S105: -10.54 | T105: 2022-03-13 | U105: 2022-05-31 | V105: 222.86 | W105: 1093.86 | X105: 506.55 | Y105: 314.73 | Z105: 191.75 | AA105: 159.99 | AB105: 214.8 | AC105: 1178.67 | AD105: 362.56 | AE105: 101.2 | AF105: 0 | AG105: 46.88 | AH105: 44.965 | AI105: 41.71
A106: FIN-0105 | B106: CUST-0511 | C106: 2022-Q3 | D106: WorkHub Pro | E106: Cold Outreach | F106: Optimistic | G106: 5500.9 | H106: 66010.8 | I106: 808.57 | J106: 86032.15 | K106: 106.4 | L106: 9.88 | M106: 0 | N106: 0 | O106: 590654.77 | P106: 24409455 | R106: 74.94 | S106: 48.23 | T106: 2022-07-07 | U106: 2022-09-25 | V106: 317.72 | W106: 1035.23 | X106: 166.11 | Y106: 501.23 | Z106: 234.94 | AA106: 225.06 | AB106: 178.24 | AC106: 1083.81 | AD106: 303.93 | AE106: 239.24 | AF106: 186.5 | AG106: 3.69 | AH106: 20.105 | AI106: 5.15
A107: FIN-0106 | B107: CUST-0334 | C107: 2024-Q3 | D107: API Access | E107: LinkedIn Ads | F107: Base | G107: 3952.58 | H107: 47430.96 | I107: 838.65 | J107: 150963.74 | K107: 180.01 | L107: 10.06 | M107: 0 | N107: 0 | O107: 523787.48 | P107: 21117840 | Q107: 40.3 | R107: -19.03 | S107: -39.81 | T107: 2023-12-10 | U107: 2024-02-29 | V107: 1369.03 | W107: 2071.64 | X107: 289.23 | Y107: 338.49 | Z107: 692.76 | AA107: 196.33 | AB107: 290.66 | AC107: 32.5 | AD107: 1340.34 | AE107: 116.12 | AF107: 23.76 | AG107: 454.13 | AH107: 8.625 | AI107: 117.57
A108: FIN-0107 | B108: CUST-1492 | C108: 2022-Q3 | D108: API Access | E108: Inbound Organic | F108: Base | G108: 9678.33 | H108: 116139.96 | I108: 132.29 | J108: 209429.41 | K108: 1583.11 | L108: 7.65 | M108: 2405.7 | N108: 0 | O108: 267498.15 | P108: 14492699 | Q108: 54.2 | R108: 63.06 | S108: 48.04 | T108: 2024-07-24 | U108: 2024-09-27 | V108: 2310.1 | W108: 1680.61 | X108: 251.61 | Y108: 92.21 | Z108: 459.75 | AA108: 120.35 | AB108: 92.01 | AC108: 908.57 | AD108: 949.31 | AE108: 153.74 | AF108: 222.52 | AG108: 221.12 | AH108: 84.605 | AI108: 81.08
A109: FIN-0108 | B109: CUST-0849 | C109: 2023-Q1 | D109: WorkHub Enterprise | E109: Webinar | F109: Pessimistic | G109: 594.43 | H109: 7133.16 | I109: 483.27 | J109: 7253.59 | K109: 15.01 | L109: 1.34 | M109: 0 | N109: 0 | O109: 609364.63 | P109: 15896145 | Q109: 26.1 | R109: 61.43 | S109: 59.67 | T109: 2024-09-22 | U109: 30/11/2024 | V109: 717.46 | W109: 2411.53 | X109: 245.47 | Y109: 817.48 | Z109: 664.31 | AA109: 124.59 | AB109: 87.52 | AC109: 684.07 | AD109: 1680.23 | AE109: 159.88 | AF109: 502.75 | AG109: 425.68 | AH109: 80.365 | AI109: 85.57
A110: FIN-0109 | B110: CUST-1067 | C110: 2022-Q3 | D110: WorkHub Core | E110: LinkedIn Ads | F110: Base | G110: 15438.69 | H110: 185264.28 | I110: 1053.51 | J110: 264186.89 | K110: 250.77 | L110: 7.23 | M110: 0 | N110: 865.31 | O110: 557753 | P110: 13392485 | Q110: 24 | R110: 62.45 | S110: -29.79 | T110: 2022-01-12 | U110: 2022-02-13 | V110: 2064.64 | W110: 1171.57 | X110: 870.26 | Y110: 796.59 | Z110: 103.78 | AA110: 296.91 | AB110: 331.48 | AC110: 663.11 | AD110: 440.27 | AE110: 464.91 | AF110: 481.86 | AG110: 134.85 | AH110: 91.955 | AI110: 158.39
A111: FIN-0110 | B111: CUST-0926 | C111: 2022-Q2 | D111: API Access | E111: Cold Outreach | F111: Optimistic | G111: 791.71 | H111: 9500.52 | I111: 561.82 | J111: 18650.18 | K111: 33.2 | L111: 8.08 | M111: 0 | N111: 0 | O111: 767613.37 | P111: 21877381 | Q111: 28.5 | R111: -33.1 | S111: -15.2 | T111: 2023-03-12 | U111: 2023-04-12 | V111: 492.03 | W111: 580.33 | X111: 62.09 | Y111: 166.21 | Z111: 356.18 | AA111: 146.85 | AB111: 192.48 | AC111: 909.5 | AD111: 150.97 | AE111: 343.26 | AF111: 148.52 | AG111: 117.55 | AH111: 58.105 | AI111: 19.39
A112: FIN-0111 | B112: CUST-1167 | C112: 2023-Q1 | D112: Analytics Add-on | E112: Cold Outreach | F112: Pessimistic | G112: 15717.22 | H112: 188606.64 | I112: 437.66 | J112: 224478.74 | K112: 512.91 | L112: 4.34 | M112: 4507.44 | N112: 1316.83 | O112: 759879.93 | P112: 22414047 | Q112: 29.5 | R112: 63.21 | S112: 3.57 | T112: 2023-04-14 | U112: 23/06/2023 | V112: 1544.76 | W112: 311.15 | X112: 461.4 | Y112: 178.26 | Z112: 67.32 | AA112: 57.49 | AB112: 67.54 | AC112: 143.23 | AD112: 420.15 | AE112: 56.05 | AF112: 136.47 | AG112: 171.31 | AH112: 147.465 | AI112: 105.55
A113: FIN-0112 | B113: CUST-1078 | C113: 2022-Q1 | D113: API Access | E113: Partner Referral | F113: Base | G113: 15338.19 | H113: 184058.28 | I113: 387.13 | J113: 460915.43 | K113: 1190.6 | L113: 9.7 | M113: 5269.44 | N113: 0 | O113: 805258.32 | P113: 10585949 | Q113: 13.1 | R113: 67.03 | S113: -9.84 | T113: 2024-05-17 | U113: 2024-08-15 | V113: 3691.28 | W113: 1576.49 | X113: 457.21 | Y113: 310.01 | Z113: 300.46 | AA113: 251.6 | AB113: 70.35 | AC113: 2289.75 | AD113: 845.19 | AE113: 51.86 | AF113: 4.72 | AG113: 61.83 | AH113: 46.645 | AI113: 102.74
A114: FIN-0113 | B114: CUST-0099 | C114: 2024-Q2 | D114: WorkHub Core | E114: Product-Led Signup | F114: Pessimistic | G114: 3380.64 | H114: 40567.68 | I114: 118.57 | J114: 22161.65 | L114: 4.14 | M114: 1108.33 | N114: 0 | O114: 651078.63 | P114: 1479192.5 | Q114: 2.3 | R114: 63.19 | S114: -17.93 | T114: 2024-04-01 | U114: 2024-06-22 | V114: 2562.49 | W114: 248.71 | X114: 685.59 | Y114: 27.85 | Z114: 569.12 | AA114: 206.21 | AB114: 169.21 | AC114: 1160.96 | AD114: 482.59 | AE114: 280.24 | AF114: 286.88 | AG114: 330.49 | AH114: 1.255 | AI114: 3.88
A115: FIN-0114 | B115: CUST-0621 | C115: 2025-Q1 | D115: WorkHub Core | E115: Webinar | F115: Base | G115: 15949.49 | H115: 191393.88 | I115: 466.87 | J115: 343205.33 | K115: 735.12 | L115: 6.05 | M115: 2533.32 | N115: 0 | O115: 773102.19 | P115: 16269668 | Q115: 21 | R115: 77.48 | S115: 17.98 | T115: 2022-10-16 | U115: 2023-01-12 | V115: 256.27 | W115: 332.24 | X115: 846.39 | Y115: 521.99 | Z115: 700 | AA115: 347.54 | AB115: 74.76 | AC115: 1145.26 | AD115: 399.06 | AE115: 441.04 | AF115: 207.26 | AG115: 461.37 | AH115: 142.585 | AI115: 98.33
A116: FIN-0115 | B116: CUST-0947 | C116: 2024-Q4 | D116: WorkHub Enterprise | E116: Product-Led Signup | F116: Optimistic | G116: 15599.86 | H116: 187198.32 | I116: 149.67 | J116: 404965.11 | K116: 2705.72 | L116: 10.28 | M116: 4918.56 | N116: 0 | O116: 523768.31 | P116: 20643315 | R116: 72.23 | S116: -20.2 | T116: 2023-01-01 | U116: 2023-02-01 | V116: 467.64 | W116: 552.24 | X116: 778.74 | Y116: 500.54 | Z116: 34.43 | AA116: 227.6 | AB116: 474.52 | AC116: 933.89 | AD116: 179.06 | AE116: 373.39 | AF116: 185.81 | AG116: 204.2 | AH116: 22.645 | AI116: 301.43
A117: FIN-0116 | B117: CUST-0327 | C117: 2024-Q4 | D117: Analytics Add-on | E117: LinkedIn Ads | F117: Base | G117: 4293.56 | H117: 51522.72 | I117: 1177.97 | J117: 66590.55 | K117: 56.53 | L117: 1.06 | M117: 829.23 | N117: 0 | O117: 724148.49 | P117: 23055463 | Q117: 31.8 | R117: 59.82 | S117: -32.71 | T117: 2022-10-19 | U117: 2023-01-14 | V117: 6052.5 | W117: 102.53 | X117: 966.05 | Y117: 1203.68 | Z117: 200.52 | AA117: 6.4 | AB117: 530.18 | AC117: 4650.97 | AD117: 628.77 | AE117: 560.7 | AF117: 888.95 | AG117: 38.11 | AH117: 198.555 | AI117: 357.09
A118: FIN-0117 | B118: CUST-0213 | C118: 2023-Q2 | D118: Analytics Add-on | E118: LinkedIn Ads | F118: Pessimistic | G118: 11082.37 | H118: 132988.44 | I118: 572.06 | J118: 65800.69 | K118: 115.02 | L118: 5.2 | M118: 0 | N118: 0 | O118: 321783.06 | P118: 2536529.8 | Q118: 7.9 | R118: 60.99 | S118: 34.23 | T118: 2022-12-02 | U118: 2023-02-27 | V118: 3229.2 | W118: 100.15 | X118: 148.65 | Y118: 132.52 | Z118: 824.44 | AA118: 559.13 | AB118: 123.03 | AC118: 1827.67 | AD118: 631.15 | AE118: 256.7 | AF118: 182.21 | AG118: 585.81 | AH118: 354.175 | AI118: 50.06
A119: FIN-0118 | B119: CUST-0054 | C119: 2023-Q4 | D119: WorkHub Enterprise | E119: Webinar | F119: Optimistic | G119: 6826.53 | H119: 81918.36 | I119: 313.12 | J119: 77044.77 | K119: 246.06 | L119: 5.89 | M119: 0 | N119: 449.33 | O119: 618596.04 | P119: 23369544 | R119: 60.67 | S119: 1.63 | T119: 2024-01-17 | U119: 2024-03-21 | V119: 2425.88 | W119: 708.1 | X119: 542.11 | Y119: 45.65 | Z119: 137.75 | AA119: 396.38 | AB119: 477.81 | AC119: 1024.35 | AD119: 23.2 | AE119: 136.76 | AF119: 269.08 | AG119: 100.88 | AH119: 191.425 | AI119: 304.72
A120: FIN-0119 | B120: CUST-0567 | C120: 2024-Q2 | D120: WorkHub Pro | E120: Product-Led Signup | F120: Pessimistic | G120: 12650.63 | H120: 151807.56 | I120: 150.23 | J120: 392598.38 | K120: 2613.32 | L120: 4.14 | M120: 2317.11 | N120: 0 | O120: 498689.57 | P120: 17025532 | Q120: 34.1 | R120: 69.16 | S120: -2.76 | T120: 2024-01-29 | U120: 2024-03-20 | V120: 2261.97 | W120: 731.3 | X120: 280.81 | Y120: 787.75 | Z120: 17.25 | AA120: 1015.43 | AB120: 7.5 | AC120: 860.44 | AD120: 0 | AE120: 124.54 | AF120: 473.02 | AG120: 221.38 | AH120: 810.475 | AI120: 165.59
A121: FIN-0120 | B121: CUST-1015 | C121: 2023-Q3 | D121: WorkHub Core | E121: Partner Referral | F121: Pessimistic | G121: 9377.12 | H121: 112525.44 | I121: 569.05 | J121: 175480.3 | K121: 308.37 | L121: 4.17 | M121: 3253.11 | N121: 0 | O121: 481097.91 | P121: 1253685.6 | Q121: 2.6 | R121: 58 | S121: -14.97 | T121: 15/10/2022 | U121: 2022-12-09 | V121: 1159.23 | W121: 457.71 | X121: 562.79 | Y121: 331.58 | Z121: 93.83 | AA121: 75.47 | AB121: 37.53 | AC121: 242.3 | AD121: 273.59 | AE121: 157.44 | AF121: 16.85 | AG121: 144.8 | AH121: 129.485 | AI121: 135.56
A122: FIN-0121 | B122: CUST-0719 | C122: 2022-Q1 | D122: API Access | E122: Webinar | F122: Base | G122: 17510.16 | H122: 210121.92 | I122: 315.2 | J122: 394630.92 | K122: 1252 | L122: 6.03 | M122: 0 | N122: 0 | O122: 504373.28 | P122: 17100361 | Q122: 33.9 | R122: 69.49 | S122: 50.62 | T122: 02/02/2023 | U122: 2023-04-14 | V122: 876.89 | W122: 520.12 | X122: 748.78 | Y122: 186.66 | Z122: 577.69 | AA122: 369.85 | AB122: 277.34 | AC122: 524.64 | AD122: 211.18 | AE122: 343.43 | AF122: 128.07 | AG122: 339.06 | AH122: 164.895 | AI122: 104.25
...

Sheet Descriptive Statistics
A1: Task 5 – Descriptive Statistics
A3: Metric | B3: N | C3: Mean | D3: Median | E3: Standard Deviation | F3: Skewness | G3: Kurtosis
A4: MRR_USD | B4: =COUNT('SaaS_Financials '!G:G) -> 1100 | C4: =AVERAGE('SaaS_Financials '!G:G) -> 9197.6271 | D4: =MEDIAN('SaaS_Financials '!G:G) -> 9282.295 | E4: =_xlfn.STDEV.S('SaaS_Financials '!G:G) -> 5197.143 | F4: =SKEW('SaaS_Financials '!G:G) -> -0.037256709 | G4: =KURT('SaaS_Financials '!G:G) -> -1.2034882
A5: LTV_CAC_Ratio | B5: =COUNTIF('SaaS_Financials '!K:K,">0") -> 994 | C5: =AVERAGEIF('SaaS_Financials '!K:K,">0") -> 638.76469 | D5: {=MEDIAN(IF('SaaS_Financials '!K:K>0,'SaaS_Financials '!K:K))} -> 341.79 | E5: {=_xlfn.STDEV.S(IF('SaaS_Financials '!K:K>0,'SaaS_Financials '!K:K))} -> 826.43507 | F5: {=SKEW(IF('SaaS_Financials '!K:K>0,'SaaS_Financials '!K:K))} -> 2.9007948 | G5: {=KURT(IF('SaaS_Financials '!K:K>0,'SaaS_Financials '!K:K))} -> 11.09666
A6: Resolution_Hours | B6: =COUNT(Support_Tickets!R:R) -> 4559 | C6: =AVERAGE(Support_Tickets!R:R) -> 56.617644 | D6: =MEDIAN(Support_Tickets!R:R) -> 30.83 | E6: =_xlfn.STDEV.S(Support_Tickets!R:R) -> 62.411665 | F6: =SKEW(Support_Tickets!R:R) -> 1.5605802 | G6: =KURT(Support_Tickets!R:R) -> 1.5353486
A7: Deal_Value_USD | B7: =COUNT(Sales_Pipeline!R:R) -> 4200 | C7: =AVERAGE(Sales_Pipeline!R:R) -> 37480.063 | D7: =MEDIAN(Sales_Pipeline!R:R) -> 13205 | E7: =_xlfn.STDEV.S(Sales_Pipeline!R:R) -> 52353.855 | F7: =SKEW(Sales_Pipeline!R:R) -> 1.9294989 | G7: =KURT(Sales_Pipeline!R:R) -> 2.6007192

Sheet Statistical Report
A1: Task 5 – Statistical Analysis Report
A2: Statistical validation of acquisition, sales, customer risk, activation, and churn
A4: 1. Hypothesis 1 – Win Rate Comparison
A5: Null Hypothesis (H₀): | B5: Product-Led Signup + Inbound Organic deals do not have a higher win rate than Cold Outreach + Paid Search deals.
A6: Alternative Hypothesis (H₁): | B6: Product-Led Signup + Inbound Organic deals have a higher win rate than Cold Outreach + Paid Search deals.
A7: Test: | B7: Two-Proportion Z-Test
A8: Confidence Level: | B8: 0.95
A9: Significance Level (α): | B9: 0.05
A10: Results:
A11: Product-Led + Inbound | B11: Won: 158 | Lost: 119 | Closed: 277 | Win Rate: 57.04%
A12: Cold + Paid | B12: Won: 163 | Lost: 152 | Closed: 315 | Win Rate: 51.75%
A13: Z-Statistic: | B13: 1.29
A14: One-Tailed p-value: | B14: 0.0985
A15: Decision: | B15: Fail to Reject H₀
A16: Business Interpretation: | B16: Product-Led Signup + Inbound Organic had a higher observed win rate (57.04% vs. 51.75%), but the difference was not statistically significant (p = 0.099 > 0.05). Therefore, there is not enough evidence to conclude that these channels have a higher win rate.
A18: 2. Hypothesis 2 – LTV/CAC by Acquisition Channel
A19: Null Hypothesis (H₀): | B19: Mean LTV/CAC ratio is the same across all acquisition channels.
A20: Alternative Hypothesis (H₁): | B20: At least one acquisition channel has a different mean LTV/CAC ratio.
A21: Test: | B21: One-Way ANOVA
A22: Confidence: | B22: 95% confidence; α = 0.05
A23: ANOVA F-Statistic: | B23: 108.1272
A24: ANOVA p-value: | B24: 1.03e-104
A25: Kruskal-Wallis: | B25: H = 334.8933; p = 2.70E-69
A26: Decision: | B26: Reject H₀
A27: Business Interpretation: | B27: LTV/CAC differs significantly across acquisition channels. ANOVA assumptions were violated because variances were unequal (Levene p < 0.001) and the data were strongly right-skewed, so Kruskal-Wallis is the primary result. Product-Led Signup showed the highest average LTV/CAC.
A29: 3. Hypothesis 3 – SLA Breach vs Churn Risk
A30: Null Hypothesis (H₀): | B30: SLA breach status in the first 90 days is independent of Churn Risk Flag.
A31: Alternative Hypothesis (H₁): | B31: Customers with one or more first-90-day SLA breaches have a different Churn Risk Flag.
A32: Test: | B32: Chi-Square Test of Independence
A33: Confidence: | B33: 95% confidence; α = 0.05
A34: Chi-Square Statistic: | B34: 0.034697
A35: Degrees of Freedom: | B35: 1
A36: p-value: | B36: 0.852232
A37: Decision: | B37: Fail to Reject H₀
A38: Business Interpretation: | B38: Customers with first-90-day SLA breaches did not show a statistically significant difference in Churn Risk Flag compared with customers without SLA breaches (χ² = 0.035, p = 0.852 > 0.05).
A40: 4. Hypothesis 4 – In-App Nudge vs Activation Rate
A41: Null Hypothesis (H₀): | B41: In-App Nudge campaigns do not have a higher average Activation Rate than non-In-App campaigns.
A42: Alternative Hypothesis (H₁): | B42: In-App Nudge campaigns have a higher average Activation Rate than non-In-App campaigns.
A43: Test: | B43: Independent Samples t-Test (Welch)
A44: Confidence: | B44: 95% confidence; α = 0.05
A45: In-App Nudge: | B45: N = 46; Mean Activation Rate = 24.33%
A46: Non-In-App: | B46: N = 361; Mean Activation Rate = 16.09%
A47: t-Statistic: | B47: 4.688
A48: p-value: | B48: 1.0653618e-05
A49: Decision: | B49: Reject H₀
A50: Business Interpretation: | B50: In-App Nudge campaigns had a significantly higher Activation Rate than non-In-App campaigns (24.33% vs. 16.09%, p < 0.001). This provides strong statistical evidence that In-App Nudge campaigns are associated with higher activation.
A52: 5. Descriptive Statistics
A53: Metric | B53: N | C53: Mean | D53: Median | E53: Standard Deviation | F53: Skewness | G53: Kurtosis
A54: MRR_USD | B54: 1100 | C54: 9197.6271 | D54: 9282.295 | E54: 5197.143 | F54: -0.0373 | G54: -1.2035
A55: LTV_CAC_Ratio | B55: 994 | C55: 638.7647 | D55: 341.79 | E55: 826.4351 | F55: 2.9008 | G55: 11.0967
A56: Resolution_Hours | B56: 4559 | C56: 56.61764 | D56: 30.83 | E56: 62.41166 | F56: 1.56058 | G56: 1.535349
A57: Deal_Value_USD | B57: 4200 | C57: 37480.063 | D57: 13205 | E57: 52353.855 | F57: 1.9295 | G57: 2.6007
A59: 6. Monthly Churn Rate Distribution
A60: Best-Fit Distribution: | B60: Lognormal
A61: Lognormal Mu: | B61: 1.6379624
A62: Lognormal Sigma: | B62: 0.78715514
A63: Churn Rate Range: | B63: 0.52% – 53.17%
A64: Interpretation: | B64: Monthly Churn Rate is strongly right-skewed. Among the tested distributions, the Lognormal distribution provided the best fit to the observed churn-rate data.
A66: 7. NPS Score vs. Monthly Churn Rate
A67: Correlation Method: | B67: Pearson Correlation
A68: Correlation Coefficient (r): | B68: -0.00217
A69: Interpretation: | B69: The Pearson correlation indicates virtually no linear relationship between NPS Score and Monthly Churn Rate (r = -0.00217).
A71: 8. Overall Conclusion
A72: Conclusion: | B72: The analysis shows that acquisition channel significantly affects LTV/CAC and In-App Nudge campaigns significantly improve activation. However, the win-rate difference and SLA-breach relationship with churn risk were not statistically significant. Monthly churn is strongly right-skewed, with a Lognormal distribution providing the best fit, while NPS has virtually no linear relationship with churn.

Sheet Churn Distribution
A1: Monthly_Churn_Rate_Pct | C1: Bin | D1: Frequency | H1: Churn Rate | I1: Lognormal Fitted Frequency | J1: Bin Center | K1: Lognormal Expected Frequency
A2: =SaaS_Financials__2[[#This Row],[Monthly_Churn_Rate_Pct]] -> 6.58 | C2: 5 | D2: =COUNTIFS($A$2:$A$1101,">"&C2-5,$A$2:$A$1101,"<="&C2) -> 421 | F2: =MIN(A2:A1101) -> 0.52 | H2: =MIN($A$2:$A$1101) -> 0.52 | J2: =5/2 -> 2.5 | K2: =COUNT($A$2:$A$1101)*_xlfn.LOGNORM.DIST(5,$I$57,$I$58,TRUE) -> 534.10118
A3: =SaaS_Financials__2[[#This Row],[Monthly_Churn_Rate_Pct]] -> 53.17 | C3: 10 | D3: =COUNTIFS($A$2:$A$1101,">"&C3-5,$A$2:$A$1101,"<="&C3) -> 483 | F3: =MAX(A2:A1101) -> 53.17 | H3: =H2+1 -> 1.52 | J3: =J2+5 -> 7.5 | K3: =COUNT($A$2:$A$1101)*(_xlfn.LOGNORM.DIST(J3+2.5,$I$57,$I$58,TRUE)-_xlfn.LOGNORM.DIST(J3-2.5,$I$57,$I$58,TRUE)) -> 346.73362
A4: =SaaS_Financials__2[[#This Row],[Monthly_Churn_Rate_Pct]] -> 6.06 | C4: 15 | D4: =COUNTIFS($A$2:$A$1101,">"&C4-5,$A$2:$A$1101,"<="&C4) -> 181 | H4: =H3+1 -> 2.52 | J4: =J3+5 -> 12.5 | K4: =COUNT($A$2:$A$1101)*(_xlfn.LOGNORM.DIST(J4+2.5,$I$57,$I$58,TRUE)-_xlfn.LOGNORM.DIST(J4-2.5,$I$57,$I$58,TRUE)) -> 123.46071
A5: =SaaS_Financials__2[[#This Row],[Monthly_Churn_Rate_Pct]] -> 2.94 | C5: 20 | D5: =COUNTIFS($A$2:$A$1101,">"&C5-5,$A$2:$A$1101,"<="&C5) -> 0 | H5: =H4+1 -> 3.52 | J5: =J4+5 -> 17.5 | K5: =COUNT($A$2:$A$1101)*(_xlfn.LOGNORM.DIST(J5+2.5,$I$57,$I$58,TRUE)-_xlfn.LOGNORM.DIST(J5-2.5,$I$57,$I$58,TRUE)) -> 49.205217
A6: =SaaS_Financials__2[[#This Row],[Monthly_Churn_Rate_Pct]] -> 1.56 | C6: 25 | D6: =COUNTIFS($A$2:$A$1101,">"&C6-5,$A$2:$A$1101,"<="&C6) -> 0 | H6: =H5+1 -> 4.52 | J6: =J5+5 -> 22.5 | K6: =COUNT($A$2:$A$1101)*(_xlfn.LOGNORM.DIST(J6+2.5,$I$57,$I$58,TRUE)-_xlfn.LOGNORM.DIST(J6-2.5,$I$57,$I$58,TRUE)) -> 21.968163
A7: =SaaS_Financials__2[[#This Row],[Monthly_Churn_Rate_Pct]] -> 7.78 | C7: 30 | D7: =COUNTIFS($A$2:$A$1101,">"&C7-5,$A$2:$A$1101,"<="&C7) -> 1 | H7: =H6+1 -> 5.52 | J7: =J6+5 -> 27.5 | K7: =COUNT($A$2:$A$1101)*(_xlfn.LOGNORM.DIST(J7+2.5,$I$57,$I$58,TRUE)-_xlfn.LOGNORM.DIST(J7-2.5,$I$57,$I$58,TRUE)) -> 10.731437
A8: =SaaS_Financials__2[[#This Row],[Monthly_Churn_Rate_Pct]] -> 2.22 | C8: 35 | D8: =COUNTIFS($A$2:$A$1101,">"&C8-5,$A$2:$A$1101,"<="&C8) -> 6 | H8: =H7+1 -> 6.52 | J8: =J7+5 -> 32.5 | K8: =COUNT($A$2:$A$1101)*(_xlfn.LOGNORM.DIST(J8+2.5,$I$57,$I$58,TRUE)-_xlfn.LOGNORM.DIST(J8-2.5,$I$57,$I$58,TRUE)) -> 5.6282269
A9: =SaaS_Financials__2[[#This Row],[Monthly_Churn_Rate_Pct]] -> 52.17 | C9: 40 | D9: =COUNTIFS($A$2:$A$1101,">"&C9-5,$A$2:$A$1101,"<="&C9) -> 1 | H9: =H8+1 -> 7.52 | J9: =J8+5 -> 37.5 | K9: =COUNT($A$2:$A$1101)*(_xlfn.LOGNORM.DIST(J9+2.5,$I$57,$I$58,TRUE)-_xlfn.LOGNORM.DIST(J9-2.5,$I$57,$I$58,TRUE)) -> 3.1254334
A10: =SaaS_Financials__2[[#This Row],[Monthly_Churn_Rate_Pct]] -> 9.74 | C10: 45 | D10: =COUNTIFS($A$2:$A$1101,">"&C10-5,$A$2:$A$1101,"<="&C10) -> 3 | H10: =H9+1 -> 8.52 | J10: =J9+5 -> 42.5 | K10: =COUNT($A$2:$A$1101)*(_xlfn.LOGNORM.DIST(J10+2.5,$I$57,$I$58,TRUE)-_xlfn.LOGNORM.DIST(J10-2.5,$I$57,$I$58,TRUE)) -> 1.8190394
A11: =SaaS_Financials__2[[#This Row],[Monthly_Churn_Rate_Pct]] -> 11.1 | C11: 50 | D11: =COUNTIFS($A$2:$A$1101,">"&C11-5,$A$2:$A$1101,"<="&C11) -> 1 | H11: =H10+1 -> 9.52 | J11: =J10+5 -> 47.5 | K11: =COUNT($A$2:$A$1101)*(_xlfn.LOGNORM.DIST(J11+2.5,$I$57,$I$58,TRUE)-_xlfn.LOGNORM.DIST(J11-2.5,$I$57,$I$58,TRUE)) -> 1.101126
A12: =SaaS_Financials__2[[#This Row],[Monthly_Churn_Rate_Pct]] -> 11.04 | C12: 55 | D12: =COUNTIFS($A$2:$A$1101,">"&C12-5,$A$2:$A$1101,"<="&C12) -> 3 | H12: =H11+1 -> 10.52 | J12: =J11+5 -> 52.5 | K12: =COUNT($A$2:$A$1101)*(_xlfn.LOGNORM.DIST(J12+2.5,$I$57,$I$58,TRUE)-_xlfn.LOGNORM.DIST(J12-2.5,$I$57,$I$58,TRUE)) -> 0.68918353
A13: =SaaS_Financials__2[[#This Row],[Monthly_Churn_Rate_Pct]] -> 8.31 | H13: =H12+1 -> 11.52
A14: =SaaS_Financials__2[[#This Row],[Monthly_Churn_Rate_Pct]] -> 11.14 | H14: =H13+1 -> 12.52
A15: =SaaS_Financials__2[[#This Row],[Monthly_Churn_Rate_Pct]] -> 8.57 | H15: =H14+1 -> 13.52
A16: =SaaS_Financials__2[[#This Row],[Monthly_Churn_Rate_Pct]] -> 11.71 | H16: =H15+1 -> 14.52
A17: =SaaS_Financials__2[[#This Row],[Monthly_Churn_Rate_Pct]] -> 3.93 | H17: =H16+1 -> 15.52
A18: =SaaS_Financials__2[[#This Row],[Monthly_Churn_Rate_Pct]] -> 5.41 | H18: =H17+1 -> 16.52
A19: =SaaS_Financials__2[[#This Row],[Monthly_Churn_Rate_Pct]] -> 32.88 | H19: =H18+1 -> 17.52
A20: =SaaS_Financials__2[[#This Row],[Monthly_Churn_Rate_Pct]] -> 3.37 | H20: =H19+1 -> 18.52
A21: =SaaS_Financials__2[[#This Row],[Monthly_Churn_Rate_Pct]] -> 9.28 | H21: =H20+1 -> 19.52
A22: =SaaS_Financials__2[[#This Row],[Monthly_Churn_Rate_Pct]] -> 3.77 | H22: =H21+1 -> 20.52
A23: =SaaS_Financials__2[[#This Row],[Monthly_Churn_Rate_Pct]] -> 5.76 | H23: =H22+1 -> 21.52
A24: =SaaS_Financials__2[[#This Row],[Monthly_Churn_Rate_Pct]] -> 1.82 | H24: =H23+1 -> 22.52
... A55: =SaaS_Financials__2[[#This Row],[Monthly_Churn_Rate_Pct]] -> 9.05 | H55: =H54+1 -> 53.52
A56: =SaaS_Financials__2[[#This Row],[Monthly_Churn_Rate_Pct]] -> 1.31
A57: =SaaS_Financials__2[[#This Row],[Monthly_Churn_Rate_Pct]] -> 10.15 | H57: Lognormal Mu | I57: {=AVERAGE(LN($A$2:$A$1101))} -> 1.6379624
A58: =SaaS_Financials__2[[#This Row],[Monthly_Churn_Rate_Pct]] -> 8.12 | H58: Lognormal Sigma | I58: {=_xlfn.STDEV.P(LN($A$2:$A$1101))} -> 0.78715514
A59: =SaaS_Financials__2[[#This Row],[Monthly_Churn_Rate_Pct]] -> 7.99
A60: =SaaS_Financials__2[[#This Row],[Monthly_Churn_Rate_Pct]] -> 9.62
A61: =SaaS_Financials__2[[#This Row],[Monthly_Churn_Rate_Pct]] -> 9.33
A62: =SaaS_Financials__2[[#This Row],[Monthly_Churn_Rate_Pct]] -> 3.46
A63: =SaaS_Financials__2[[#This Row],[Monthly_Churn_Rate_Pct]] -> 2.15
A64: =SaaS_Financials__2[[#This Row],[Monthly_Churn_Rate_Pct]] -> 3.91
A65: =SaaS_Financials__2[[#This Row],[Monthly_Churn_Rate_Pct]] -> 10.55
A66: =SaaS_Financials__2[[#This Row],[Monthly_Churn_Rate_Pct]] -> 2.5
A67: =SaaS_Financials__2[[#This Row],[Monthly_Churn_Rate_Pct]] -> 11.12
A68: =SaaS_Financials__2[[#This Row],[Monthly_Churn_Rate_Pct]] -> 9.92
A69: =SaaS_Financials__2[[#This Row],[Monthly_Churn_Rate_Pct]] -> 7.15
A70: =SaaS_Financials__2[[#This Row],[Monthly_Churn_Rate_Pct]] -> 0.56
... A1101: =SaaS_Financials__2[[#This Row],[Monthly_Churn_Rate_Pct]] -> 4.47

Sheet Correlation
A1: NPS_Score | B1: Monthly_Churn_Rate_Pct | D1: Pearson Correlation
A2: ='Customers'!J2 -> 8 | B2: =IFERROR(AVERAGEIF('SaaS_Financials '!$B$2:$B$1101,'Customers'!A2,'SaaS_Financials '!$L$2:$L$1101),"") -> 7.545 | D2: {=CORREL(_xlfn._xlws.FILTER(A2:A1521,B2:B1521<>""),_xlfn._xlws.FILTER(B2:B1521,B2:B1521<>""))} -> -0.002168514
A3: ='Customers'!J3 -> 9 | B3: =IFERROR(AVERAGEIF('SaaS_Financials '!$B$2:$B$1101,'Customers'!A3,'SaaS_Financials '!$L$2:$L$1101),"") | D3: Interpretation
A4: ='Customers'!J4 -> 15 | B4: =IFERROR(AVERAGEIF('SaaS_Financials '!$B$2:$B$1101,'Customers'!A4,'SaaS_Financials '!$L$2:$L$1101),"") -> 4.28 | D4: Virtually no linear relationship between NPS Score and Monthly Churn Rate (r = -0.00217).
A5: ='Customers'!J5 -> 91 | B5: =IFERROR(AVERAGEIF('SaaS_Financials '!$B$2:$B$1101,'Customers'!A5,'SaaS_Financials '!$L$2:$L$1101),"") -> 3.495
A6: ='Customers'!J6 -> 0 | B6: =IFERROR(AVERAGEIF('SaaS_Financials '!$B$2:$B$1101,'Customers'!A6,'SaaS_Financials '!$L$2:$L$1101),"")
A7: ='Customers'!J7 -> 59 | B7: =IFERROR(AVERAGEIF('SaaS_Financials '!$B$2:$B$1101,'Customers'!A7,'SaaS_Financials '!$L$2:$L$1101),"")
A8: ='Customers'!J8 -> 40 | B8: =IFERROR(AVERAGEIF('SaaS_Financials '!$B$2:$B$1101,'Customers'!A8,'SaaS_Financials '!$L$2:$L$1101),"") -> 10.42
A9: ='Customers'!J9 -> 7 | B9: =IFERROR(AVERAGEIF('SaaS_Financials '!$B$2:$B$1101,'Customers'!A9,'SaaS_Financials '!$L$2:$L$1101),"")
A10: ='Customers'!J10 -> 70 | B10: =IFERROR(AVERAGEIF('SaaS_Financials '!$B$2:$B$1101,'Customers'!A10,'SaaS_Financials '!$L$2:$L$1101),"") -> 4.64
A11: ='Customers'!J11 -> 0 | B11: =IFERROR(AVERAGEIF('SaaS_Financials '!$B$2:$B$1101,'Customers'!A11,'SaaS_Financials '!$L$2:$L$1101),"")
A12: ='Customers'!J12 -> 80 | B12: =IFERROR(AVERAGEIF('SaaS_Financials '!$B$2:$B$1101,'Customers'!A12,'SaaS_Financials '!$L$2:$L$1101),"") -> 7.9
A13: ='Customers'!J13 -> 59 | B13: =IFERROR(AVERAGEIF('SaaS_Financials '!$B$2:$B$1101,'Customers'!A13,'SaaS_Financials '!$L$2:$L$1101),"") -> 9.96
A14: ='Customers'!J14 -> 0 | B14: =IFERROR(AVERAGEIF('SaaS_Financials '!$B$2:$B$1101,'Customers'!A14,'SaaS_Financials '!$L$2:$L$1101),"") -> 2.73
A15: ='Customers'!J15 -> 41 | B15: =IFERROR(AVERAGEIF('SaaS_Financials '!$B$2:$B$1101,'Customers'!A15,'SaaS_Financials '!$L$2:$L$1101),"") -> 6.87
A16: ='Customers'!J16 -> 64 | B16: =IFERROR(AVERAGEIF('SaaS_Financials '!$B$2:$B$1101,'Customers'!A16,'SaaS_Financials '!$L$2:$L$1101),"")
... A1521: ='Customers'!J1521 -> 46 | B1521: =IFERROR(AVERAGEIF('SaaS_Financials '!$B$2:$B$1101,'Customers'!A1521,'SaaS_Financials '!$L$2:$L$1101),"") -> 7.1625

Sheet Summary
A1: Task 5 – Statistical Validation Summary
A2: Statistical testing of business performance, customer risk, acquisition, and churn
A4: Hypothesis | B4: Test | C4: Statistic | D4: p-value | E4: Decision | F4: Business Interpretation
A5: H1 – Win Rate | B5: Two-Proportion Z-Test | C5: 1.28996 | D5: 0.09853 | E5: Fail to Reject H0 | F5: Product-Led Signup + Inbound Organic had a higher observed win rate, but the difference was not statistically significant.
A6: H2 – LTV/CAC | B6: One-Way ANOVA + Kruskal-Wallis | C6: 334.8933 | D6: 2.696e-69 | E6: Reject H0 | F6: LTV/CAC differs significantly across acquisition channels. ANOVA assumptions were violated, so Kruskal-Wallis is the primary result.
A7: H3 – SLA Breach | B7: Chi-Square Test | C7: 0.034697 | D7: 0.852232 | E7: Fail to Reject H0 | F7: Customers with first-90-day SLA breaches did not show a statistically significant difference in Churn Risk Flag.
A8: H4 – In-App Nudge | B8: Independent Samples t-Test | C8: 4.68802 | D8: 1.07E-05 | E8: Reject H0 | F8: In-App Nudge campaigns had a significantly higher Activation Rate than non-In-App campaigns.
A11: Metric | B11: N | C11: Mean | D11: Median | E11: Standard Deviation | F11: Skewness | G11: Kurtosis
A12: MRR_USD | B12: =COUNT('SaaS_Financials '!G:G) -> 1100 | C12: =AVERAGE('SaaS_Financials '!G:G) -> 9197.6271 | D12: =MEDIAN('SaaS_Financials '!G:G) -> 9282.295 | E12: =_xlfn.STDEV.S('SaaS_Financials '!G:G) -> 5197.143 | F12: =SKEW('SaaS_Financials '!G:G) -> -0.037256709 | G12: =KURT('SaaS_Financials '!G:G) -> -1.2034882
A13: LTV_CAC_Ratio | B13: =COUNTIF('SaaS_Financials '!K:K,">0") -> 994 | C13: =AVERAGEIF('SaaS_Financials '!K:K,">0") -> 638.76469 | D13: {=MEDIAN(IF('SaaS_Financials '!K:K>0,'SaaS_Financials '!K:K))} -> 341.79 | E13: {=_xlfn.STDEV.S(IF('SaaS_Financials '!K:K>0,'SaaS_Financials '!K:K))} -> 826.43507 | F13: {=SKEW(IF('SaaS_Financials '!K:K>0,'SaaS_Financials '!K:K))} -> 2.9007948 | G13: {=KURT(IF('SaaS_Financials '!K:K>0,'SaaS_Financials '!K:K))} -> 11.09666
A14: Resolution_Hours | B14: =COUNTIF(Support_Tickets!I:I,">=0") -> 4663 | C14: =AVERAGEIF(Support_Tickets!I:I,">=0") -> 56.473086 | D14: {=MEDIAN(_xlfn._xlws.FILTER(Support_Tickets!I:I,Support_Tickets!I:I>=0))} -> 30.42 | E14: {=_xlfn.STDEV.S(_xlfn._xlws.FILTER(Support_Tickets!I:I,Support_Tickets!I:I>=0))} -> 62.513116 | F14: {=SKEW(_xlfn._xlws.FILTER(Support_Tickets!I:I,Support_Tickets!I:I>=0))} -> 1.5685388 | G14: {=KURT(_xlfn._xlws.FILTER(Support_Tickets!I:I,Support_Tickets!I:I>=0))} -> 1.5571277
A15: Deal_Value_USD | B15: =COUNT(Sales_Pipeline!R:R) -> 4200 | C15: =AVERAGE(Sales_Pipeline!R:R) -> 37480.063 | D15: =MEDIAN(Sales_Pipeline!R:R) -> 13205 | E15: =_xlfn.STDEV.S(Sales_Pipeline!R:R) -> 52353.855 | F15: =SKEW(Sales_Pipeline!R:R) -> 1.9294989 | G15: =KURT(Sales_Pipeline!R:R) -> 2.6007192
A18: Analysis | B18: Result
A19: Best-Fit Churn Distribution | B19: Lognormal
A20: Lognormal Mu | B20: 1.6379624
A21: Lognormal Sigma | B21: 0.78715514
A22: Churn Rate Range | B22: 0.52% – 53.17%
A23: Pearson Correlation | B23: -0.00217
A24: Correlation Interpretation | B24: Virtually no linear relationship between NPS Score and Monthly Churn Rate.
A27: Overall Conclusion | B27: The analysis shows that acquisition channel significantly affects LTV/CAC and In-App Nudge campaigns significantly improve activation. However, the win-rate difference and SLA-breach relationship with churn risk were not statistically significant. Monthly churn is strongly right-skewed, with a Lognormal distribution providing the best fit, while NPS has virtually no linear relationship with churn.

Sheet Support_Tickets
A1: Ticket_ID | B1: Customer_ID | C1: Deal_ID | D1: Category | E1: Priority | F1: Status | G1: Created_Date | H1: Resolved_Date | I1: Resolution_Hours | J1: SLA_Target_Hours | K1: SLA_Met | L1: Assigned_Agent | M1: Contact_Channel | N1: CSAT_Score | O1: Automation_Flag | P1: Created_Date_Clean | Q1: Unique_Ticket | R1: Resolution_Hours_Clean
A2: TKT-00001 | B2: CUST-0751 | C2: DL-02878 | D2: Integration Issue | E2: Medium | F2: Resolved | G2: 2024-11-01 | J2: 24 | L2: Chatura Bal | M2: Slack Integration | O2: False | P2: =IFERROR(DATEVALUE(G2),IFERROR(DATE(RIGHT(G2,4),MID(G2,4,2),LEFT(G2,2)),"")) -> 45597 | Q2: =--(COUNTIF($A$2:A2,A2)=1) -> 1 | R2: =IF(AND(Q2=1,I2<>"",ISNUMBER(I2),I2>=0),I2,"")
A3: TKT-00002 | B3: CUST-0976 | C3: DL-01196 | D3: Access & Permissions | E3: High | F3: Resolved | G3: 2023-01-24 | H3: 44950 | I3: 22.76 | J3: 8 | K3: No | L3: Nidhi Bora | M3: Help Portal | O3: True | P3: =IFERROR(DATEVALUE(G3),IFERROR(DATE(RIGHT(G3,4),MID(G3,4,2),LEFT(G3,2)),"")) -> 44950 | Q3: =--(COUNTIF($A$2:A3,A3)=1) -> 1 | R3: =IF(AND(Q3=1,I3<>"",ISNUMBER(I3),I3>=0),I3,"") -> 22.76
A4: TKT-00003 | B4: CUST-0599 | D4: Integration Issue | E4: Medium | F4: In Progress | G4: 2023-09-10 | J4: 24 | L4: Fiyaz Chawla | M4: Slack Integration | O4: 0 | P4: =IFERROR(DATEVALUE(G4),IFERROR(DATE(RIGHT(G4,4),MID(G4,4,2),LEFT(G4,2)),"")) -> 45179 | Q4: =--(COUNTIF($A$2:A4,A4)=1) -> 1 | R4: =IF(AND(Q4=1,I4<>"",ISNUMBER(I4),I4>=0),I4,"") | U4: N | V4: =COUNT(R:R) -> 4559
A5: TKT-00004 | B5: CUST-0454 | C5: DL-00550 | D5: Performance Issue | E5: Medium | F5: Resolved | G5: 2025-02-18 | J5: 24 | L5: Abha Dugal | M5: In-App Chat | O5: FALSE | P5: =IFERROR(DATEVALUE(G5),IFERROR(DATE(RIGHT(G5,4),MID(G5,4,2),LEFT(G5,2)),"")) -> 45706 | Q5: =--(COUNTIF($A$2:A5,A5)=1) -> 1 | R5: =IF(AND(Q5=1,I5<>"",ISNUMBER(I5),I5>=0),I5,"")
A6: TKT-00005 | B6: CUST-0090 | D6: Integration Issue | E6: High | F6: Resolved | G6: 20/07/2023 | H6: 45127 | I6: 21.49 | J6: 8 | K6: No | L6: Dayita Palan | M6: In-App Chat | N6: 2.3 | O6: FALSE | P6: =IFERROR(DATEVALUE(G6),IFERROR(DATE(RIGHT(G6,4),MID(G6,4,2),LEFT(G6,2)),"")) -> 45127 | Q6: =--(COUNTIF($A$2:A6,A6)=1) -> 1 | R6: =IF(AND(Q6=1,I6<>"",ISNUMBER(I6),I6>=0),I6,"") -> 21.49 | U6: Mean: | V6: =AVERAGE(R:R) -> 56.617644
A7: TKT-00006 | B7: CUST-1099 | D7: Access & Permissions | E7: Low | F7: Resolved | G7: 2022-04-07 | H7: 44660 | I7: 58.66 | J7: 72 | K7: Yes | L7: Abha Dugal | M7: Help Portal | N7: 2.6 | O7: No | P7: =IFERROR(DATEVALUE(G7),IFERROR(DATE(RIGHT(G7,4),MID(G7,4,2),LEFT(G7,2)),"")) -> 44658 | Q7: =--(COUNTIF($A$2:A7,A7)=1) -> 1 | R7: =IF(AND(Q7=1,I7<>"",ISNUMBER(I7),I7>=0),I7,"") -> 58.66 | T7: =COUNT(R:R) -> 4559
A8: TKT-00007 | B8: CUST-1099 | D8: Data Discrepancy | E8: Medium | F8: Resolved | G8: 2024-12-23 | H8: 45651 | I8: 65.52 | J8: 24 | K8: No | L8: Darika Pau | M8: In-App Chat | O8: Yes | P8: =IFERROR(DATEVALUE(G8),IFERROR(DATE(RIGHT(G8,4),MID(G8,4,2),LEFT(G8,2)),"")) -> 45649 | Q8: =--(COUNTIF($A$2:A8,A8)=1) -> 1 | R8: =IF(AND(Q8=1,I8<>"",ISNUMBER(I8),I8>=0),I8,"") -> 65.52 | U8: Median | V8: =MEDIAN(R:R) -> 30.83
A9: TKT-00008 | B9: CUST-1302 | D9: Feature Request | E9: Low | F9: Resolved | G9: 2024-09-27 | H9: 45567 | I9: 131.51 | J9: 72 | K9: No | L9: Bhavini Sheth | M9: Phone | O9: FALSE | P9: =IFERROR(DATEVALUE(G9),IFERROR(DATE(RIGHT(G9,4),MID(G9,4,2),LEFT(G9,2)),"")) -> 45562 | Q9: =--(COUNTIF($A$2:A9,A9)=1) -> 1 | R9: =IF(AND(Q9=1,I9<>"",ISNUMBER(I9),I9>=0),I9,"") -> 131.51 | T9: =COUNTIF(R:R,">=0") -> 4559
A10: TKT-00009 | B10: CUST-1269 | C10: DL-01325 | D10: Performance Issue | E10: Low | F10: Resolved | G10: 2022-06-03 | H10: 44718 | I10: 78.59 | J10: 72 | K10: No | L10: Peter Shan | M10: Email | N10: 1.4 | O10: FALSE | P10: =IFERROR(DATEVALUE(G10),IFERROR(DATE(RIGHT(G10,4),MID(G10,4,2),LEFT(G10,2)),"")) -> 44715 | Q10: =--(COUNTIF($A$2:A10,A10)=1) -> 1 | R10: =IF(AND(Q10=1,I10<>"",ISNUMBER(I10),I10>=0),I10,"") -> 78.59 | U10: Standard deviation: | V10: =_xlfn.STDEV.S(R:R) -> 62.411665
A11: TKT-00010 | B11: CUST-0478 | D11: Performance Issue | E11: Low | F11: Resolved | G11: 2024-09-03 | H11: 45541 | I11: 89.4 | J11: 72 | K11: No | L11: Bhanumati Savant | M11: Help Portal | N11: 1 | O11: True | P11: =IFERROR(DATEVALUE(G11),IFERROR(DATE(RIGHT(G11,4),MID(G11,4,2),LEFT(G11,2)),"")) -> 45538 | Q11: =--(COUNTIF($A$2:A11,A11)=1) -> 1 | R11: =IF(AND(Q11=1,I11<>"",ISNUMBER(I11),I11>=0),I11,"") -> 89.4 | T11: =COUNTIF(R:R,0) -> 0
A12: TKT-00011 | B12: CUST-1453 | D12: Performance Issue | E12: High | F12: Resolved | G12: 2023-12-04 | H12: 45264 | I12: 5.45 | J12: 8 | K12: Yes | L12: Ayush Banerjee | M12: Slack Integration | N12: 2.7 | O12: TRUE | P12: =IFERROR(DATEVALUE(G12),IFERROR(DATE(RIGHT(G12,4),MID(G12,4,2),LEFT(G12,2)),"")) -> 45264 | Q12: =--(COUNTIF($A$2:A12,A12)=1) -> 1 | R12: =IF(AND(Q12=1,I12<>"",ISNUMBER(I12),I12>=0),I12,"") -> 5.45 | U12: skewness: | V12: =SKEW(R:R) -> 1.5605802
A13: TKT-00012 | B13: CUST-0023 | C13: DL-02589 | D13: Data Discrepancy | E13: Low | F13: Resolved | G13: 2024-07-23 | H13: 45502 | I13: 157.18 | J13: 72 | K13: No | L13: Arin Dass | M13: Phone | N13: 3.6 | O13: TRUE | P13: =IFERROR(DATEVALUE(G13),IFERROR(DATE(RIGHT(G13,4),MID(G13,4,2),LEFT(G13,2)),"")) -> 45496 | Q13: =--(COUNTIF($A$2:A13,A13)=1) -> 1 | R13: =IF(AND(Q13=1,I13<>"",ISNUMBER(I13),I13>=0),I13,"") -> 157.18
A14: TKT-00013 | B14: CUST-0831 | D14: Data Discrepancy | E14: High | F14: Resolved | G14: 2022-12-07 | J14: 8 | L14: Neel Oza | M14: Help Portal | O14: TRUE | P14: =IFERROR(DATEVALUE(G14),IFERROR(DATE(RIGHT(G14,4),MID(G14,4,2),LEFT(G14,2)),"")) -> 44902 | Q14: =--(COUNTIF($A$2:A14,A14)=1) -> 1 | R14: =IF(AND(Q14=1,I14<>"",ISNUMBER(I14),I14>=0),I14,"") | U14: kurtosis: | V14: =KURT(R:R) -> 1.5353486
A15: TKT-00014 | B15: CUST-0874 | D15: Data Discrepancy | E15: Low | F15: Escalated | G15: 2024-02-20 | H15: 45347 | I15: 143.5 | J15: 72 | K15: No | L15: Hemangini Mangat | M15: Phone | N15: 2.4 | O15: True | P15: =IFERROR(DATEVALUE(G15),IFERROR(DATE(RIGHT(G15,4),MID(G15,4,2),LEFT(G15,2)),"")) -> 45342 | Q15: =--(COUNTIF($A$2:A15,A15)=1) -> 1 | R15: =IF(AND(Q15=1,I15<>"",ISNUMBER(I15),I15>=0),I15,"") -> 143.5
A16: TKT-00015 | B16: CUST-0989 | C16: DL-01854 | D16: Access & Permissions | E16: Low | F16: Resolved | G16: 2025-02-22 | H16: 45717 | I16: 175.8 | J16: 72 | K16: No | L16: Odika Ganesh | M16: In-App Chat | N16: 3.1 | O16: False | P16: =IFERROR(DATEVALUE(G16),IFERROR(DATE(RIGHT(G16,4),MID(G16,4,2),LEFT(G16,2)),"")) -> 45710 | Q16: =--(COUNTIF($A$2:A16,A16)=1) -> 1 | R16: =IF(AND(Q16=1,I16<>"",ISNUMBER(I16),I16>=0),I16,"") -> 175.8
A17: TKT-00016 | B17: CUST-1289 | D17: Account Management | E17: High | F17: Open | G17: 2023-04-14 | J17: 8 | L17: Dipta Nadig | M17: Phone | O17: No | P17: =IFERROR(DATEVALUE(G17),IFERROR(DATE(RIGHT(G17,4),MID(G17,4,2),LEFT(G17,2)),"")) -> 45030 | Q17: =--(COUNTIF($A$2:A17,A17)=1) -> 1 | R17: =IF(AND(Q17=1,I17<>"",ISNUMBER(I17),I17>=0),I17,"")
A18: TKT-00017 | B18: CUST-1317 | D18: Account Management | E18: High | F18: Resolved | G18: 2024-06-25 | H18: 45468 | I18: 16.34 | J18: 8 | K18: No | L18: Anita Saxena | M18: In-App Chat | N18: 4.7 | O18: No | P18: =IFERROR(DATEVALUE(G18),IFERROR(DATE(RIGHT(G18,4),MID(G18,4,2),LEFT(G18,2)),"")) -> 45468 | Q18: =--(COUNTIF($A$2:A18,A18)=1) -> 1 | R18: =IF(AND(Q18=1,I18<>"",ISNUMBER(I18),I18>=0),I18,"") -> 16.34
A19: TKT-00018 | B19: CUST-0105 | C19: DL-03503 | D19: Data Discrepancy | E19: Medium | F19: Open | G19: 2024-10-22 | J19: 24 | L19: Neel Oza | M19: Help Portal | O19: No | P19: =IFERROR(DATEVALUE(G19),IFERROR(DATE(RIGHT(G19,4),MID(G19,4,2),LEFT(G19,2)),"")) -> 45587 | Q19: =--(COUNTIF($A$2:A19,A19)=1) -> 1 | R19: =IF(AND(Q19=1,I19<>"",ISNUMBER(I19),I19>=0),I19,"")
A20: TKT-00019 | B20: CUST-0131 | C20: DL-01941 | D20: Billing & Payments | E20: Medium | F20: Resolved | G20: 2022-10-22 | H20: 44859 | I20: 74.88 | J20: 24 | K20: No | L20: Chatura Bal | M20: Slack Integration | O20: Yes | P20: =IFERROR(DATEVALUE(G20),IFERROR(DATE(RIGHT(G20,4),MID(G20,4,2),LEFT(G20,2)),"")) -> 44856 | Q20: =--(COUNTIF($A$2:A20,A20)=1) -> 1 | R20: =IF(AND(Q20=1,I20<>"",ISNUMBER(I20),I20>=0),I20,"") -> 74.88
A21: TKT-00020 | B21: CUST-1372 | D21: Technical Bug | E21: Low | F21: Open | G21: 2023-09-25 | J21: 72 | L21: Dipta Nadig | M21: Slack Integration | O21: TRUE | P21: =IFERROR(DATEVALUE(G21),IFERROR(DATE(RIGHT(G21,4),MID(G21,4,2),LEFT(G21,2)),"")) -> 45194 | Q21: =--(COUNTIF($A$2:A21,A21)=1) -> 1 | R21: =IF(AND(Q21=1,I21<>"",ISNUMBER(I21),I21>=0),I21,"")
A22: TKT-00021 | B22: CUST-1487 | C22: DL-00949 | D22: Performance Issue | E22: Low | F22: Escalated | G22: 2024-06-07 | H22: 45455 | I22: 131.61 | J22: 72 | K22: No | L22: Eshana Soni | M22: Email | O22: False | P22: =IFERROR(DATEVALUE(G22),IFERROR(DATE(RIGHT(G22,4),MID(G22,4,2),LEFT(G22,2)),"")) -> 45450 | Q22: =--(COUNTIF($A$2:A22,A22)=1) -> 1 | R22: =IF(AND(Q22=1,I22<>"",ISNUMBER(I22),I22>=0),I22,"") -> 131.61
A23: TKT-00022 | B23: CUST-0619 | C23: DL-03703 | D23: Data Discrepancy | E23: Low | F23: Resolved | G23: 2024-11-11 | H23: 45615 | I23: 198.8 | J23: 72 | K23: No | L23: Utkarsh Chakraborty | M23: Slack Integration | N23: 3.1 | O23: True | P23: =IFERROR(DATEVALUE(G23),IFERROR(DATE(RIGHT(G23,4),MID(G23,4,2),LEFT(G23,2)),"")) -> 45607 | Q23: =--(COUNTIF($A$2:A23,A23)=1) -> 1 | R23: =IF(AND(Q23=1,I23<>"",ISNUMBER(I23),I23>=0),I23,"") -> 198.8
A24: TKT-00023 | B24: CUST-0095 | D24: Onboarding Support | E24: Low | F24: Resolved | G24: 2023-05-27 | H24: 45075 | I24: 53.66 | J24: 72 | K24: Yes | L24: Arin Dass | M24: In-App Chat | N24: 2.5 | O24: TRUE | P24: =IFERROR(DATEVALUE(G24),IFERROR(DATE(RIGHT(G24,4),MID(G24,4,2),LEFT(G24,2)),"")) -> 45073 | Q24: =--(COUNTIF($A$2:A24,A24)=1) -> 1 | R24: =IF(AND(Q24=1,I24<>"",ISNUMBER(I24),I24>=0),I24,"") -> 53.66
A25: TKT-00024 | B25: CUST-0374 | D25: Onboarding Support | E25: Medium | F25: Resolved | G25: 2022-01-15 | H25: 44578 | I25: 50.89 | J25: 24 | K25: No | L25: Dayamai Karnik | M25: Help Portal | N25: 2.7 | O25: True | P25: =IFERROR(DATEVALUE(G25),IFERROR(DATE(RIGHT(G25,4),MID(G25,4,2),LEFT(G25,2)),"")) -> 44576 | Q25: =--(COUNTIF($A$2:A25,A25)=1) -> 1 | R25: =IF(AND(Q25=1,I25<>"",ISNUMBER(I25),I25>=0),I25,"") -> 50.89
A26: TKT-00025 | B26: CUST-0097 | D26: Account Management | E26: High | F26: Resolved | G26: 2022-06-29 | H26: 44741 | I26: 5.3 | J26: 8 | K26: Yes | M26: Phone | O26: Yes | P26: =IFERROR(DATEVALUE(G26),IFERROR(DATE(RIGHT(G26,4),MID(G26,4,2),LEFT(G26,2)),"")) -> 44741 | Q26: =--(COUNTIF($A$2:A26,A26)=1) -> 1 | R26: =IF(AND(Q26=1,I26<>"",ISNUMBER(I26),I26>=0),I26,"") -> 5.3
A27: TKT-00026 | B27: CUST-0487 | D27: Account Management | E27: Medium | F27: Resolved | G27: 2023-07-02 | J27: 24 | L27: Dayamai Karnik | M27: Slack Integration | O27: 0 | P27: =IFERROR(DATEVALUE(G27),IFERROR(DATE(RIGHT(G27,4),MID(G27,4,2),LEFT(G27,2)),"")) -> 45109 | Q27: =--(COUNTIF($A$2:A27,A27)=1) -> 1 | R27: =IF(AND(Q27=1,I27<>"",ISNUMBER(I27),I27>=0),I27,"")
A28: TKT-00027 | B28: CUST-0965 | C28: DL-03232 | D28: Performance Issue | E28: Medium | F28: Resolved | G28: 2023-12-29 | H28: 45289 | I28: 9.97 | J28: 24 | K28: Yes | L28: Odika Ganesh | M28: Help Portal | N28: 1.8 | O28: 1 | P28: =IFERROR(DATEVALUE(G28),IFERROR(DATE(RIGHT(G28,4),MID(G28,4,2),LEFT(G28,2)),"")) -> 45289 | Q28: =--(COUNTIF($A$2:A28,A28)=1) -> 1 | R28: =IF(AND(Q28=1,I28<>"",ISNUMBER(I28),I28>=0),I28,"") -> 9.97
A29: TKT-00028 | B29: CUST-0178 | C29: DL-01013 | D29: Account Management | E29: High | F29: In Progress | G29: 2023-03-21 | J29: 8 | L29: Arin Dass | M29: Phone | O29: FALSE | P29: =IFERROR(DATEVALUE(G29),IFERROR(DATE(RIGHT(G29,4),MID(G29,4,2),LEFT(G29,2)),"")) -> 45006 | Q29: =--(COUNTIF($A$2:A29,A29)=1) -> 1 | R29: =IF(AND(Q29=1,I29<>"",ISNUMBER(I29),I29>=0),I29,"")
A30: TKT-00029 | B30: CUST-0880 | D30: Integration Issue | E30: Medium | F30: In Progress | G30: 22/11/2022 | J30: 24 | L30: Sai Patil | M30: In-App Chat | O30: False | P30: =IFERROR(DATEVALUE(G30),IFERROR(DATE(RIGHT(G30,4),MID(G30,4,2),LEFT(G30,2)),"")) -> 44887 | Q30: =--(COUNTIF($A$2:A30,A30)=1) -> 1 | R30: =IF(AND(Q30=1,I30<>"",ISNUMBER(I30),I30>=0),I30,"")
A31: TKT-00030 | B31: CUST-1082 | C31: DL-03821 | D31: Access & Permissions | E31: High | F31: Resolved | G31: 2022-10-18 | H31: 44853 | I31: 27.38 | J31: 8 | K31: No | L31: Ojas Ranganathan | M31: Phone | N31: 1.1 | O31: TRUE | P31: =IFERROR(DATEVALUE(G31),IFERROR(DATE(RIGHT(G31,4),MID(G31,4,2),LEFT(G31,2)),"")) -> 44852 | Q31: =--(COUNTIF($A$2:A31,A31)=1) -> 1 | R31: =IF(AND(Q31=1,I31<>"",ISNUMBER(I31),I31>=0),I31,"") -> 27.38
A32: TKT-00031 | B32: CUST-0736 | D32: Technical Bug | E32: Medium | F32: Open | G32: 2023-07-15 | J32: 24 | L32: Sanya Brar | M32: Phone | O32: TRUE | P32: =IFERROR(DATEVALUE(G32),IFERROR(DATE(RIGHT(G32,4),MID(G32,4,2),LEFT(G32,2)),"")) -> 45122 | Q32: =--(COUNTIF($A$2:A32,A32)=1) -> 1 | R32: =IF(AND(Q32=1,I32<>"",ISNUMBER(I32),I32>=0),I32,"")
A33: TKT-00032 | B33: CUST-0715 | D33: Account Management | E33: Medium | F33: Resolved | G33: 2024-05-01 | H33: 45414 | I33: 38.42 | J33: 24 | K33: No | L33: Fiyaz Chawla | M33: Phone | N33: 3.5 | O33: False | P33: =IFERROR(DATEVALUE(G33),IFERROR(DATE(RIGHT(G33,4),MID(G33,4,2),LEFT(G33,2)),"")) -> 45413 | Q33: =--(COUNTIF($A$2:A33,A33)=1) -> 1 | R33: =IF(AND(Q33=1,I33<>"",ISNUMBER(I33),I33>=0),I33,"") -> 38.42
A34: TKT-00033 | B34: CUST-0148 | D34: Onboarding Support | E34: Low | F34: Resolved | G34: 2022-06-04 | H34: 44724 | I34: 215.2 | J34: 72 | K34: No | L34: Dayamai Karnik | M34: Help Portal | O34: TRUE | P34: =IFERROR(DATEVALUE(G34),IFERROR(DATE(RIGHT(G34,4),MID(G34,4,2),LEFT(G34,2)),"")) -> 44716 | Q34: =--(COUNTIF($A$2:A34,A34)=1) -> 1 | R34: =IF(AND(Q34=1,I34<>"",ISNUMBER(I34),I34>=0),I34,"") -> 215.2
A35: TKT-00034 | B35: CUST-0274 | D35: Access & Permissions | E35: Medium | F35: In Progress | G35: 2024-02-09 | J35: 24 | L35: Odika Ganesh | M35: In-App Chat | O35: 0 | P35: =IFERROR(DATEVALUE(G35),IFERROR(DATE(RIGHT(G35,4),MID(G35,4,2),LEFT(G35,2)),"")) -> 45331 | Q35: =--(COUNTIF($A$2:A35,A35)=1) -> 1 | R35: =IF(AND(Q35=1,I35<>"",ISNUMBER(I35),I35>=0),I35,"")
A36: TKT-00035 | B36: CUST-0276 | D36: Integration Issue | E36: Low | F36: Resolved | G36: 2025-01-29 | H36: 45693 | I36: 171.42 | J36: 72 | K36: No | L36: Chatura Bal | M36: Email | O36: True | P36: =IFERROR(DATEVALUE(G36),IFERROR(DATE(RIGHT(G36,4),MID(G36,4,2),LEFT(G36,2)),"")) -> 45686 | Q36: =--(COUNTIF($A$2:A36,A36)=1) -> 1 | R36: =IF(AND(Q36=1,I36<>"",ISNUMBER(I36),I36>=0),I36,"") -> 171.42
A37: TKT-00036 | B37: CUST-0971 | D37: Integration Issue | E37: Critical | F37: In Progress | G37: 2022-08-27 | J37: 4 | L37: Advaith Acharya | M37: In-App Chat | O37: FALSE | P37: =IFERROR(DATEVALUE(G37),IFERROR(DATE(RIGHT(G37,4),MID(G37,4,2),LEFT(G37,2)),"")) -> 44800 | Q37: =--(COUNTIF($A$2:A37,A37)=1) -> 1 | R37: =IF(AND(Q37=1,I37<>"",ISNUMBER(I37),I37>=0),I37,"")
A38: TKT-00037 | B38: CUST-1409 | D38: Billing & Payments | E38: Critical | F38: Resolved | G38: 2022-08-22 | H38: 44795 | I38: 6.22 | J38: 4 | K38: No | L38: Dayita Palan | M38: Phone | N38: 2 | O38: 0 | P38: =IFERROR(DATEVALUE(G38),IFERROR(DATE(RIGHT(G38,4),MID(G38,4,2),LEFT(G38,2)),"")) -> 44795 | Q38: =--(COUNTIF($A$2:A38,A38)=1) -> 1 | R38: =IF(AND(Q38=1,I38<>"",ISNUMBER(I38),I38>=0),I38,"") -> 6.22
A39: TKT-00038 | B39: CUST-1053 | D39: Data Discrepancy | E39: Low | F39: Resolved | G39: 2024-08-14 | H39: 45524 | I39: 158.09 | J39: 72 | K39: No | L39: Dipta Nadig | M39: Help Portal | N39: 4.9 | O39: False | P39: =IFERROR(DATEVALUE(G39),IFERROR(DATE(RIGHT(G39,4),MID(G39,4,2),LEFT(G39,2)),"")) -> 45518 | Q39: =--(COUNTIF($A$2:A39,A39)=1) -> 1 | R39: =IF(AND(Q39=1,I39<>"",ISNUMBER(I39),I39>=0),I39,"") -> 158.09
A40: TKT-00039 | B40: CUST-0797 | D40: Performance Issue | E40: Low | F40: In Progress | G40: 2024-08-26 | J40: 72 | L40: Eshana Soni | M40: Help Portal | O40: No | P40: =IFERROR(DATEVALUE(G40),IFERROR(DATE(RIGHT(G40,4),MID(G40,4,2),LEFT(G40,2)),"")) -> 45530 | Q40: =--(COUNTIF($A$2:A40,A40)=1) -> 1 | R40: =IF(AND(Q40=1,I40<>"",ISNUMBER(I40),I40>=0),I40,"")
A41: TKT-00040 | B41: CUST-0606 | C41: DL-01203 | D41: Data Discrepancy | E41: High | F41: Resolved | G41: 2023-10-10 | H41: 45209 | I41: 11.49 | J41: 8 | K41: No | L41: Dayamai Karnik | M41: Email | O41: True | P41: =IFERROR(DATEVALUE(G41),IFERROR(DATE(RIGHT(G41,4),MID(G41,4,2),LEFT(G41,2)),"")) -> 45209 | Q41: =--(COUNTIF($A$2:A41,A41)=1) -> 1 | R41: =IF(AND(Q41=1,I41<>"",ISNUMBER(I41),I41>=0),I41,"") -> 11.49
A42: TKT-00041 | B42: CUST-0054 | D42: Feature Request | E42: High | F42: Resolved | G42: 2022-03-18 | H42: 44638 | I42: 14.45 | J42: 8 | K42: No | L42: Bhavini Sheth | M42: In-App Chat | N42: 3.9 | O42: 0 | P42: =IFERROR(DATEVALUE(G42),IFERROR(DATE(RIGHT(G42,4),MID(G42,4,2),LEFT(G42,2)),"")) -> 44638 | Q42: =--(COUNTIF($A$2:A42,A42)=1) -> 1 | R42: =IF(AND(Q42=1,I42<>"",ISNUMBER(I42),I42>=0),I42,"") -> 14.45
A43: TKT-00042 | B43: CUST-0620 | C43: DL-00047 | D43: Integration Issue | E43: Critical | F43: Resolved | G43: 30/04/2022 | H43: 44681 | I43: 10.18 | J43: 4 | K43: No | L43: Arin Dass | M43: Phone | O43: False | P43: =IFERROR(DATEVALUE(G43),IFERROR(DATE(RIGHT(G43,4),MID(G43,4,2),LEFT(G43,2)),"")) -> 44681 | Q43: =--(COUNTIF($A$2:A43,A43)=1) -> 1 | R43: =IF(AND(Q43=1,I43<>"",ISNUMBER(I43),I43>=0),I43,"") -> 10.18
A44: TKT-00043 | B44: CUST-0832 | C44: DL-00376 | D44: Performance Issue | E44: High | F44: Resolved | G44: 2024-10-19 | H44: 45584 | I44: 14.45 | J44: 8 | K44: No | L44: Bhanumati Savant | M44: In-App Chat | N44: 4.4 | O44: 0 | P44: =IFERROR(DATEVALUE(G44),IFERROR(DATE(RIGHT(G44,4),MID(G44,4,2),LEFT(G44,2)),"")) -> 45584 | Q44: =--(COUNTIF($A$2:A44,A44)=1) -> 1 | R44: =IF(AND(Q44=1,I44<>"",ISNUMBER(I44),I44>=0),I44,"") -> 14.45
A45: TKT-00044 | B45: CUST-0910 | C45: DL-02120 | D45: Access & Permissions | E45: High | F45: In Progress | G45: 2023-05-28 | J45: 8 | L45: Ojas Ranganathan | M45: Help Portal | O45: True | P45: =IFERROR(DATEVALUE(G45),IFERROR(DATE(RIGHT(G45,4),MID(G45,4,2),LEFT(G45,2)),"")) -> 45074 | Q45: =--(COUNTIF($A$2:A45,A45)=1) -> 1 | R45: =IF(AND(Q45=1,I45<>"",ISNUMBER(I45),I45>=0),I45,"")
A46: TKT-00045 | B46: CUST-0754 | D46: Feature Request | E46: High | F46: Resolved | G46: 2024-08-01 | H46: 45506 | I46: 25.32 | J46: 8 | K46: No | L46: Dayamai Karnik | M46: Email | N46: 4.5 | O46: 0 | P46: =IFERROR(DATEVALUE(G46),IFERROR(DATE(RIGHT(G46,4),MID(G46,4,2),LEFT(G46,2)),"")) -> 45505 | Q46: =--(COUNTIF($A$2:A46,A46)=1) -> 1 | R46: =IF(AND(Q46=1,I46<>"",ISNUMBER(I46),I46>=0),I46,"") -> 25.32
A47: TKT-00046 | B47: CUST-0567 | C47: DL-04010 | D47: Onboarding Support | E47: Medium | F47: Resolved | G47: 2024-08-02 | J47: 24 | L47: Karan Vyas | M47: Email | O47: 1 | P47: =IFERROR(DATEVALUE(G47),IFERROR(DATE(RIGHT(G47,4),MID(G47,4,2),LEFT(G47,2)),"")) -> 45506 | Q47: =--(COUNTIF($A$2:A47,A47)=1) -> 1 | R47: =IF(AND(Q47=1,I47<>"",ISNUMBER(I47),I47>=0),I47,"")
A48: TKT-00047 | B48: CUST-0628 | D48: Access & Permissions | E48: Medium | F48: In Progress | G48: 2023-09-10 | J48: 24 | L48: Chatura Bal | M48: In-App Chat | O48: Yes | P48: =IFERROR(DATEVALUE(G48),IFERROR(DATE(RIGHT(G48,4),MID(G48,4,2),LEFT(G48,2)),"")) -> 45179 | Q48: =--(COUNTIF($A$2:A48,A48)=1) -> 1 | R48: =IF(AND(Q48=1,I48<>"",ISNUMBER(I48),I48>=0),I48,"")
A49: TKT-00048 | B49: CUST-0210 | D49: Feature Request | E49: High | F49: Resolved | G49: 2022-06-25 | H49: 44737 | I49: 15.35 | J49: 8 | K49: No | L49: Abhiram Swamy | M49: In-App Chat | O49: FALSE | P49: =IFERROR(DATEVALUE(G49),IFERROR(DATE(RIGHT(G49,4),MID(G49,4,2),LEFT(G49,2)),"")) -> 44737 | Q49: =--(COUNTIF($A$2:A49,A49)=1) -> 1 | R49: =IF(AND(Q49=1,I49<>"",ISNUMBER(I49),I49>=0),I49,"") -> 15.35
A50: TKT-00049 | B50: CUST-0755 | D50: Integration Issue | E50: Critical | F50: Resolved | G50: 2024-08-07 | H50: 45511 | I50: 4.45 | J50: 4 | K50: No | L50: Odika Ganesh | M50: Email | N50: 3.5 | O50: No | P50: =IFERROR(DATEVALUE(G50),IFERROR(DATE(RIGHT(G50,4),MID(G50,4,2),LEFT(G50,2)),"")) -> 45511 | Q50: =--(COUNTIF($A$2:A50,A50)=1) -> 1 | R50: =IF(AND(Q50=1,I50<>"",ISNUMBER(I50),I50>=0),I50,"") -> 4.45
A51: TKT-00050 | B51: CUST-0302 | C51: DL-02070 | D51: Performance Issue | E51: High | F51: Resolved | G51: 2024-02-16 | H51: 45339 | I51: 26.21 | J51: 8 | K51: No | L51: Dipta Nadig | M51: Help Portal | N51: 1.3 | O51: No | P51: =IFERROR(DATEVALUE(G51),IFERROR(DATE(RIGHT(G51,4),MID(G51,4,2),LEFT(G51,2)),"")) -> 45338 | Q51: =--(COUNTIF($A$2:A51,A51)=1) -> 1 | R51: =IF(AND(Q51=1,I51<>"",ISNUMBER(I51),I51>=0),I51,"") -> 26.21
A52: TKT-00051 | B52: CUST-1034 | C52: DL-01927 | D52: Feature Request | E52: High | F52: Resolved | G52: 2022-08-08 | H52: 44782 | I52: 24.61 | J52: 8 | K52: No | L52: Sanya Brar | M52: Email | N52: 3.3 | O52: False | P52: =IFERROR(DATEVALUE(G52),IFERROR(DATE(RIGHT(G52,4),MID(G52,4,2),LEFT(G52,2)),"")) -> 44781 | Q52: =--(COUNTIF($A$2:A52,A52)=1) -> 1 | R52: =IF(AND(Q52=1,I52<>"",ISNUMBER(I52),I52>=0),I52,"") -> 24.61
A53: TKT-00052 | B53: CUST-1014 | D53: Billing & Payments | E53: High | F53: Resolved | G53: 2025-02-05 | H53: 45693 | I53: 18.38 | J53: 8 | K53: No | L53: Oliver Nazareth | M53: Phone | N53: 2.7 | O53: True | P53: =IFERROR(DATEVALUE(G53),IFERROR(DATE(RIGHT(G53,4),MID(G53,4,2),LEFT(G53,2)),"")) -> 45693 | Q53: =--(COUNTIF($A$2:A53,A53)=1) -> 1 | R53: =IF(AND(Q53=1,I53<>"",ISNUMBER(I53),I53>=0),I53,"") -> 18.38
A54: TKT-00053 | B54: CUST-1174 | C54: DL-01605 | D54: Access & Permissions | E54: Low | F54: Resolved | G54: 2023-03-01 | H54: 44995 | I54: 216.09 | J54: 72 | K54: No | L54: Dayamai Karnik | M54: Email | N54: 1.7 | O54: TRUE | P54: =IFERROR(DATEVALUE(G54),IFERROR(DATE(RIGHT(G54,4),MID(G54,4,2),LEFT(G54,2)),"")) -> 44986 | Q54: =--(COUNTIF($A$2:A54,A54)=1) -> 1 | R54: =IF(AND(Q54=1,I54<>"",ISNUMBER(I54),I54>=0),I54,"") -> 216.09
A55: TKT-00054 | B55: CUST-1391 | D55: Onboarding Support | E55: High | F55: Resolved | G55: 2022-03-30 | J55: 8 | L55: Peter Shan | M55: Slack Integration | O55: 1 | P55: =IFERROR(DATEVALUE(G55),IFERROR(DATE(RIGHT(G55,4),MID(G55,4,2),LEFT(G55,2)),"")) -> 44650 | Q55: =--(COUNTIF($A$2:A55,A55)=1) -> 1 | R55: =IF(AND(Q55=1,I55<>"",ISNUMBER(I55),I55>=0),I55,"")
A56: TKT-00055 | B56: CUST-0364 | D56: Billing & Payments | E56: High | F56: Escalated | G56: 2022-02-25 | H56: 44617 | I56: 15.36 | J56: 8 | K56: No | L56: Ayush Banerjee | M56: In-App Chat | N56: 3.7 | O56: TRUE | P56: =IFERROR(DATEVALUE(G56),IFERROR(DATE(RIGHT(G56,4),MID(G56,4,2),LEFT(G56,2)),"")) -> 44617 | Q56: =--(COUNTIF($A$2:A56,A56)=1) -> 1 | R56: =IF(AND(Q56=1,I56<>"",ISNUMBER(I56),I56>=0),I56,"") -> 15.36
A57: TKT-00056 | B57: CUST-0726 | D57: Feature Request | E57: Medium | F57: Resolved | G57: 2023-10-31 | H57: 45230 | I57: 18.42 | J57: 24 | K57: Yes | L57: Karan Vyas | M57: Slack Integration | N57: 3.6 | O57: True | P57: =IFERROR(DATEVALUE(G57),IFERROR(DATE(RIGHT(G57,4),MID(G57,4,2),LEFT(G57,2)),"")) -> 45230 | Q57: =--(COUNTIF($A$2:A57,A57)=1) -> 1 | R57: =IF(AND(Q57=1,I57<>"",ISNUMBER(I57),I57>=0),I57,"") -> 18.42
A58: TKT-00057 | B58: CUST-1232 | C58: DL-02333 | D58: Billing & Payments | E58: Medium | F58: Resolved | G58: 2022-08-27 | H58: 44803 | I58: 74.05 | J58: 24 | K58: No | L58: Karan Vyas | M58: Phone | N58: 4.8 | O58: FALSE | P58: =IFERROR(DATEVALUE(G58),IFERROR(DATE(RIGHT(G58,4),MID(G58,4,2),LEFT(G58,2)),"")) -> 44800 | Q58: =--(COUNTIF($A$2:A58,A58)=1) -> 1 | R58: =IF(AND(Q58=1,I58<>"",ISNUMBER(I58),I58>=0),I58,"") -> 74.05
A59: TKT-00058 | B59: CUST-1336 | D59: Data Discrepancy | E59: High | F59: Resolved | G59: 2024-09-08 | H59: 45543 | I59: 7.98 | J59: 8 | K59: Yes | L59: Oliver Nazareth | M59: Help Portal | O59: TRUE | P59: =IFERROR(DATEVALUE(G59),IFERROR(DATE(RIGHT(G59,4),MID(G59,4,2),LEFT(G59,2)),"")) -> 45543 | Q59: =--(COUNTIF($A$2:A59,A59)=1) -> 1 | R59: =IF(AND(Q59=1,I59<>"",ISNUMBER(I59),I59>=0),I59,"") -> 7.98
A60: TKT-00059 | B60: CUST-0828 | C60: DL-04124 | D60: Onboarding Support | E60: Low | F60: Resolved | G60: 2023-04-23 | H60: 45041 | I60: 67.19 | J60: 72 | K60: Yes | M60: In-App Chat | N60: 2.5 | O60: No | P60: =IFERROR(DATEVALUE(G60),IFERROR(DATE(RIGHT(G60,4),MID(G60,4,2),LEFT(G60,2)),"")) -> 45039 | Q60: =--(COUNTIF($A$2:A60,A60)=1) -> 1 | R60: =IF(AND(Q60=1,I60<>"",ISNUMBER(I60),I60>=0),I60,"") -> 67.19
A61: TKT-00060 | B61: CUST-1023 | D61: Onboarding Support | E61: Medium | F61: Open | G61: 2023-12-17 | J61: 24 | L61: Dipta Nadig | M61: Help Portal | O61: 0 | P61: =IFERROR(DATEVALUE(G61),IFERROR(DATE(RIGHT(G61,4),MID(G61,4,2),LEFT(G61,2)),"")) -> 45277 | Q61: =--(COUNTIF($A$2:A61,A61)=1) -> 1 | R61: =IF(AND(Q61=1,I61<>"",ISNUMBER(I61),I61>=0),I61,"")
A62: TKT-00061 | B62: CUST-0600 | D62: Technical Bug | E62: Medium | F62: Open | G62: 2022-02-26 | J62: 24 | L62: Darika Pau | M62: Slack Integration | O62: FALSE | P62: =IFERROR(DATEVALUE(G62),IFERROR(DATE(RIGHT(G62,4),MID(G62,4,2),LEFT(G62,2)),"")) -> 44618 | Q62: =--(COUNTIF($A$2:A62,A62)=1) -> 1 | R62: =IF(AND(Q62=1,I62<>"",ISNUMBER(I62),I62>=0),I62,"")
A63: TKT-00062 | B63: CUST-0235 | D63: Feature Request | E63: Low | F63: Resolved | G63: 2024-01-08 | H63: 45304 | I63: 133.5 | J63: 72 | K63: No | L63: Bhavini Sheth | M63: Email | N63: 3.5 | O63: FALSE | P63: =IFERROR(DATEVALUE(G63),IFERROR(DATE(RIGHT(G63,4),MID(G63,4,2),LEFT(G63,2)),"")) -> 45299 | Q63: =--(COUNTIF($A$2:A63,A63)=1) -> 1 | R63: =IF(AND(Q63=1,I63<>"",ISNUMBER(I63),I63>=0),I63,"") -> 133.5
A64: TKT-00063 | B64: CUST-0262 | D64: Technical Bug | E64: Medium | F64: In Progress | G64: 2022-10-29 | J64: 24 | L64: Chatura Bal | M64: In-App Chat | O64: 1 | P64: =IFERROR(DATEVALUE(G64),IFERROR(DATE(RIGHT(G64,4),MID(G64,4,2),LEFT(G64,2)),"")) -> 44863 | Q64: =--(COUNTIF($A$2:A64,A64)=1) -> 1 | R64: =IF(AND(Q64=1,I64<>"",ISNUMBER(I64),I64>=0),I64,"")
A65: TKT-00064 | B65: CUST-1323 | D65: Integration Issue | E65: Medium | F65: Resolved | G65: 2024-04-06 | H65: 45389 | I65: 36.31 | J65: 24 | K65: No | L65: Dayita Palan | M65: Slack Integration | O65: No | P65: =IFERROR(DATEVALUE(G65),IFERROR(DATE(RIGHT(G65,4),MID(G65,4,2),LEFT(G65,2)),"")) -> 45388 | Q65: =--(COUNTIF($A$2:A65,A65)=1) -> 1 | R65: =IF(AND(Q65=1,I65<>"",ISNUMBER(I65),I65>=0),I65,"") -> 36.31
A66: TKT-00065 | B66: CUST-0175 | D66: Technical Bug | E66: High | F66: Resolved | G66: 2022-09-06 | H66: 44811 | I66: 26.71 | J66: 8 | K66: No | L66: Arin Dass | M66: Phone | N66: 4 | O66: No | P66: =IFERROR(DATEVALUE(G66),IFERROR(DATE(RIGHT(G66,4),MID(G66,4,2),LEFT(G66,2)),"")) -> 44810 | Q66: =--(COUNTIF($A$2:A66,A66)=1) -> 1 | R66: =IF(AND(Q66=1,I66<>"",ISNUMBER(I66),I66>=0),I66,"") -> 26.71
A67: TKT-00066 | B67: CUST-0164 | C67: DL-02882 | D67: Data Discrepancy | E67: Medium | F67: Open | G67: 2023-02-22 | J67: 24 | L67: Amara Rana | M67: Phone | O67: No | P67: =IFERROR(DATEVALUE(G67),IFERROR(DATE(RIGHT(G67,4),MID(G67,4,2),LEFT(G67,2)),"")) -> 44979 | Q67: =--(COUNTIF($A$2:A67,A67)=1) -> 1 | R67: =IF(AND(Q67=1,I67<>"",ISNUMBER(I67),I67>=0),I67,"")
A68: TKT-00067 | B68: CUST-0381 | C68: DL-01582 | D68: Access & Permissions | E68: Medium | F68: In Progress | G68: 2024-01-11 | J68: 24 | L68: Girish Bhatt | M68: Phone | O68: FALSE | P68: =IFERROR(DATEVALUE(G68),IFERROR(DATE(RIGHT(G68,4),MID(G68,4,2),LEFT(G68,2)),"")) -> 45302 | Q68: =--(COUNTIF($A$2:A68,A68)=1) -> 1 | R68: =IF(AND(Q68=1,I68<>"",ISNUMBER(I68),I68>=0),I68,"")
A69: TKT-00068 | B69: CUST-1230 | D69: Data Discrepancy | E69: Critical | F69: Resolved | G69: 2022-09-16 | H69: 44820 | I69: 3.19 | J69: 4 | K69: Yes | L69: Chatura Bal | M69: Phone | O69: FALSE | P69: =IFERROR(DATEVALUE(G69),IFERROR(DATE(RIGHT(G69,4),MID(G69,4,2),LEFT(G69,2)),"")) -> 44820 | Q69: =--(COUNTIF($A$2:A69,A69)=1) -> 1 | R69: =IF(AND(Q69=1,I69<>"",ISNUMBER(I69),I69>=0),I69,"") -> 3.19
A70: TKT-00069 | B70: CUST-1118 | D70: Access & Permissions | E70: Medium | F70: Escalated | G70: 2024-02-25 | J70: 24 | L70: Advaith Acharya | M70: Email | O70: False | P70: =IFERROR(DATEVALUE(G70),IFERROR(DATE(RIGHT(G70,4),MID(G70,4,2),LEFT(G70,2)),"")) -> 45347 | Q70: =--(COUNTIF($A$2:A70,A70)=1) -> 1 | R70: =IF(AND(Q70=1,I70<>"",ISNUMBER(I70),I70>=0),I70,"")
A71: TKT-00070 | B71: CUST-0340 | C71: DL-01494 | D71: Performance Issue | E71: High | F71: Resolved | G71: 2022-12-10 | J71: 8 | L71: Nidhi Bora | M71: In-App Chat | O71: 1 | P71: =IFERROR(DATEVALUE(G71),IFERROR(DATE(RIGHT(G71,4),MID(G71,4,2),LEFT(G71,2)),"")) -> 44905 | Q71: =--(COUNTIF($A$2:A71,A71)=1) -> 1 | R71: =IF(AND(Q71=1,I71<>"",ISNUMBER(I71),I71>=0),I71,"")
A72: TKT-00071 | B72: CUST-0534 | C72: DL-00723 | D72: Billing & Payments | E72: Medium | F72: In Progress | G72: 2024-12-07 | J72: 24 | L72: Eshana Soni | M72: Slack Integration | O72: False | P72: =IFERROR(DATEVALUE(G72),IFERROR(DATE(RIGHT(G72,4),MID(G72,4,2),LEFT(G72,2)),"")) -> 45633 | Q72: =--(COUNTIF($A$2:A72,A72)=1) -> 1 | R72: =IF(AND(Q72=1,I72<>"",ISNUMBER(I72),I72>=0),I72,"")
A73: TKT-00072 | B73: CUST-1030 | C73: DL-01151 | D73: Onboarding Support | E73: Low | F73: Resolved | G73: 2023-08-14 | H73: 45157 | I73: 125.72 | J73: 72 | K73: No | L73: Peter Shan | M73: In-App Chat | O73: False | P73: =IFERROR(DATEVALUE(G73),IFERROR(DATE(RIGHT(G73,4),MID(G73,4,2),LEFT(G73,2)),"")) -> 45152 | Q73: =--(COUNTIF($A$2:A73,A73)=1) -> 1 | R73: =IF(AND(Q73=1,I73<>"",ISNUMBER(I73),I73>=0),I73,"") -> 125.72
A74: TKT-00073 | B74: CUST-0785 | D74: Billing & Payments | E74: High | F74: Open | G74: 2023-11-05 | J74: 8 | L74: Ayush Banerjee | M74: Phone | O74: 1 | P74: =IFERROR(DATEVALUE(G74),IFERROR(DATE(RIGHT(G74,4),MID(G74,4,2),LEFT(G74,2)),"")) -> 45235 | Q74: =--(COUNTIF($A$2:A74,A74)=1) -> 1 | R74: =IF(AND(Q74=1,I74<>"",ISNUMBER(I74),I74>=0),I74,"")
A75: TKT-00074 | B75: CUST-1354 | C75: DL-00312 | D75: Access & Permissions | E75: Medium | F75: Escalated | G75: 2023-05-15 | H75: 45062 | I75: 29.19 | J75: 24 | K75: No | L75: Dayita Palan | M75: Help Portal | N75: 4.8 | O75: FALSE | P75: =IFERROR(DATEVALUE(G75),IFERROR(DATE(RIGHT(G75,4),MID(G75,4,2),LEFT(G75,2)),"")) -> 45061 | Q75: =--(COUNTIF($A$2:A75,A75)=1) -> 1 | R75: =IF(AND(Q75=1,I75<>"",ISNUMBER(I75),I75>=0),I75,"") -> 29.19
A76: TKT-00075 | B76: CUST-0769 | C76: DL-02279 | D76: Onboarding Support | E76: Medium | F76: Resolved | G76: 05/10/2022 | H76: 44841 | I76: 60.31 | J76: 24 | K76: No | L76: Anita Saxena | M76: Phone | N76: 3.2 | O76: False | P76: =IFERROR(DATEVALUE(G76),IFERROR(DATE(RIGHT(G76,4),MID(G76,4,2),LEFT(G76,2)),"")) -> 44839 | Q76: =--(COUNTIF($A$2:A76,A76)=1) -> 1 | R76: =IF(AND(Q76=1,I76<>"",ISNUMBER(I76),I76>=0),I76,"") -> 60.31
A77: TKT-00076 | B77: CUST-0040 | C77: DL-00083 | D77: Integration Issue | E77: Medium | F77: Resolved | G77: 2024-08-14 | H77: 45520 | I77: 54.97 | J77: 24 | K77: No | L77: Oliver Nazareth | M77: Help Portal | N77: 3.5 | O77: TRUE | P77: =IFERROR(DATEVALUE(G77),IFERROR(DATE(RIGHT(G77,4),MID(G77,4,2),LEFT(G77,2)),"")) -> 45518 | Q77: =--(COUNTIF($A$2:A77,A77)=1) -> 1 | R77: =IF(AND(Q77=1,I77<>"",ISNUMBER(I77),I77>=0),I77,"") -> 54.97
A78: TKT-00077 | B78: CUST-0200 | D78: Feature Request | E78: Medium | F78: In Progress | G78: 2022-09-19 | J78: 24 | L78: Abhiram Swamy | M78: Slack Integration | O78: False | P78: =IFERROR(DATEVALUE(G78),IFERROR(DATE(RIGHT(G78,4),MID(G78,4,2),LEFT(G78,2)),"")) -> 44823 | Q78: =--(COUNTIF($A$2:A78,A78)=1) -> 1 | R78: =IF(AND(Q78=1,I78<>"",ISNUMBER(I78),I78>=0),I78,"")
A79: TKT-00078 | B79: CUST-0134 | D79: Billing & Payments | E79: Medium | F79: Resolved | G79: 2024-02-24 | J79: 24 | L79: Amara Rana | M79: Help Portal | O79: 1 | P79: =IFERROR(DATEVALUE(G79),IFERROR(DATE(RIGHT(G79,4),MID(G79,4,2),LEFT(G79,2)),"")) -> 45346 | Q79: =--(COUNTIF($A$2:A79,A79)=1) -> 1 | R79: =IF(AND(Q79=1,I79<>"",ISNUMBER(I79),I79>=0),I79,"")
A80: TKT-00079 | B80: CUST-0651 | D80: Integration Issue | E80: Medium | F80: Escalated | G80: 2022-10-06 | H80: 44841 | I80: 44.01 | J80: 24 | K80: No | L80: Ojas Ranganathan | M80: Help Portal | O80: FALSE | P80: =IFERROR(DATEVALUE(G80),IFERROR(DATE(RIGHT(G80,4),MID(G80,4,2),LEFT(G80,2)),"")) -> 44840 | Q80: =--(COUNTIF($A$2:A80,A80)=1) -> 1 | R80: =IF(AND(Q80=1,I80<>"",ISNUMBER(I80),I80>=0),I80,"") -> 44.01
A81: TKT-00080 | B81: CUST-1394 | C81: DL-02335 | D81: Technical Bug | E81: Medium | F81: In Progress | G81: 2024-01-30 | J81: 24 | L81: Ayush Banerjee | M81: Help Portal | O81: 0 | P81: =IFERROR(DATEVALUE(G81),IFERROR(DATE(RIGHT(G81,4),MID(G81,4,2),LEFT(G81,2)),"")) -> 45321 | Q81: =--(COUNTIF($A$2:A81,A81)=1) -> 1 | R81: =IF(AND(Q81=1,I81<>"",ISNUMBER(I81),I81>=0),I81,"")
A82: TKT-00081 | B82: CUST-0108 | C82: DL-01254 | D82: Account Management | E82: Medium | F82: Resolved | G82: 2022-02-17 | H82: 44611 | I82: 50.33 | J82: 24 | K82: No | L82: Neel Oza | M82: Phone | N82: 3.8 | O82: No | P82: =IFERROR(DATEVALUE(G82),IFERROR(DATE(RIGHT(G82,4),MID(G82,4,2),LEFT(G82,2)),"")) -> 44609 | Q82: =--(COUNTIF($A$2:A82,A82)=1) -> 1 | R82: =IF(AND(Q82=1,I82<>"",ISNUMBER(I82),I82>=0),I82,"") -> 50.33
A83: TKT-00082 | B83: CUST-0060 | D83: Performance Issue | E83: High | F83: In Progress | G83: 2023-01-18 | J83: 8 | L83: Ayush Banerjee | M83: Email | O83: False | P83: =IFERROR(DATEVALUE(G83),IFERROR(DATE(RIGHT(G83,4),MID(G83,4,2),LEFT(G83,2)),"")) -> 44944 | Q83: =--(COUNTIF($A$2:A83,A83)=1) -> 1 | R83: =IF(AND(Q83=1,I83<>"",ISNUMBER(I83),I83>=0),I83,"")
A84: TKT-00083 | B84: CUST-1130 | D84: Billing & Payments | E84: Low | F84: Resolved | G84: 2022-05-22 | H84: 44706 | I84: 85.71 | J84: 72 | K84: No | L84: Karan Vyas | M84: Email | N84: 2.3 | O84: No | P84: =IFERROR(DATEVALUE(G84),IFERROR(DATE(RIGHT(G84,4),MID(G84,4,2),LEFT(G84,2)),"")) -> 44703 | Q84: =--(COUNTIF($A$2:A84,A84)=1) -> 1 | R84: =IF(AND(Q84=1,I84<>"",ISNUMBER(I84),I84>=0),I84,"") -> 85.71
A85: TKT-00084 | B85: CUST-1145 | C85: DL-01140 | D85: Integration Issue | E85: Medium | F85: Resolved | G85: 2022-09-29 | H85: 44833 | I85: 6.19 | J85: 24 | K85: Yes | L85: Karan Vyas | M85: Phone | O85: False | P85: =IFERROR(DATEVALUE(G85),IFERROR(DATE(RIGHT(G85,4),MID(G85,4,2),LEFT(G85,2)),"")) -> 44833 | Q85: =--(COUNTIF($A$2:A85,A85)=1) -> 1 | R85: =IF(AND(Q85=1,I85<>"",ISNUMBER(I85),I85>=0),I85,"") -> 6.19
A86: TKT-00085 | B86: CUST-0948 | D86: Data Discrepancy | E86: Low | F86: Escalated | G86: 14/02/2023 | H86: 44978 | I86: 174.38 | J86: 72 | K86: No | L86: Girish Bhatt | M86: Email | N86: 4.8 | O86: 1 | P86: =IFERROR(DATEVALUE(G86),IFERROR(DATE(RIGHT(G86,4),MID(G86,4,2),LEFT(G86,2)),"")) -> 44971 | Q86: =--(COUNTIF($A$2:A86,A86)=1) -> 1 | R86: =IF(AND(Q86=1,I86<>"",ISNUMBER(I86),I86>=0),I86,"") -> 174.38
A87: TKT-00086 | B87: CUST-1397 | C87: DL-02087 | D87: Feature Request | E87: Low | F87: Resolved | G87: 2024-10-17 | H87: 45592 | I87: 247.32 | J87: 72 | K87: No | L87: Zayan Buch | M87: Email | O87: 0 | P87: =IFERROR(DATEVALUE(G87),IFERROR(DATE(RIGHT(G87,4),MID(G87,4,2),LEFT(G87,2)),"")) -> 45582 | Q87: =--(COUNTIF($A$2:A87,A87)=1) -> 1 | R87: =IF(AND(Q87=1,I87<>"",ISNUMBER(I87),I87>=0),I87,"") -> 247.32
A88: TKT-00087 | B88: CUST-0141 | D88: Access & Permissions | E88: Medium | F88: Open | G88: 2022-10-19 | J88: 24 | M88: Email | O88: 0 | P88: =IFERROR(DATEVALUE(G88),IFERROR(DATE(RIGHT(G88,4),MID(G88,4,2),LEFT(G88,2)),"")) -> 44853 | Q88: =--(COUNTIF($A$2:A88,A88)=1) -> 1 | R88: =IF(AND(Q88=1,I88<>"",ISNUMBER(I88),I88>=0),I88,"")
A89: TKT-00088 | B89: CUST-1462 | C89: DL-03862 | D89: Feature Request | E89: Low | F89: Resolved | G89: 2024-01-24 | H89: 45317 | I89: 54.1 | J89: 72 | K89: Yes | L89: Neel Oza | M89: Phone | N89: 2.6 | O89: FALSE | P89: =IFERROR(DATEVALUE(G89),IFERROR(DATE(RIGHT(G89,4),MID(G89,4,2),LEFT(G89,2)),"")) -> 45315 | Q89: =--(COUNTIF($A$2:A89,A89)=1) -> 1 | R89: =IF(AND(Q89=1,I89<>"",ISNUMBER(I89),I89>=0),I89,"") -> 54.1
A90: TKT-00089 | B90: CUST-0477 | D90: Account Management | E90: High | F90: Resolved | G90: 2022-10-08 | H90: 44842 | I90: 7.45 | J90: 8 | K90: Yes | M90: Slack Integration | N90: 1.9 | O90: Yes | P90: =IFERROR(DATEVALUE(G90),IFERROR(DATE(RIGHT(G90,4),MID(G90,4,2),LEFT(G90,2)),"")) -> 44842 | Q90: =--(COUNTIF($A$2:A90,A90)=1) -> 1 | R90: =IF(AND(Q90=1,I90<>"",ISNUMBER(I90),I90>=0),I90,"") -> 7.45
A91: TKT-00090 | B91: CUST-0586 | D91: Access & Permissions | E91: Medium | F91: Resolved | G91: 2022-06-16 | H91: 44729 | I91: 39.51 | J91: 24 | K91: No | L91: Arin Dass | M91: Email | O91: FALSE | P91: =IFERROR(DATEVALUE(G91),IFERROR(DATE(RIGHT(G91,4),MID(G91,4,2),LEFT(G91,2)),"")) -> 44728 | Q91: =--(COUNTIF($A$2:A91,A91)=1) -> 1 | R91: =IF(AND(Q91=1,I91<>"",ISNUMBER(I91),I91>=0),I91,"") -> 39.51
A92: TKT-00091 | B92: CUST-0020 | D92: Data Discrepancy | E92: Medium | F92: Escalated | G92: 2025-01-21 | H92: 45678 | I92: 1.45 | J92: 24 | K92: Yes | L92: Amara Rana | M92: In-App Chat | N92: 2.9 | O92: True | P92: =IFERROR(DATEVALUE(G92),IFERROR(DATE(RIGHT(G92,4),MID(G92,4,2),LEFT(G92,2)),"")) -> 45678 | Q92: =--(COUNTIF($A$2:A92,A92)=1) -> 1 | R92: =IF(AND(Q92=1,I92<>"",ISNUMBER(I92),I92>=0),I92,"") -> 1.45
A93: TKT-00092 | B93: CUST-0767 | C93: DL-04041 | D93: Technical Bug | E93: Medium | F93: Resolved | G93: 2022-02-14 | H93: 44608 | I93: 55.74 | J93: 24 | K93: No | L93: Anita Saxena | M93: Slack Integration | N93: 3.1 | O93: False | P93: =IFERROR(DATEVALUE(G93),IFERROR(DATE(RIGHT(G93,4),MID(G93,4,2),LEFT(G93,2)),"")) -> 44606 | Q93: =--(COUNTIF($A$2:A93,A93)=1) -> 1 | R93: =IF(AND(Q93=1,I93<>"",ISNUMBER(I93),I93>=0),I93,"") -> 55.74
A94: TKT-00093 | B94: CUST-1285 | D94: Technical Bug | E94: Low | F94: In Progress | G94: 2025-01-10 | J94: 72 | L94: Nidhi Bora | M94: Slack Integration | O94: True | P94: =IFERROR(DATEVALUE(G94),IFERROR(DATE(RIGHT(G94,4),MID(G94,4,2),LEFT(G94,2)),"")) -> 45667 | Q94: =--(COUNTIF($A$2:A94,A94)=1) -> 1 | R94: =IF(AND(Q94=1,I94<>"",ISNUMBER(I94),I94>=0),I94,"")
A95: TKT-00094 | B95: CUST-0491 | C95: DL-00625 | D95: Technical Bug | E95: High | F95: Resolved | G95: 2023-03-15 | H95: 45000 | I95: 18.78 | J95: 8 | K95: No | M95: Slack Integration | N95: 4.3 | O95: False | P95: =IFERROR(DATEVALUE(G95),IFERROR(DATE(RIGHT(G95,4),MID(G95,4,2),LEFT(G95,2)),"")) -> 45000 | Q95: =--(COUNTIF($A$2:A95,A95)=1) -> 1 | R95: =IF(AND(Q95=1,I95<>"",ISNUMBER(I95),I95>=0),I95,"") -> 18.78
A96: TKT-00095 | B96: CUST-1496 | C96: DL-03298 | D96: Data Discrepancy | E96: High | F96: Resolved | G96: 2022-07-11 | H96: 44753 | I96: 18.84 | J96: 8 | K96: No | L96: Nidhi Bora | M96: Email | O96: False | P96: =IFERROR(DATEVALUE(G96),IFERROR(DATE(RIGHT(G96,4),MID(G96,4,2),LEFT(G96,2)),"")) -> 44753 | Q96: =--(COUNTIF($A$2:A96,A96)=1) -> 1 | R96: =IF(AND(Q96=1,I96<>"",ISNUMBER(I96),I96>=0),I96,"") -> 18.84
A97: TKT-00096 | B97: CUST-1132 | D97: Account Management | E97: Medium | F97: Resolved | G97: 2024-12-12 | J97: 24 | L97: Sai Patil | M97: Phone | O97: False | P97: =IFERROR(DATEVALUE(G97),IFERROR(DATE(RIGHT(G97,4),MID(G97,4,2),LEFT(G97,2)),"")) -> 45638 | Q97: =--(COUNTIF($A$2:A97,A97)=1) -> 1 | R97: =IF(AND(Q97=1,I97<>"",ISNUMBER(I97),I97>=0),I97,"")
A98: TKT-00097 | B98: CUST-0590 | C98: DL-02099 | D98: Account Management | E98: Medium | F98: Resolved | G98: 2023-04-07 | H98: 45023 | I98: 14.82 | J98: 24 | K98: Yes | L98: Advaith Acharya | M98: Phone | N98: 2.6 | O98: True | P98: =IFERROR(DATEVALUE(G98),IFERROR(DATE(RIGHT(G98,4),MID(G98,4,2),LEFT(G98,2)),"")) -> 45023 | Q98: =--(COUNTIF($A$2:A98,A98)=1) -> 1 | R98: =IF(AND(Q98=1,I98<>"",ISNUMBER(I98),I98>=0),I98,"") -> 14.82
A99: TKT-00098 | B99: CUST-1136 | C99: DL-00839 | D99: Integration Issue | E99: Low | F99: Resolved | G99: 2023-08-30 | H99: 45170 | I99: 66.87 | J99: 72 | K99: Yes | L99: Odika Ganesh | M99: Help Portal | N99: 1.6 | O99: True | P99: =IFERROR(DATEVALUE(G99),IFERROR(DATE(RIGHT(G99,4),MID(G99,4,2),LEFT(G99,2)),"")) -> 45168 | Q99: =--(COUNTIF($A$2:A99,A99)=1) -> 1 | R99: =IF(AND(Q99=1,I99<>"",ISNUMBER(I99),I99>=0),I99,"") -> 66.87
A100: TKT-00099 | B100: CUST-0126 | D100: Billing & Payments | E100: High | F100: Resolved | G100: 2024-02-16 | H100: 45338 | I100: 5.06 | J100: 8 | K100: Yes | L100: Bhavini Sheth | M100: In-App Chat | O100: False | P100: =IFERROR(DATEVALUE(G100),IFERROR(DATE(RIGHT(G100,4),MID(G100,4,2),LEFT(G100,2)),"")) -> 45338 | Q100: =--(COUNTIF($A$2:A100,A100)=1) -> 1 | R100: =IF(AND(Q100=1,I100<>"",ISNUMBER(I100),I100>=0),I100,"") -> 5.06
...

Sheet Sales_Pipeline
A1: Deal_ID | B1: Customer_ID | C1: Campaign_ID | D1: Service_Line | E1: Sales_Stage | F1: Deal_Value_USD | G1: Deal_Source | H1: Sales_Rep_Name | I1: Created_Date | J1: Expected_Close_Date | K1: Closed_Date | L1: Days_to_Close | M1: Upsell_Flag | N1: Products_Sold | O1: Discount_Pct | P1: Region | Q1: Deal_Value_Clean | R1: Deal_Value_Unique
A2: DL-00001 | B2: CUST-1258 | D2: WorkHub Core | E2: Negotiation | F2: 7902 | G2: Paid Search | H2: Nihal Bhasin | I2: 2022-03-15 | J2: 44803 | M2: 0 | N2: 1 | O2: 3.6 | P2: Middle East | Q2: =IFERROR(IF(RIGHT(UPPER(TRIM(F2)),1)="K",VALUE(SUBSTITUTE(SUBSTITUTE(LEFT(TRIM(F2),LEN(TRIM(F2))-1),"$",""),",",""))*1000,IF(RIGHT(UPPER(TRIM(F2)),1)="M",VALUE(SUBSTITUTE(SUBSTITUTE(LEFT(TRIM(F2),LEN(TRIM(F2))-1),"$",""),",",""))*1000000,VALUE(SUBSTITUTE(SUBSTITUTE(TRIM(F2),"$",""),",","")))),"") -> 7902 | R2: =IF(COUNTIF($A$2:A2,A2)=1,Q2,"") -> 7902
A3: DL-00002 | B3: CUST-0652 | D3: WorkHub Core | E3: Proposal | F3: 3K | G3: LinkedIn Ads | H3: Ati Seshadri | I3: 2023-06-06 | J3: 45144 | M3: 0 | N3: 1 | O3: 12.6 | P3: Southeast Asia | Q3: =IFERROR(IF(RIGHT(UPPER(TRIM(F3)),1)="K",VALUE(SUBSTITUTE(SUBSTITUTE(LEFT(TRIM(F3),LEN(TRIM(F3))-1),"$",""),",",""))*1000,IF(RIGHT(UPPER(TRIM(F3)),1)="M",VALUE(SUBSTITUTE(SUBSTITUTE(LEFT(TRIM(F3),LEN(TRIM(F3))-1),"$",""),",",""))*1000000,VALUE(SUBSTITUTE(SUBSTITUTE(TRIM(F3),"$",""),",","")))),"") -> 3000 | R3: =IF(COUNTIF($A$2:A3,A3)=1,Q3,"") -> 3000
A4: DL-00003 | B4: CUST-0657 | C4: CMP-258 | D4: WorkHub Enterprise | E4: Negotiation | F4: $81,996 | G4: Product-Led Signup | H4: Karan Karnik | I4: 2023-02-05 | J4: 45054 | M4: 0 | N4: 1 | P4: ANZ | Q4: =IFERROR(IF(RIGHT(UPPER(TRIM(F4)),1)="K",VALUE(SUBSTITUTE(SUBSTITUTE(LEFT(TRIM(F4),LEN(TRIM(F4))-1),"$",""),",",""))*1000,IF(RIGHT(UPPER(TRIM(F4)),1)="M",VALUE(SUBSTITUTE(SUBSTITUTE(LEFT(TRIM(F4),LEN(TRIM(F4))-1),"$",""),",",""))*1000000,VALUE(SUBSTITUTE(SUBSTITUTE(TRIM(F4),"$",""),",","")))),"") -> 81996 | R4: =IF(COUNTIF($A$2:A4,A4)=1,Q4,"") -> 81996
A5: DL-00004 | B5: CUST-1189 | D5: WorkHub Enterprise | E5: Prospecting | F5: $151,127 | G5: Event | H5: rachit lall | I5: 2024-02-06 | J5: 45472 | M5: 0 | N5: 1 | O5: 2.5 | P5: ANZ | Q5: =IFERROR(IF(RIGHT(UPPER(TRIM(F5)),1)="K",VALUE(SUBSTITUTE(SUBSTITUTE(LEFT(TRIM(F5),LEN(TRIM(F5))-1),"$",""),",",""))*1000,IF(RIGHT(UPPER(TRIM(F5)),1)="M",VALUE(SUBSTITUTE(SUBSTITUTE(LEFT(TRIM(F5),LEN(TRIM(F5))-1),"$",""),",",""))*1000000,VALUE(SUBSTITUTE(SUBSTITUTE(TRIM(F5),"$",""),",","")))),"") -> 151127 | R5: =IF(COUNTIF($A$2:A5,A5)=1,Q5,"") -> 151127
A6: DL-00005 | B6: CUST-1278 | C6: CMP-184 | D6: WorkHub Pro | E6: Demo | F6: 19,891 | G6: Webinar | H6: Ati Seshadri | I6: 2023-04-23 | J6: 45181 | M6: 0 | N6: 1 | O6: 27.8 | P6: South Asia | Q6: =IFERROR(IF(RIGHT(UPPER(TRIM(F6)),1)="K",VALUE(SUBSTITUTE(SUBSTITUTE(LEFT(TRIM(F6),LEN(TRIM(F6))-1),"$",""),",",""))*1000,IF(RIGHT(UPPER(TRIM(F6)),1)="M",VALUE(SUBSTITUTE(SUBSTITUTE(LEFT(TRIM(F6),LEN(TRIM(F6))-1),"$",""),",",""))*1000000,VALUE(SUBSTITUTE(SUBSTITUTE(TRIM(F6),"$",""),",","")))),"") -> 19891 | R6: =IF(COUNTIF($A$2:A6,A6)=1,Q6,"") -> 19891
A7: DL-00006 | B7: CUST-0818 | D7: WorkHub Enterprise | E7: Proposal | F7: $73,353 | G7: LinkedIn Ads | H7: Jairaj Panchal | I7: 2022-11-19 | J7: 44917 | M7: 0 | N7: 1 | O7: 30.3 | P7: Southeast Asia | Q7: =IFERROR(IF(RIGHT(UPPER(TRIM(F7)),1)="K",VALUE(SUBSTITUTE(SUBSTITUTE(LEFT(TRIM(F7),LEN(TRIM(F7))-1),"$",""),",",""))*1000,IF(RIGHT(UPPER(TRIM(F7)),1)="M",VALUE(SUBSTITUTE(SUBSTITUTE(LEFT(TRIM(F7),LEN(TRIM(F7))-1),"$",""),",",""))*1000000,VALUE(SUBSTITUTE(SUBSTITUTE(TRIM(F7),"$",""),",","")))),"") -> 73353 | R7: =IF(COUNTIF($A$2:A7,A7)=1,Q7,"") -> 73353
A8: DL-00007 | B8: CUST-0647 | D8: API Access | E8: Demo | F8: 7K | G8: Product-Led Signup | H8: Anamika Keer | I8: 2024-04-16 | J8: 45488 | M8: 0 | N8: 1 | P8: Middle East | Q8: =IFERROR(IF(RIGHT(UPPER(TRIM(F8)),1)="K",VALUE(SUBSTITUTE(SUBSTITUTE(LEFT(TRIM(F8),LEN(TRIM(F8))-1),"$",""),",",""))*1000,IF(RIGHT(UPPER(TRIM(F8)),1)="M",VALUE(SUBSTITUTE(SUBSTITUTE(LEFT(TRIM(F8),LEN(TRIM(F8))-1),"$",""),",",""))*1000000,VALUE(SUBSTITUTE(SUBSTITUTE(TRIM(F8),"$",""),",","")))),"") -> 7000 | R8: =IF(COUNTIF($A$2:A8,A8)=1,Q8,"") -> 7000
A9: DL-00008 | B9: CUST-0056 | D9: API Access | E9: Demo | F9: 4K | G9: Webinar | H9: Karan Karnik | I9: 24/03/2022 | J9: 44716 | M9: 0 | N9: 1 | O9: 5.5 | P9: Southeast Asia | Q9: =IFERROR(IF(RIGHT(UPPER(TRIM(F9)),1)="K",VALUE(SUBSTITUTE(SUBSTITUTE(LEFT(TRIM(F9),LEN(TRIM(F9))-1),"$",""),",",""))*1000,IF(RIGHT(UPPER(TRIM(F9)),1)="M",VALUE(SUBSTITUTE(SUBSTITUTE(LEFT(TRIM(F9),LEN(TRIM(F9))-1),"$",""),",",""))*1000000,VALUE(SUBSTITUTE(SUBSTITUTE(TRIM(F9),"$",""),",","")))),"") -> 4000 | R9: =IF(COUNTIF($A$2:A9,A9)=1,Q9,"") -> 4000
A10: DL-00009 | B10: CUST-0355 | C10: CMP-054 | D10: WorkHub Core | E10: Demo | F10: 8,506 | G10: Partner Referral | H10: Shivani Natt | I10: 2022-11-11 | J10: 45028 | M10: 0 | N10: 1 | O10: 14.1 | P10: South Asia | Q10: =IFERROR(IF(RIGHT(UPPER(TRIM(F10)),1)="K",VALUE(SUBSTITUTE(SUBSTITUTE(LEFT(TRIM(F10),LEN(TRIM(F10))-1),"$",""),",",""))*1000,IF(RIGHT(UPPER(TRIM(F10)),1)="M",VALUE(SUBSTITUTE(SUBSTITUTE(LEFT(TRIM(F10),LEN(TRIM(F10))-1),"$",""),",",""))*1000000,VALUE(SUBSTITUTE(SUBSTITUTE(TRIM(F10),"$",""),",","")))),"") -> 8506 | R10: =IF(COUNTIF($A$2:A10,A10)=1,Q10,"") -> 8506
A11: DL-00010 | B11: CUST-0537 | C11: CMP-327 | D11: API Access | E11: Proposal | F11: $4,469 | G11: Product-Led Signup | H11: Mason Solanki | I11: 2022-01-02 | J11: 44723 | M11: 0 | N11: 1 | O11: 32 | P11: Southeast Asia | Q11: =IFERROR(IF(RIGHT(UPPER(TRIM(F11)),1)="K",VALUE(SUBSTITUTE(SUBSTITUTE(LEFT(TRIM(F11),LEN(TRIM(F11))-1),"$",""),",",""))*1000,IF(RIGHT(UPPER(TRIM(F11)),1)="M",VALUE(SUBSTITUTE(SUBSTITUTE(LEFT(TRIM(F11),LEN(TRIM(F11))-1),"$",""),",",""))*1000000,VALUE(SUBSTITUTE(SUBSTITUTE(TRIM(F11),"$",""),",","")))),"") -> 4469 | R11: =IF(COUNTIF($A$2:A11,A11)=1,Q11,"") -> 4469
A12: DL-00011 | B12: CUST-1067 | C12: CMP-224 | D12: WorkHub Enterprise | E12: Closed Won | F12: $178,212 | G12: Product-Led Signup | H12: Owen Mane | I12: 29/09/2023 | J12: 45324 | K12: 45273 | L12: 75 | M12: 1 | N12: 2 | O12: 3.9 | P12: Southeast Asia | Q12: =IFERROR(IF(RIGHT(UPPER(TRIM(F12)),1)="K",VALUE(SUBSTITUTE(SUBSTITUTE(LEFT(TRIM(F12),LEN(TRIM(F12))-1),"$",""),",",""))*1000,IF(RIGHT(UPPER(TRIM(F12)),1)="M",VALUE(SUBSTITUTE(SUBSTITUTE(LEFT(TRIM(F12),LEN(TRIM(F12))-1),"$",""),",",""))*1000000,VALUE(SUBSTITUTE(SUBSTITUTE(TRIM(F12),"$",""),",","")))),"") -> 178212 | R12: =IF(COUNTIF($A$2:A12,A12)=1,Q12,"") -> 178212
A13: DL-00012 | B13: CUST-0375 | D13: WorkHub Core | E13: Demo | F13: 3,564 | G13: Paid Search | H13: Amruta Sinha | I13: 2022-08-19 | J13: 44937 | M13: 0 | N13: 1 | O13: 19.9 | P13: East Africa | Q13: =IFERROR(IF(RIGHT(UPPER(TRIM(F13)),1)="K",VALUE(SUBSTITUTE(SUBSTITUTE(LEFT(TRIM(F13),LEN(TRIM(F13))-1),"$",""),",",""))*1000,IF(RIGHT(UPPER(TRIM(F13)),1)="M",VALUE(SUBSTITUTE(SUBSTITUTE(LEFT(TRIM(F13),LEN(TRIM(F13))-1),"$",""),",",""))*1000000,VALUE(SUBSTITUTE(SUBSTITUTE(TRIM(F13),"$",""),",","")))),"") -> 3564 | R13: =IF(COUNTIF($A$2:A13,A13)=1,Q13,"") -> 3564
A14: DL-00013 | B14: CUST-0833 | C14: CMP-378 | D14: API Access | E14: Negotiation | F14: 5,862 | G14: Partner Referral | H14: Hemangini Bahri | I14: 2023-02-12 | J14: 44998 | M14: 0 | N14: 1 | O14: 15.1 | P14: Southeast Asia | Q14: =IFERROR(IF(RIGHT(UPPER(TRIM(F14)),1)="K",VALUE(SUBSTITUTE(SUBSTITUTE(LEFT(TRIM(F14),LEN(TRIM(F14))-1),"$",""),",",""))*1000,IF(RIGHT(UPPER(TRIM(F14)),1)="M",VALUE(SUBSTITUTE(SUBSTITUTE(LEFT(TRIM(F14),LEN(TRIM(F14))-1),"$",""),",",""))*1000000,VALUE(SUBSTITUTE(SUBSTITUTE(TRIM(F14),"$",""),",","")))),"") -> 5862 | R14: =IF(COUNTIF($A$2:A14,A14)=1,Q14,"") -> 5862
A15: DL-00014 | B15: CUST-0128 | C15: CMP-121 | D15: WorkHub Core | E15: Demo | F15: 1K | G15: Webinar | H15: Ati Seshadri | I15: 2022-07-17 | J15: 44857 | M15: 0 | N15: 1 | O15: 9.5 | P15: South Asia | Q15: =IFERROR(IF(RIGHT(UPPER(TRIM(F15)),1)="K",VALUE(SUBSTITUTE(SUBSTITUTE(LEFT(TRIM(F15),LEN(TRIM(F15))-1),"$",""),",",""))*1000,IF(RIGHT(UPPER(TRIM(F15)),1)="M",VALUE(SUBSTITUTE(SUBSTITUTE(LEFT(TRIM(F15),LEN(TRIM(F15))-1),"$",""),",",""))*1000000,VALUE(SUBSTITUTE(SUBSTITUTE(TRIM(F15),"$",""),",","")))),"") -> 1000 | R15: =IF(COUNTIF($A$2:A15,A15)=1,Q15,"") -> 1000
A16: DL-00015 | B16: CUST-1133 | C16: CMP-091 | D16: WorkHub Pro | E16: Closed Lost | F16: 24887 | G16: LinkedIn Ads | H16: Ekta Uppal | I16: 2024-07-12 | J16: 45541 | K16: 45616 | L16: 131 | M16: 0 | N16: 1 | O16: 32.7 | P16: Southeast Asia | Q16: =IFERROR(IF(RIGHT(UPPER(TRIM(F16)),1)="K",VALUE(SUBSTITUTE(SUBSTITUTE(LEFT(TRIM(F16),LEN(TRIM(F16))-1),"$",""),",",""))*1000,IF(RIGHT(UPPER(TRIM(F16)),1)="M",VALUE(SUBSTITUTE(SUBSTITUTE(LEFT(TRIM(F16),LEN(TRIM(F16))-1),"$",""),",",""))*1000000,VALUE(SUBSTITUTE(SUBSTITUTE(TRIM(F16),"$",""),",","")))),"") -> 24887 | R16: =IF(COUNTIF($A$2:A16,A16)=1,Q16,"") -> 24887
A17: DL-00016 | B17: CUST-1028 | C17: CMP-127 | D17: API Access | E17: Closed Lost | F17: $10,459 | G17: Webinar | H17: Karan Karnik | I17: 2024-11-01 | J17: 45773 | K17: 45720 | L17: 123 | M17: 0 | N17: 1 | O17: 6.2 | P17: Middle East | Q17: =IFERROR(IF(RIGHT(UPPER(TRIM(F17)),1)="K",VALUE(SUBSTITUTE(SUBSTITUTE(LEFT(TRIM(F17),LEN(TRIM(F17))-1),"$",""),",",""))*1000,IF(RIGHT(UPPER(TRIM(F17)),1)="M",VALUE(SUBSTITUTE(SUBSTITUTE(LEFT(TRIM(F17),LEN(TRIM(F17))-1),"$",""),",",""))*1000000,VALUE(SUBSTITUTE(SUBSTITUTE(TRIM(F17),"$",""),",","")))),"") -> 10459 | R17: =IF(COUNTIF($A$2:A17,A17)=1,Q17,"") -> 10459
A18: DL-00017 | B18: CUST-0223 | C18: CMP-378 | D18: WorkHub Core | E18: Closed Lost | F18: $7,222 | G18: Webinar | H18: Kashish Patla | I18: 2023-04-08 | J18: 45177 | K18: 45101 | L18: 77 | M18: 0 | N18: 1 | O18: 12.2 | P18: South Asia | Q18: =IFERROR(IF(RIGHT(UPPER(TRIM(F18)),1)="K",VALUE(SUBSTITUTE(SUBSTITUTE(LEFT(TRIM(F18),LEN(TRIM(F18))-1),"$",""),",",""))*1000,IF(RIGHT(UPPER(TRIM(F18)),1)="M",VALUE(SUBSTITUTE(SUBSTITUTE(LEFT(TRIM(F18),LEN(TRIM(F18))-1),"$",""),",",""))*1000000,VALUE(SUBSTITUTE(SUBSTITUTE(TRIM(F18),"$",""),",","")))),"") -> 7222 | R18: =IF(COUNTIF($A$2:A18,A18)=1,Q18,"") -> 7222
A19: DL-00018 | B19: CUST-0667 | C19: CMP-335 | D19: WorkHub Core | E19: Demo | F19: $8,134 | G19: Event | H19: Aachal Soni | I19: 2024-01-29 | J19: 45497 | M19: 0 | N19: 1 | P19: Southeast Asia | Q19: =IFERROR(IF(RIGHT(UPPER(TRIM(F19)),1)="K",VALUE(SUBSTITUTE(SUBSTITUTE(LEFT(TRIM(F19),LEN(TRIM(F19))-1),"$",""),",",""))*1000,IF(RIGHT(UPPER(TRIM(F19)),1)="M",VALUE(SUBSTITUTE(SUBSTITUTE(LEFT(TRIM(F19),LEN(TRIM(F19))-1),"$",""),",",""))*1000000,VALUE(SUBSTITUTE(SUBSTITUTE(TRIM(F19),"$",""),",","")))),"") -> 8134 | R19: =IF(COUNTIF($A$2:A19,A19)=1,Q19,"") -> 8134
A20: DL-00019 | B20: CUST-1273 | C20: CMP-339 | D20: WorkHub Pro | E20: Proposal | F20: 46,846 | G20: Event | H20: Champak Rao | I20: 2023-12-23 | J20: 45434 | M20: 0 | N20: 1 | O20: 18.9 | P20: South Asia | Q20: =IFERROR(IF(RIGHT(UPPER(TRIM(F20)),1)="K",VALUE(SUBSTITUTE(SUBSTITUTE(LEFT(TRIM(F20),LEN(TRIM(F20))-1),"$",""),",",""))*1000,IF(RIGHT(UPPER(TRIM(F20)),1)="M",VALUE(SUBSTITUTE(SUBSTITUTE(LEFT(TRIM(F20),LEN(TRIM(F20))-1),"$",""),",",""))*1000000,VALUE(SUBSTITUTE(SUBSTITUTE(TRIM(F20),"$",""),",","")))),"") -> 46846 | R20: =IF(COUNTIF($A$2:A20,A20)=1,Q20,"") -> 46846
A21: DL-00020 | B21: CUST-1499 | C21: CMP-140 | D21: WorkHub Pro | E21: Closed Won | F21: $33,087 | G21: Product-Led Signup | H21: Krish Varughese | I21: 2022-12-16 | J21: 44950 | K21: 45045 | L21: 134 | M21: 1 | N21: 2 | O21: 12 | P21: South Asia | Q21: =IFERROR(IF(RIGHT(UPPER(TRIM(F21)),1)="K",VALUE(SUBSTITUTE(SUBSTITUTE(LEFT(TRIM(F21),LEN(TRIM(F21))-1),"$",""),",",""))*1000,IF(RIGHT(UPPER(TRIM(F21)),1)="M",VALUE(SUBSTITUTE(SUBSTITUTE(LEFT(TRIM(F21),LEN(TRIM(F21))-1),"$",""),",",""))*1000000,VALUE(SUBSTITUTE(SUBSTITUTE(TRIM(F21),"$",""),",","")))),"") -> 33087 | R21: =IF(COUNTIF($A$2:A21,A21)=1,Q21,"") -> 33087
A22: DL-00021 | B22: CUST-1485 | C22: CMP-012 | D22: WorkHub Enterprise | E22: Closed Lost | F22: 119072 | G22: Inbound Organic | H22: Nihal Bhasin | I22: 2024-04-23 | J22: 45497 | K22: 45537 | L22: 132 | M22: 0 | N22: 1 | O22: 20.1 | P22: East Africa | Q22: =IFERROR(IF(RIGHT(UPPER(TRIM(F22)),1)="K",VALUE(SUBSTITUTE(SUBSTITUTE(LEFT(TRIM(F22),LEN(TRIM(F22))-1),"$",""),",",""))*1000,IF(RIGHT(UPPER(TRIM(F22)),1)="M",VALUE(SUBSTITUTE(SUBSTITUTE(LEFT(TRIM(F22),LEN(TRIM(F22))-1),"$",""),",",""))*1000000,VALUE(SUBSTITUTE(SUBSTITUTE(TRIM(F22),"$",""),",","")))),"") -> 119072 | R22: =IF(COUNTIF($A$2:A22,A22)=1,Q22,"") -> 119072
A23: DL-00022 | B23: CUST-0937 | D23: WorkHub Enterprise | E23: Negotiation | F23: $116,146 | G23: Event | H23: Lakshmi Hayre | I23: 2023-08-06 | J23: 45289 | M23: 0 | N23: 1 | O23: 21.3 | P23: ANZ | Q23: =IFERROR(IF(RIGHT(UPPER(TRIM(F23)),1)="K",VALUE(SUBSTITUTE(SUBSTITUTE(LEFT(TRIM(F23),LEN(TRIM(F23))-1),"$",""),",",""))*1000,IF(RIGHT(UPPER(TRIM(F23)),1)="M",VALUE(SUBSTITUTE(SUBSTITUTE(LEFT(TRIM(F23),LEN(TRIM(F23))-1),"$",""),",",""))*1000000,VALUE(SUBSTITUTE(SUBSTITUTE(TRIM(F23),"$",""),",","")))),"") -> 116146 | R23: =IF(COUNTIF($A$2:A23,A23)=1,Q23,"") -> 116146
A24: DL-00023 | B24: CUST-0939 | D24: API Access | E24: Closed Lost | F24: $23,944 | G24: Cold Outreach | H24: Karan Karnik | I24: 2022-08-07 | J24: 44944 | K24: 44867 | L24: 87 | M24: 0 | N24: 1 | P24: East Africa | Q24: =IFERROR(IF(RIGHT(UPPER(TRIM(F24)),1)="K",VALUE(SUBSTITUTE(SUBSTITUTE(LEFT(TRIM(F24),LEN(TRIM(F24))-1),"$",""),",",""))*1000,IF(RIGHT(UPPER(TRIM(F24)),1)="M",VALUE(SUBSTITUTE(SUBSTITUTE(LEFT(TRIM(F24),LEN(TRIM(F24))-1),"$",""),",",""))*1000000,VALUE(SUBSTITUTE(SUBSTITUTE(TRIM(F24),"$",""),",","")))),"") -> 23944 | R24: =IF(COUNTIF($A$2:A24,A24)=1,Q24,"") -> 23944
A25: DL-00024 | B25: CUST-0021 | C25: CMP-130 | D25: WorkHub Enterprise | E25: Closed Lost | F25: 115K | G25: Paid Search | H25: Amruta Sinha | I25: 2024-03-23 | K25: 45533 | L25: 159 | M25: 0 | N25: 1 | O25: 6.3 | P25: South Asia | Q25: =IFERROR(IF(RIGHT(UPPER(TRIM(F25)),1)="K",VALUE(SUBSTITUTE(SUBSTITUTE(LEFT(TRIM(F25),LEN(TRIM(F25))-1),"$",""),",",""))*1000,IF(RIGHT(UPPER(TRIM(F25)),1)="M",VALUE(SUBSTITUTE(SUBSTITUTE(LEFT(TRIM(F25),LEN(TRIM(F25))-1),"$",""),",",""))*1000000,VALUE(SUBSTITUTE(SUBSTITUTE(TRIM(F25),"$",""),",","")))),"") -> 115000 | R25: =IF(COUNTIF($A$2:A25,A25)=1,Q25,"") -> 115000
A26: DL-00025 | B26: CUST-0002 | C26: CMP-055 | D26: API Access | E26: Closed Lost | F26: 17,202 | G26: Content Download | H26: Karan Karnik | I26: 2023-09-17 | J26: 45261 | K26: 45327 | L26: 141 | M26: 0 | N26: 1 | O26: 9.2 | P26: ANZ | Q26: =IFERROR(IF(RIGHT(UPPER(TRIM(F26)),1)="K",VALUE(SUBSTITUTE(SUBSTITUTE(LEFT(TRIM(F26),LEN(TRIM(F26))-1),"$",""),",",""))*1000,IF(RIGHT(UPPER(TRIM(F26)),1)="M",VALUE(SUBSTITUTE(SUBSTITUTE(LEFT(TRIM(F26),LEN(TRIM(F26))-1),"$",""),",",""))*1000000,VALUE(SUBSTITUTE(SUBSTITUTE(TRIM(F26),"$",""),",","")))),"") -> 17202 | R26: =IF(COUNTIF($A$2:A26,A26)=1,Q26,"") -> 17202
A27: DL-00026 | B27: CUST-0485 | C27: CMP-399 | D27: WorkHub Core | E27: Qualification | F27: $1,586 | G27: Event | H27: krish varughese | I27: 12/03/2023 | J27: 45111 | M27: 0 | N27: 1 | O27: 14.1 | P27: Southeast Asia | Q27: =IFERROR(IF(RIGHT(UPPER(TRIM(F27)),1)="K",VALUE(SUBSTITUTE(SUBSTITUTE(LEFT(TRIM(F27),LEN(TRIM(F27))-1),"$",""),",",""))*1000,IF(RIGHT(UPPER(TRIM(F27)),1)="M",VALUE(SUBSTITUTE(SUBSTITUTE(LEFT(TRIM(F27),LEN(TRIM(F27))-1),"$",""),",",""))*1000000,VALUE(SUBSTITUTE(SUBSTITUTE(TRIM(F27),"$",""),",","")))),"") -> 1586 | R27: =IF(COUNTIF($A$2:A27,A27)=1,Q27,"") -> 1586
A28: DL-00027 | B28: CUST-0733 | D28: Analytics Add-on | E28: Demo | F28: 8K | G28: Content Download | H28: Lakshmi Hayre | I28: 2023-08-26 | J28: 45307 | M28: 0 | N28: 1 | O28: 32 | P28: ANZ | Q28: =IFERROR(IF(RIGHT(UPPER(TRIM(F28)),1)="K",VALUE(SUBSTITUTE(SUBSTITUTE(LEFT(TRIM(F28),LEN(TRIM(F28))-1),"$",""),",",""))*1000,IF(RIGHT(UPPER(TRIM(F28)),1)="M",VALUE(SUBSTITUTE(SUBSTITUTE(LEFT(TRIM(F28),LEN(TRIM(F28))-1),"$",""),",",""))*1000000,VALUE(SUBSTITUTE(SUBSTITUTE(TRIM(F28),"$",""),",","")))),"") -> 8000 | R28: =IF(COUNTIF($A$2:A28,A28)=1,Q28,"") -> 8000
A29: DL-00028 | B29: CUST-1317 | D29: WorkHub Core | E29: Prospecting | F29: $8,919 | G29: Webinar | H29: Champak Rao | I29: 2023-07-10 | J29: 45196 | M29: 0 | N29: 1 | P29: Middle East | Q29: =IFERROR(IF(RIGHT(UPPER(TRIM(F29)),1)="K",VALUE(SUBSTITUTE(SUBSTITUTE(LEFT(TRIM(F29),LEN(TRIM(F29))-1),"$",""),",",""))*1000,IF(RIGHT(UPPER(TRIM(F29)),1)="M",VALUE(SUBSTITUTE(SUBSTITUTE(LEFT(TRIM(F29),LEN(TRIM(F29))-1),"$",""),",",""))*1000000,VALUE(SUBSTITUTE(SUBSTITUTE(TRIM(F29),"$",""),",","")))),"") -> 8919 | R29: =IF(COUNTIF($A$2:A29,A29)=1,Q29,"") -> 8919
A30: DL-00029 | B30: CUST-1145 | C30: CMP-218 | D30: Analytics Add-on | E30: Closed Won | F30: $11,849 | G30: Cold Outreach | H30: ati seshadri | I30: 2022-10-18 | J30: 44949 | K30: 45028 | L30: 176 | M30: 0 | N30: 1 | O30: 30.5 | P30: Southeast Asia | Q30: =IFERROR(IF(RIGHT(UPPER(TRIM(F30)),1)="K",VALUE(SUBSTITUTE(SUBSTITUTE(LEFT(TRIM(F30),LEN(TRIM(F30))-1),"$",""),",",""))*1000,IF(RIGHT(UPPER(TRIM(F30)),1)="M",VALUE(SUBSTITUTE(SUBSTITUTE(LEFT(TRIM(F30),LEN(TRIM(F30))-1),"$",""),",",""))*1000000,VALUE(SUBSTITUTE(SUBSTITUTE(TRIM(F30),"$",""),",","")))),"") -> 11849 | R30: =IF(COUNTIF($A$2:A30,A30)=1,Q30,"") -> 11849
A31: DL-00030 | B31: CUST-0371 | C31: CMP-351 | D31: WorkHub Core | E31: Negotiation | F31: $7,862 | G31: Cold Outreach | H31: Anamika Keer | I31: 2024-06-19 | J31: 45555 | M31: 0 | N31: 1 | O31: 13.6 | P31: Middle East | Q31: =IFERROR(IF(RIGHT(UPPER(TRIM(F31)),1)="K",VALUE(SUBSTITUTE(SUBSTITUTE(LEFT(TRIM(F31),LEN(TRIM(F31))-1),"$",""),",",""))*1000,IF(RIGHT(UPPER(TRIM(F31)),1)="M",VALUE(SUBSTITUTE(SUBSTITUTE(LEFT(TRIM(F31),LEN(TRIM(F31))-1),"$",""),",",""))*1000000,VALUE(SUBSTITUTE(SUBSTITUTE(TRIM(F31),"$",""),",","")))),"") -> 7862 | R31: =IF(COUNTIF($A$2:A31,A31)=1,Q31,"") -> 7862
A32: DL-00031 | B32: CUST-1231 | D32: Analytics Add-on | E32: Demo | F32: $14,033 | G32: Paid Search | H32: Anamika Keer | I32: 2022-06-17 | J32: 44833 | M32: 0 | N32: 1 | O32: 5.8 | P32: Southeast Asia | Q32: =IFERROR(IF(RIGHT(UPPER(TRIM(F32)),1)="K",VALUE(SUBSTITUTE(SUBSTITUTE(LEFT(TRIM(F32),LEN(TRIM(F32))-1),"$",""),",",""))*1000,IF(RIGHT(UPPER(TRIM(F32)),1)="M",VALUE(SUBSTITUTE(SUBSTITUTE(LEFT(TRIM(F32),LEN(TRIM(F32))-1),"$",""),",",""))*1000000,VALUE(SUBSTITUTE(SUBSTITUTE(TRIM(F32),"$",""),",","")))),"") -> 14033 | R32: =IF(COUNTIF($A$2:A32,A32)=1,Q32,"") -> 14033
A33: DL-00032 | B33: CUST-1349 | C33: CMP-285 | D33: WorkHub Pro | E33: Closed Lost | F33: 28,595 | G33: Paid Search | H33: Aachal Soni | I33: 2024-08-06 | J33: 45594 | K33: 45669 | L33: 159 | M33: 0 | N33: 1 | O33: 25.6 | P33: Middle East | Q33: =IFERROR(IF(RIGHT(UPPER(TRIM(F33)),1)="K",VALUE(SUBSTITUTE(SUBSTITUTE(LEFT(TRIM(F33),LEN(TRIM(F33))-1),"$",""),",",""))*1000,IF(RIGHT(UPPER(TRIM(F33)),1)="M",VALUE(SUBSTITUTE(SUBSTITUTE(LEFT(TRIM(F33),LEN(TRIM(F33))-1),"$",""),",",""))*1000000,VALUE(SUBSTITUTE(SUBSTITUTE(TRIM(F33),"$",""),",","")))),"") -> 28595 | R33: =IF(COUNTIF($A$2:A33,A33)=1,Q33,"") -> 28595
A34: DL-00033 | B34: CUST-0351 | D34: WorkHub Pro | E34: Negotiation | F34: $13,494 | G34: Partner Referral | H34: Ati Seshadri | I34: 2023-10-03 | J34: 45345 | M34: 0 | N34: 1 | P34: South Asia | Q34: =IFERROR(IF(RIGHT(UPPER(TRIM(F34)),1)="K",VALUE(SUBSTITUTE(SUBSTITUTE(LEFT(TRIM(F34),LEN(TRIM(F34))-1),"$",""),",",""))*1000,IF(RIGHT(UPPER(TRIM(F34)),1)="M",VALUE(SUBSTITUTE(SUBSTITUTE(LEFT(TRIM(F34),LEN(TRIM(F34))-1),"$",""),",",""))*1000000,VALUE(SUBSTITUTE(SUBSTITUTE(TRIM(F34),"$",""),",","")))),"") -> 13494 | R34: =IF(COUNTIF($A$2:A34,A34)=1,Q34,"") -> 13494
A35: DL-00034 | B35: CUST-1305 | C35: CMP-375 | D35: WorkHub Core | E35: Demo | F35: $6,564 | G35: Paid Search | H35: Lakshmi Hayre | I35: 2024-01-20 | J35: 45362 | M35: 0 | N35: 1 | O35: 30.6 | P35: ANZ | Q35: =IFERROR(IF(RIGHT(UPPER(TRIM(F35)),1)="K",VALUE(SUBSTITUTE(SUBSTITUTE(LEFT(TRIM(F35),LEN(TRIM(F35))-1),"$",""),",",""))*1000,IF(RIGHT(UPPER(TRIM(F35)),1)="M",VALUE(SUBSTITUTE(SUBSTITUTE(LEFT(TRIM(F35),LEN(TRIM(F35))-1),"$",""),",",""))*1000000,VALUE(SUBSTITUTE(SUBSTITUTE(TRIM(F35),"$",""),",","")))),"") -> 6564 | R35: =IF(COUNTIF($A$2:A35,A35)=1,Q35,"") -> 6564
A36: DL-00035 | B36: CUST-1190 | C36: CMP-036 | D36: WorkHub Enterprise | E36: Closed Won | F36: 104,006 | G36: Event | H36: Karan Karnik | I36: 2022-03-17 | K36: 44706 | L36: 69 | M36: 1 | N36: 2 | O36: 14.7 | P36: Southeast Asia | Q36: =IFERROR(IF(RIGHT(UPPER(TRIM(F36)),1)="K",VALUE(SUBSTITUTE(SUBSTITUTE(LEFT(TRIM(F36),LEN(TRIM(F36))-1),"$",""),",",""))*1000,IF(RIGHT(UPPER(TRIM(F36)),1)="M",VALUE(SUBSTITUTE(SUBSTITUTE(LEFT(TRIM(F36),LEN(TRIM(F36))-1),"$",""),",",""))*1000000,VALUE(SUBSTITUTE(SUBSTITUTE(TRIM(F36),"$",""),",","")))),"") -> 104006 | R36: =IF(COUNTIF($A$2:A36,A36)=1,Q36,"") -> 104006
A37: DL-00036 | B37: CUST-1068 | C37: CMP-095 | D37: API Access | E37: Closed Lost | F37: $10,794 | G37: Product-Led Signup | H37: Amruta Sinha | I37: 2022-05-20 | J37: 44855 | K37: 44723 | L37: 22 | M37: 0 | N37: 1 | O37: 10 | P37: South Asia | Q37: =IFERROR(IF(RIGHT(UPPER(TRIM(F37)),1)="K",VALUE(SUBSTITUTE(SUBSTITUTE(LEFT(TRIM(F37),LEN(TRIM(F37))-1),"$",""),",",""))*1000,IF(RIGHT(UPPER(TRIM(F37)),1)="M",VALUE(SUBSTITUTE(SUBSTITUTE(LEFT(TRIM(F37),LEN(TRIM(F37))-1),"$",""),",",""))*1000000,VALUE(SUBSTITUTE(SUBSTITUTE(TRIM(F37),"$",""),",","")))),"") -> 10794 | R37: =IF(COUNTIF($A$2:A37,A37)=1,Q37,"") -> 10794
A38: DL-00037 | B38: CUST-0251 | D38: Analytics Add-on | E38: Closed Won | F38: 8191 | G38: Product-Led Signup | H38: Patrick Sama | I38: 2023-04-09 | J38: 45171 | K38: 45176 | L38: 151 | M38: 0 | N38: 1 | O38: 3.8 | P38: Middle East | Q38: =IFERROR(IF(RIGHT(UPPER(TRIM(F38)),1)="K",VALUE(SUBSTITUTE(SUBSTITUTE(LEFT(TRIM(F38),LEN(TRIM(F38))-1),"$",""),",",""))*1000,IF(RIGHT(UPPER(TRIM(F38)),1)="M",VALUE(SUBSTITUTE(SUBSTITUTE(LEFT(TRIM(F38),LEN(TRIM(F38))-1),"$",""),",",""))*1000000,VALUE(SUBSTITUTE(SUBSTITUTE(TRIM(F38),"$",""),",","")))),"") -> 8191 | R38: =IF(COUNTIF($A$2:A38,A38)=1,Q38,"") -> 8191
A39: DL-00038 | B39: CUST-1017 | D39: WorkHub Core | E39: Closed Won | F39: $9,490 | G39: Event | H39: Vidhi Mital | I39: 14/05/2022 | J39: 44811 | K39: 44869 | L39: 174 | M39: 0 | N39: 1 | O39: 31.1 | P39: Middle East | Q39: =IFERROR(IF(RIGHT(UPPER(TRIM(F39)),1)="K",VALUE(SUBSTITUTE(SUBSTITUTE(LEFT(TRIM(F39),LEN(TRIM(F39))-1),"$",""),",",""))*1000,IF(RIGHT(UPPER(TRIM(F39)),1)="M",VALUE(SUBSTITUTE(SUBSTITUTE(LEFT(TRIM(F39),LEN(TRIM(F39))-1),"$",""),",",""))*1000000,VALUE(SUBSTITUTE(SUBSTITUTE(TRIM(F39),"$",""),",","")))),"") -> 9490 | R39: =IF(COUNTIF($A$2:A39,A39)=1,Q39,"") -> 9490
A40: DL-00039 | B40: CUST-1204 | C40: CMP-049 | D40: API Access | E40: Negotiation | F40: $8,249 | G40: Inbound Organic | H40: Amruta Sinha | I40: 2024-09-09 | J40: 45618 | M40: 0 | N40: 1 | O40: 23.9 | P40: East Africa | Q40: =IFERROR(IF(RIGHT(UPPER(TRIM(F40)),1)="K",VALUE(SUBSTITUTE(SUBSTITUTE(LEFT(TRIM(F40),LEN(TRIM(F40))-1),"$",""),",",""))*1000,IF(RIGHT(UPPER(TRIM(F40)),1)="M",VALUE(SUBSTITUTE(SUBSTITUTE(LEFT(TRIM(F40),LEN(TRIM(F40))-1),"$",""),",",""))*1000000,VALUE(SUBSTITUTE(SUBSTITUTE(TRIM(F40),"$",""),",","")))),"") -> 8249 | R40: =IF(COUNTIF($A$2:A40,A40)=1,Q40,"") -> 8249
A41: DL-00040 | B41: CUST-1359 | C41: CMP-288 | D41: API Access | E41: Demo | F41: $19,440 | G41: Partner Referral | H41: Ati Seshadri | I41: 2024-11-19 | J41: 45787 | M41: 0 | N41: 1 | O41: 20.4 | P41: Middle East | Q41: =IFERROR(IF(RIGHT(UPPER(TRIM(F41)),1)="K",VALUE(SUBSTITUTE(SUBSTITUTE(LEFT(TRIM(F41),LEN(TRIM(F41))-1),"$",""),",",""))*1000,IF(RIGHT(UPPER(TRIM(F41)),1)="M",VALUE(SUBSTITUTE(SUBSTITUTE(LEFT(TRIM(F41),LEN(TRIM(F41))-1),"$",""),",",""))*1000000,VALUE(SUBSTITUTE(SUBSTITUTE(TRIM(F41),"$",""),",","")))),"") -> 19440 | R41: =IF(COUNTIF($A$2:A41,A41)=1,Q41,"") -> 19440
A42: DL-00041 | B42: CUST-1005 | C42: CMP-340 | D42: WorkHub Enterprise | E42: Negotiation | F42: $78,097 | G42: Cold Outreach | H42: Shivani Natt | I42: 2022-04-16 | J42: 44831 | M42: 0 | N42: 1 | O42: 18.9 | P42: South Asia | Q42: =IFERROR(IF(RIGHT(UPPER(TRIM(F42)),1)="K",VALUE(SUBSTITUTE(SUBSTITUTE(LEFT(TRIM(F42),LEN(TRIM(F42))-1),"$",""),",",""))*1000,IF(RIGHT(UPPER(TRIM(F42)),1)="M",VALUE(SUBSTITUTE(SUBSTITUTE(LEFT(TRIM(F42),LEN(TRIM(F42))-1),"$",""),",",""))*1000000,VALUE(SUBSTITUTE(SUBSTITUTE(TRIM(F42),"$",""),",","")))),"") -> 78097 | R42: =IF(COUNTIF($A$2:A42,A42)=1,Q42,"") -> 78097
A43: DL-00042 | B43: CUST-0613 | C43: CMP-106 | D43: API Access | E43: Proposal | F43: 9704 | G43: Event | H43: Jasmit Gour | I43: 2024-12-19 | J43: 45744 | M43: 0 | N43: 1 | O43: 27.6 | P43: Southeast Asia | Q43: =IFERROR(IF(RIGHT(UPPER(TRIM(F43)),1)="K",VALUE(SUBSTITUTE(SUBSTITUTE(LEFT(TRIM(F43),LEN(TRIM(F43))-1),"$",""),",",""))*1000,IF(RIGHT(UPPER(TRIM(F43)),1)="M",VALUE(SUBSTITUTE(SUBSTITUTE(LEFT(TRIM(F43),LEN(TRIM(F43))-1),"$",""),",",""))*1000000,VALUE(SUBSTITUTE(SUBSTITUTE(TRIM(F43),"$",""),",","")))),"") -> 9704 | R43: =IF(COUNTIF($A$2:A43,A43)=1,Q43,"") -> 9704
A44: DL-00043 | B44: CUST-0802 | D44: API Access | E44: Prospecting | F44: $20,918 | G44: LinkedIn Ads | H44: Karan Karnik | I44: 2024-06-08 | J44: 45486 | M44: 0 | N44: 1 | O44: 21.3 | P44: Middle East | Q44: =IFERROR(IF(RIGHT(UPPER(TRIM(F44)),1)="K",VALUE(SUBSTITUTE(SUBSTITUTE(LEFT(TRIM(F44),LEN(TRIM(F44))-1),"$",""),",",""))*1000,IF(RIGHT(UPPER(TRIM(F44)),1)="M",VALUE(SUBSTITUTE(SUBSTITUTE(LEFT(TRIM(F44),LEN(TRIM(F44))-1),"$",""),",",""))*1000000,VALUE(SUBSTITUTE(SUBSTITUTE(TRIM(F44),"$",""),",","")))),"") -> 20918 | R44: =IF(COUNTIF($A$2:A44,A44)=1,Q44,"") -> 20918
A45: DL-00044 | B45: CUST-0047 | C45: CMP-046 | D45: API Access | E45: Negotiation | F45: 15,030 | G45: LinkedIn Ads | H45: Panini Kade | I45: 2022-10-30 | J45: 44987 | M45: 0 | N45: 1 | O45: 7.7 | P45: Middle East | Q45: =IFERROR(IF(RIGHT(UPPER(TRIM(F45)),1)="K",VALUE(SUBSTITUTE(SUBSTITUTE(LEFT(TRIM(F45),LEN(TRIM(F45))-1),"$",""),",",""))*1000,IF(RIGHT(UPPER(TRIM(F45)),1)="M",VALUE(SUBSTITUTE(SUBSTITUTE(LEFT(TRIM(F45),LEN(TRIM(F45))-1),"$",""),",",""))*1000000,VALUE(SUBSTITUTE(SUBSTITUTE(TRIM(F45),"$",""),",","")))),"") -> 15030 | R45: =IF(COUNTIF($A$2:A45,A45)=1,Q45,"") -> 15030
A46: DL-00045 | B46: CUST-1103 | C46: CMP-294 | D46: WorkHub Core | E46: Closed Won | F46: 1367 | G46: Event | H46: Rachit Lall | I46: 2024-03-19 | J46: 45416 | K46: 45539 | L46: 169 | M46: 1 | N46: 2 | O46: 33.5 | P46: Middle East | Q46: =IFERROR(IF(RIGHT(UPPER(TRIM(F46)),1)="K",VALUE(SUBSTITUTE(SUBSTITUTE(LEFT(TRIM(F46),LEN(TRIM(F46))-1),"$",""),",",""))*1000,IF(RIGHT(UPPER(TRIM(F46)),1)="M",VALUE(SUBSTITUTE(SUBSTITUTE(LEFT(TRIM(F46),LEN(TRIM(F46))-1),"$",""),",",""))*1000000,VALUE(SUBSTITUTE(SUBSTITUTE(TRIM(F46),"$",""),",","")))),"") -> 1367 | R46: =IF(COUNTIF($A$2:A46,A46)=1,Q46,"") -> 1367
A47: DL-00046 | B47: CUST-0646 | D47: WorkHub Enterprise | E47: Qualification | F47: 181996 | G47: Product-Led Signup | H47: Amruta Sinha | I47: 2024-12-31 | M47: 0 | N47: 1 | O47: 11.5 | P47: ANZ | Q47: =IFERROR(IF(RIGHT(UPPER(TRIM(F47)),1)="K",VALUE(SUBSTITUTE(SUBSTITUTE(LEFT(TRIM(F47),LEN(TRIM(F47))-1),"$",""),",",""))*1000,IF(RIGHT(UPPER(TRIM(F47)),1)="M",VALUE(SUBSTITUTE(SUBSTITUTE(LEFT(TRIM(F47),LEN(TRIM(F47))-1),"$",""),",",""))*1000000,VALUE(SUBSTITUTE(SUBSTITUTE(TRIM(F47),"$",""),",","")))),"") -> 181996 | R47: =IF(COUNTIF($A$2:A47,A47)=1,Q47,"") -> 181996
A48: DL-00047 | B48: CUST-0143 | C48: CMP-124 | D48: WorkHub Enterprise | E48: Closed Lost | F48: 61249 | G48: Content Download | H48: Aachal Soni | I48: 2024-06-19 | J48: 45607 | K48: 45584 | L48: 122 | M48: 0 | N48: 1 | O48: 19.9 | P48: South Asia | Q48: =IFERROR(IF(RIGHT(UPPER(TRIM(F48)),1)="K",VALUE(SUBSTITUTE(SUBSTITUTE(LEFT(TRIM(F48),LEN(TRIM(F48))-1),"$",""),",",""))*1000,IF(RIGHT(UPPER(TRIM(F48)),1)="M",VALUE(SUBSTITUTE(SUBSTITUTE(LEFT(TRIM(F48),LEN(TRIM(F48))-1),"$",""),",",""))*1000000,VALUE(SUBSTITUTE(SUBSTITUTE(TRIM(F48),"$",""),",","")))),"") -> 61249 | R48: =IF(COUNTIF($A$2:A48,A48)=1,Q48,"") -> 61249
A49: DL-00048 | B49: CUST-1284 | C49: CMP-096 | D49: WorkHub Enterprise | E49: Proposal | F49: $62,439 | G49: Product-Led Signup | H49: Jasmit Gour | I49: 2023-05-20 | J49: 45179 | M49: 0 | N49: 1 | O49: 8.4 | P49: South Asia | Q49: =IFERROR(IF(RIGHT(UPPER(TRIM(F49)),1)="K",VALUE(SUBSTITUTE(SUBSTITUTE(LEFT(TRIM(F49),LEN(TRIM(F49))-1),"$",""),",",""))*1000,IF(RIGHT(UPPER(TRIM(F49)),1)="M",VALUE(SUBSTITUTE(SUBSTITUTE(LEFT(TRIM(F49),LEN(TRIM(F49))-1),"$",""),",",""))*1000000,VALUE(SUBSTITUTE(SUBSTITUTE(TRIM(F49),"$",""),",","")))),"") -> 62439 | R49: =IF(COUNTIF($A$2:A49,A49)=1,Q49,"") -> 62439
A50: DL-00049 | B50: CUST-0595 | C50: CMP-194 | D50: WorkHub Pro | E50: Demo | F50: $16,578 | G50: Inbound Organic | H50: Ekta Uppal | I50: 2024-09-22 | J50: 45612 | M50: 0 | N50: 1 | O50: 14.8 | P50: Middle East | Q50: =IFERROR(IF(RIGHT(UPPER(TRIM(F50)),1)="K",VALUE(SUBSTITUTE(SUBSTITUTE(LEFT(TRIM(F50),LEN(TRIM(F50))-1),"$",""),",",""))*1000,IF(RIGHT(UPPER(TRIM(F50)),1)="M",VALUE(SUBSTITUTE(SUBSTITUTE(LEFT(TRIM(F50),LEN(TRIM(F50))-1),"$",""),",",""))*1000000,VALUE(SUBSTITUTE(SUBSTITUTE(TRIM(F50),"$",""),",","")))),"") -> 16578 | R50: =IF(COUNTIF($A$2:A50,A50)=1,Q50,"") -> 16578
A51: DL-00050 | B51: CUST-0605 | C51: CMP-172 | D51: WorkHub Pro | E51: Proposal | F51: $10,943 | G51: Product-Led Signup | H51: Lakshmi Hayre | I51: 2022-06-06 | J51: 44851 | M51: 0 | N51: 1 | O51: 11.3 | P51: Middle East | Q51: =IFERROR(IF(RIGHT(UPPER(TRIM(F51)),1)="K",VALUE(SUBSTITUTE(SUBSTITUTE(LEFT(TRIM(F51),LEN(TRIM(F51))-1),"$",""),",",""))*1000,IF(RIGHT(UPPER(TRIM(F51)),1)="M",VALUE(SUBSTITUTE(SUBSTITUTE(LEFT(TRIM(F51),LEN(TRIM(F51))-1),"$",""),",",""))*1000000,VALUE(SUBSTITUTE(SUBSTITUTE(TRIM(F51),"$",""),",","")))),"") -> 10943 | R51: =IF(COUNTIF($A$2:A51,A51)=1,Q51,"") -> 10943
A52: DL-00051 | B52: CUST-0544 | C52: CMP-261 | D52: WorkHub Core | E52: Closed Lost | F52: $9,433 | G52: Paid Search | H52: Amruta Sinha | I52: 2024-10-01 | J52: 45617 | K52: 45639 | L52: 73 | M52: 0 | N52: 1 | O52: 14.8 | P52: Middle East | Q52: =IFERROR(IF(RIGHT(UPPER(TRIM(F52)),1)="K",VALUE(SUBSTITUTE(SUBSTITUTE(LEFT(TRIM(F52),LEN(TRIM(F52))-1),"$",""),",",""))*1000,IF(RIGHT(UPPER(TRIM(F52)),1)="M",VALUE(SUBSTITUTE(SUBSTITUTE(LEFT(TRIM(F52),LEN(TRIM(F52))-1),"$",""),",",""))*1000000,VALUE(SUBSTITUTE(SUBSTITUTE(TRIM(F52),"$",""),",","")))),"") -> 9433 | R52: =IF(COUNTIF($A$2:A52,A52)=1,Q52,"") -> 9433
A53: DL-00052 | B53: CUST-1386 | C53: CMP-338 | D53: WorkHub Enterprise | E53: Proposal | F53: 145K | G53: Content Download | H53: Hemangini Bahri | I53: 2022-02-14 | J53: 44632 | M53: 0 | N53: 1 | O53: 14.1 | P53: South Asia | Q53: =IFERROR(IF(RIGHT(UPPER(TRIM(F53)),1)="K",VALUE(SUBSTITUTE(SUBSTITUTE(LEFT(TRIM(F53),LEN(TRIM(F53))-1),"$",""),",",""))*1000,IF(RIGHT(UPPER(TRIM(F53)),1)="M",VALUE(SUBSTITUTE(SUBSTITUTE(LEFT(TRIM(F53),LEN(TRIM(F53))-1),"$",""),",",""))*1000000,VALUE(SUBSTITUTE(SUBSTITUTE(TRIM(F53),"$",""),",","")))),"") -> 145000 | R53: =IF(COUNTIF($A$2:A53,A53)=1,Q53,"") -> 145000
A54: DL-00053 | B54: CUST-0355 | D54: API Access | E54: Proposal | F54: 5882 | G54: Partner Referral | H54: Jairaj Panchal | I54: 2023-12-20 | J54: 45379 | M54: 0 | N54: 1 | O54: 31.2 | P54: Middle East | Q54: =IFERROR(IF(RIGHT(UPPER(TRIM(F54)),1)="K",VALUE(SUBSTITUTE(SUBSTITUTE(LEFT(TRIM(F54),LEN(TRIM(F54))-1),"$",""),",",""))*1000,IF(RIGHT(UPPER(TRIM(F54)),1)="M",VALUE(SUBSTITUTE(SUBSTITUTE(LEFT(TRIM(F54),LEN(TRIM(F54))-1),"$",""),",",""))*1000000,VALUE(SUBSTITUTE(SUBSTITUTE(TRIM(F54),"$",""),",","")))),"") -> 5882 | R54: =IF(COUNTIF($A$2:A54,A54)=1,Q54,"") -> 5882
A55: DL-00054 | B55: CUST-0044 | C55: CMP-260 | D55: Analytics Add-on | E55: Closed Won | F55: 11707 | G55: Content Download | H55: Panini Kade | I55: 2023-07-09 | J55: 45139 | K55: 45189 | L55: 73 | M55: 0 | N55: 1 | O55: 26.6 | P55: East Africa | Q55: =IFERROR(IF(RIGHT(UPPER(TRIM(F55)),1)="K",VALUE(SUBSTITUTE(SUBSTITUTE(LEFT(TRIM(F55),LEN(TRIM(F55))-1),"$",""),",",""))*1000,IF(RIGHT(UPPER(TRIM(F55)),1)="M",VALUE(SUBSTITUTE(SUBSTITUTE(LEFT(TRIM(F55),LEN(TRIM(F55))-1),"$",""),",",""))*1000000,VALUE(SUBSTITUTE(SUBSTITUTE(TRIM(F55),"$",""),",","")))),"") -> 11707 | R55: =IF(COUNTIF($A$2:A55,A55)=1,Q55,"") -> 11707
A56: DL-00055 | B56: CUST-1336 | D56: WorkHub Enterprise | E56: Closed Lost | F56: $187,339 | G56: Webinar | H56: Anamika Keer | I56: 2022-01-29 | J56: 44607 | K56: 44769 | L56: 179 | M56: 0 | N56: 1 | O56: 32 | P56: ANZ | Q56: =IFERROR(IF(RIGHT(UPPER(TRIM(F56)),1)="K",VALUE(SUBSTITUTE(SUBSTITUTE(LEFT(TRIM(F56),LEN(TRIM(F56))-1),"$",""),",",""))*1000,IF(RIGHT(UPPER(TRIM(F56)),1)="M",VALUE(SUBSTITUTE(SUBSTITUTE(LEFT(TRIM(F56),LEN(TRIM(F56))-1),"$",""),",",""))*1000000,VALUE(SUBSTITUTE(SUBSTITUTE(TRIM(F56),"$",""),",","")))),"") -> 187339 | R56: =IF(COUNTIF($A$2:A56,A56)=1,Q56,"") -> 187339
A57: DL-00056 | B57: CUST-0382 | C57: CMP-183 | D57: API Access | E57: Qualification | F57: 4983 | G57: LinkedIn Ads | H57: Krish Varughese | I57: 21/06/2023 | J57: 45172 | M57: 0 | N57: 1 | O57: 21.4 | P57: Southeast Asia | Q57: =IFERROR(IF(RIGHT(UPPER(TRIM(F57)),1)="K",VALUE(SUBSTITUTE(SUBSTITUTE(LEFT(TRIM(F57),LEN(TRIM(F57))-1),"$",""),",",""))*1000,IF(RIGHT(UPPER(TRIM(F57)),1)="M",VALUE(SUBSTITUTE(SUBSTITUTE(LEFT(TRIM(F57),LEN(TRIM(F57))-1),"$",""),",",""))*1000000,VALUE(SUBSTITUTE(SUBSTITUTE(TRIM(F57),"$",""),",","")))),"") -> 4983 | R57: =IF(COUNTIF($A$2:A57,A57)=1,Q57,"") -> 4983
A58: DL-00057 | B58: CUST-0573 | C58: CMP-248 | D58: WorkHub Core | E58: Prospecting | F58: 3474 | G58: Event | H58: Hemangini Bahri | I58: 23/11/2022 | J58: 44964 | M58: 0 | N58: 1 | P58: Middle East | Q58: =IFERROR(IF(RIGHT(UPPER(TRIM(F58)),1)="K",VALUE(SUBSTITUTE(SUBSTITUTE(LEFT(TRIM(F58),LEN(TRIM(F58))-1),"$",""),",",""))*1000,IF(RIGHT(UPPER(TRIM(F58)),1)="M",VALUE(SUBSTITUTE(SUBSTITUTE(LEFT(TRIM(F58),LEN(TRIM(F58))-1),"$",""),",",""))*1000000,VALUE(SUBSTITUTE(SUBSTITUTE(TRIM(F58),"$",""),",","")))),"") -> 3474 | R58: =IF(COUNTIF($A$2:A58,A58)=1,Q58,"") -> 3474
A59: DL-00058 | B59: CUST-1300 | C59: CMP-091 | D59: WorkHub Pro | E59: Qualification | F59: $15,399 | G59: Partner Referral | H59: jalsa parsa | I59: 2024-08-30 | J59: 45614 | M59: 0 | N59: 1 | O59: 20.1 | P59: ANZ | Q59: =IFERROR(IF(RIGHT(UPPER(TRIM(F59)),1)="K",VALUE(SUBSTITUTE(SUBSTITUTE(LEFT(TRIM(F59),LEN(TRIM(F59))-1),"$",""),",",""))*1000,IF(RIGHT(UPPER(TRIM(F59)),1)="M",VALUE(SUBSTITUTE(SUBSTITUTE(LEFT(TRIM(F59),LEN(TRIM(F59))-1),"$",""),",",""))*1000000,VALUE(SUBSTITUTE(SUBSTITUTE(TRIM(F59),"$",""),",","")))),"") -> 15399 | R59: =IF(COUNTIF($A$2:A59,A59)=1,Q59,"") -> 15399
A60: DL-00059 | B60: CUST-0296 | D60: WorkHub Pro | E60: Demo | F60: $41,412 | G60: Partner Referral | H60: Owen Mane | I60: 28/12/2024 | J60: 45718 | M60: 0 | N60: 1 | P60: ANZ | Q60: =IFERROR(IF(RIGHT(UPPER(TRIM(F60)),1)="K",VALUE(SUBSTITUTE(SUBSTITUTE(LEFT(TRIM(F60),LEN(TRIM(F60))-1),"$",""),",",""))*1000,IF(RIGHT(UPPER(TRIM(F60)),1)="M",VALUE(SUBSTITUTE(SUBSTITUTE(LEFT(TRIM(F60),LEN(TRIM(F60))-1),"$",""),",",""))*1000000,VALUE(SUBSTITUTE(SUBSTITUTE(TRIM(F60),"$",""),",","")))),"") -> 41412 | R60: =IF(COUNTIF($A$2:A60,A60)=1,Q60,"") -> 41412
A61: DL-00060 | B61: CUST-1119 | C61: CMP-210 | D61: Analytics Add-on | E61: Proposal | F61: $11,753 | G61: LinkedIn Ads | H61: Amruta Sinha | I61: 18/11/2023 | J61: 45369 | M61: 0 | N61: 1 | O61: 2.5 | P61: East Africa | Q61: =IFERROR(IF(RIGHT(UPPER(TRIM(F61)),1)="K",VALUE(SUBSTITUTE(SUBSTITUTE(LEFT(TRIM(F61),LEN(TRIM(F61))-1),"$",""),",",""))*1000,IF(RIGHT(UPPER(TRIM(F61)),1)="M",VALUE(SUBSTITUTE(SUBSTITUTE(LEFT(TRIM(F61),LEN(TRIM(F61))-1),"$",""),",",""))*1000000,VALUE(SUBSTITUTE(SUBSTITUTE(TRIM(F61),"$",""),",","")))),"") -> 11753 | R61: =IF(COUNTIF($A$2:A61,A61)=1,Q61,"") -> 11753
A62: DL-00061 | B62: CUST-0695 | C62: CMP-316 | D62: Analytics Add-on | E62: Proposal | F62: $5,321 | G62: Cold Outreach | H62: RACHIT LALL | I62: 2024-10-10 | J62: 45734 | M62: 0 | N62: 1 | O62: 0.9 | P62: Southeast Asia | Q62: =IFERROR(IF(RIGHT(UPPER(TRIM(F62)),1)="K",VALUE(SUBSTITUTE(SUBSTITUTE(LEFT(TRIM(F62),LEN(TRIM(F62))-1),"$",""),",",""))*1000,IF(RIGHT(UPPER(TRIM(F62)),1)="M",VALUE(SUBSTITUTE(SUBSTITUTE(LEFT(TRIM(F62),LEN(TRIM(F62))-1),"$",""),",",""))*1000000,VALUE(SUBSTITUTE(SUBSTITUTE(TRIM(F62),"$",""),",","")))),"") -> 5321 | R62: =IF(COUNTIF($A$2:A62,A62)=1,Q62,"") -> 5321
A63: DL-00062 | B63: CUST-0071 | C63: CMP-130 | D63: Analytics Add-on | E63: Qualification | F63: $8,071 | G63: Paid Search | H63: Panini Kade | I63: 2024-11-09 | J63: 45719 | M63: 0 | N63: 1 | P63: Middle East | Q63: =IFERROR(IF(RIGHT(UPPER(TRIM(F63)),1)="K",VALUE(SUBSTITUTE(SUBSTITUTE(LEFT(TRIM(F63),LEN(TRIM(F63))-1),"$",""),",",""))*1000,IF(RIGHT(UPPER(TRIM(F63)),1)="M",VALUE(SUBSTITUTE(SUBSTITUTE(LEFT(TRIM(F63),LEN(TRIM(F63))-1),"$",""),",",""))*1000000,VALUE(SUBSTITUTE(SUBSTITUTE(TRIM(F63),"$",""),",","")))),"") -> 8071 | R63: =IF(COUNTIF($A$2:A63,A63)=1,Q63,"") -> 8071
A64: DL-00063 | B64: CUST-0230 | C64: CMP-389 | D64: Analytics Add-on | E64: Prospecting | F64: $7,857 | G64: LinkedIn Ads | H64: Jalsa Parsa | I64: 2022-01-13 | J64: 44693 | M64: 0 | N64: 1 | O64: 34.2 | P64: Southeast Asia | Q64: =IFERROR(IF(RIGHT(UPPER(TRIM(F64)),1)="K",VALUE(SUBSTITUTE(SUBSTITUTE(LEFT(TRIM(F64),LEN(TRIM(F64))-1),"$",""),",",""))*1000,IF(RIGHT(UPPER(TRIM(F64)),1)="M",VALUE(SUBSTITUTE(SUBSTITUTE(LEFT(TRIM(F64),LEN(TRIM(F64))-1),"$",""),",",""))*1000000,VALUE(SUBSTITUTE(SUBSTITUTE(TRIM(F64),"$",""),",","")))),"") -> 7857 | R64: =IF(COUNTIF($A$2:A64,A64)=1,Q64,"") -> 7857
A65: DL-00064 | B65: CUST-0296 | C65: CMP-243 | D65: WorkHub Core | E65: Negotiation | F65: 2392 | G65: Inbound Organic | H65: Kashish Patla | I65: 2022-06-18 | J65: 44749 | M65: 0 | N65: 1 | O65: 10.7 | P65: ANZ | Q65: =IFERROR(IF(RIGHT(UPPER(TRIM(F65)),1)="K",VALUE(SUBSTITUTE(SUBSTITUTE(LEFT(TRIM(F65),LEN(TRIM(F65))-1),"$",""),",",""))*1000,IF(RIGHT(UPPER(TRIM(F65)),1)="M",VALUE(SUBSTITUTE(SUBSTITUTE(LEFT(TRIM(F65),LEN(TRIM(F65))-1),"$",""),",",""))*1000000,VALUE(SUBSTITUTE(SUBSTITUTE(TRIM(F65),"$",""),",","")))),"") -> 2392 | R65: =IF(COUNTIF($A$2:A65,A65)=1,Q65,"") -> 2392
A66: DL-00065 | B66: CUST-0427 | D66: WorkHub Pro | E66: Proposal | F66: 35K | G66: Cold Outreach | H66: Patrick Sama | I66: 2022-06-11 | J66: 44814 | M66: 0 | N66: 1 | O66: 0.8 | P66: Middle East | Q66: =IFERROR(IF(RIGHT(UPPER(TRIM(F66)),1)="K",VALUE(SUBSTITUTE(SUBSTITUTE(LEFT(TRIM(F66),LEN(TRIM(F66))-1),"$",""),",",""))*1000,IF(RIGHT(UPPER(TRIM(F66)),1)="M",VALUE(SUBSTITUTE(SUBSTITUTE(LEFT(TRIM(F66),LEN(TRIM(F66))-1),"$",""),",",""))*1000000,VALUE(SUBSTITUTE(SUBSTITUTE(TRIM(F66),"$",""),",","")))),"") -> 35000 | R66: =IF(COUNTIF($A$2:A66,A66)=1,Q66,"") -> 35000
A67: DL-00066 | B67: CUST-0736 | D67: API Access | E67: Proposal | F67: 5768 | G67: Paid Search | H67: VIDHI MITAL | I67: 2022-08-05 | J67: 44874 | M67: 0 | N67: 1 | O67: 18.8 | P67: ANZ | Q67: =IFERROR(IF(RIGHT(UPPER(TRIM(F67)),1)="K",VALUE(SUBSTITUTE(SUBSTITUTE(LEFT(TRIM(F67),LEN(TRIM(F67))-1),"$",""),",",""))*1000,IF(RIGHT(UPPER(TRIM(F67)),1)="M",VALUE(SUBSTITUTE(SUBSTITUTE(LEFT(TRIM(F67),LEN(TRIM(F67))-1),"$",""),",",""))*1000000,VALUE(SUBSTITUTE(SUBSTITUTE(TRIM(F67),"$",""),",","")))),"") -> 5768 | R67: =IF(COUNTIF($A$2:A67,A67)=1,Q67,"") -> 5768
A68: DL-00067 | B68: CUST-0829 | D68: WorkHub Enterprise | E68: Closed Won | F68: $161,310 | G68: Content Download | H68: Champak Rao | I68: 2024-11-18 | J68: 45747 | K68: 45649 | L68: 35 | M68: 0 | N68: 1 | O68: 17.5 | P68: East Africa | Q68: =IFERROR(IF(RIGHT(UPPER(TRIM(F68)),1)="K",VALUE(SUBSTITUTE(SUBSTITUTE(LEFT(TRIM(F68),LEN(TRIM(F68))-1),"$",""),",",""))*1000,IF(RIGHT(UPPER(TRIM(F68)),1)="M",VALUE(SUBSTITUTE(SUBSTITUTE(LEFT(TRIM(F68),LEN(TRIM(F68))-1),"$",""),",",""))*1000000,VALUE(SUBSTITUTE(SUBSTITUTE(TRIM(F68),"$",""),",","")))),"") -> 161310 | R68: =IF(COUNTIF($A$2:A68,A68)=1,Q68,"") -> 161310
A69: DL-00068 | B69: CUST-0898 | C69: CMP-372 | D69: API Access | E69: Closed Lost | F69: 16K | G69: Paid Search | H69: HEMANGINI BAHRI | I69: 2023-08-21 | J69: 45195 | K69: 45190 | L69: 31 | M69: 0 | N69: 1 | O69: 1.8 | P69: Southeast Asia | Q69: =IFERROR(IF(RIGHT(UPPER(TRIM(F69)),1)="K",VALUE(SUBSTITUTE(SUBSTITUTE(LEFT(TRIM(F69),LEN(TRIM(F69))-1),"$",""),",",""))*1000,IF(RIGHT(UPPER(TRIM(F69)),1)="M",VALUE(SUBSTITUTE(SUBSTITUTE(LEFT(TRIM(F69),LEN(TRIM(F69))-1),"$",""),",",""))*1000000,VALUE(SUBSTITUTE(SUBSTITUTE(TRIM(F69),"$",""),",","")))),"") -> 16000 | R69: =IF(COUNTIF($A$2:A69,A69)=1,Q69,"") -> 16000
A70: DL-00069 | B70: CUST-1496 | D70: WorkHub Pro | E70: Closed Won | F70: $45,871 | G70: Cold Outreach | H70: Anamika Keer | I70: 2024-07-08 | J70: 45536 | K70: 45647 | L70: 166 | M70: 0 | N70: 1 | O70: 14.4 | P70: South Asia | Q70: =IFERROR(IF(RIGHT(UPPER(TRIM(F70)),1)="K",VALUE(SUBSTITUTE(SUBSTITUTE(LEFT(TRIM(F70),LEN(TRIM(F70))-1),"$",""),",",""))*1000,IF(RIGHT(UPPER(TRIM(F70)),1)="M",VALUE(SUBSTITUTE(SUBSTITUTE(LEFT(TRIM(F70),LEN(TRIM(F70))-1),"$",""),",",""))*1000000,VALUE(SUBSTITUTE(SUBSTITUTE(TRIM(F70),"$",""),",","")))),"") -> 45871 | R70: =IF(COUNTIF($A$2:A70,A70)=1,Q70,"") -> 45871
A71: DL-00070 | B71: CUST-0341 | C71: CMP-366 | D71: WorkHub Pro | E71: Closed Won | F71: $9,657 | G71: Event | H71: Ekta Uppal | I71: 2023-11-05 | K71: 45260 | L71: 25 | M71: 1 | N71: 4 | O71: 8.7 | P71: ANZ | Q71: =IFERROR(IF(RIGHT(UPPER(TRIM(F71)),1)="K",VALUE(SUBSTITUTE(SUBSTITUTE(LEFT(TRIM(F71),LEN(TRIM(F71))-1),"$",""),",",""))*1000,IF(RIGHT(UPPER(TRIM(F71)),1)="M",VALUE(SUBSTITUTE(SUBSTITUTE(LEFT(TRIM(F71),LEN(TRIM(F71))-1),"$",""),",",""))*1000000,VALUE(SUBSTITUTE(SUBSTITUTE(TRIM(F71),"$",""),",","")))),"") -> 9657 | R71: =IF(COUNTIF($A$2:A71,A71)=1,Q71,"") -> 9657
A72: DL-00071 | B72: CUST-0228 | C72: CMP-197 | D72: API Access | E72: Prospecting | F72: 8,743 | G72: Content Download | H72: Shivani Natt | I72: 2022-09-06 | M72: 0 | N72: 1 | O72: 33.4 | P72: Southeast Asia | Q72: =IFERROR(IF(RIGHT(UPPER(TRIM(F72)),1)="K",VALUE(SUBSTITUTE(SUBSTITUTE(LEFT(TRIM(F72),LEN(TRIM(F72))-1),"$",""),",",""))*1000,IF(RIGHT(UPPER(TRIM(F72)),1)="M",VALUE(SUBSTITUTE(SUBSTITUTE(LEFT(TRIM(F72),LEN(TRIM(F72))-1),"$",""),",",""))*1000000,VALUE(SUBSTITUTE(SUBSTITUTE(TRIM(F72),"$",""),",","")))),"") -> 8743 | R72: =IF(COUNTIF($A$2:A72,A72)=1,Q72,"") -> 8743
A73: DL-00072 | B73: CUST-0285 | C73: CMP-279 | D73: Analytics Add-on | E73: Qualification | F73: 11K | G73: Event | H73: Hemangini Bahri | I73: 2024-07-30 | M73: 0 | N73: 1 | O73: 27.8 | P73: South Asia | Q73: =IFERROR(IF(RIGHT(UPPER(TRIM(F73)),1)="K",VALUE(SUBSTITUTE(SUBSTITUTE(LEFT(TRIM(F73),LEN(TRIM(F73))-1),"$",""),",",""))*1000,IF(RIGHT(UPPER(TRIM(F73)),1)="M",VALUE(SUBSTITUTE(SUBSTITUTE(LEFT(TRIM(F73),LEN(TRIM(F73))-1),"$",""),",",""))*1000000,VALUE(SUBSTITUTE(SUBSTITUTE(TRIM(F73),"$",""),",","")))),"") -> 11000 | R73: =IF(COUNTIF($A$2:A73,A73)=1,Q73,"") -> 11000
A74: DL-00073 | B74: CUST-1122 | D74: Analytics Add-on | E74: Proposal | F74: $5,728 | G74: Partner Referral | H74: vidhi mital | I74: 2024-11-20 | J74: 45742 | M74: 0 | N74: 1 | O74: 3.4 | P74: South Asia | Q74: =IFERROR(IF(RIGHT(UPPER(TRIM(F74)),1)="K",VALUE(SUBSTITUTE(SUBSTITUTE(LEFT(TRIM(F74),LEN(TRIM(F74))-1),"$",""),",",""))*1000,IF(RIGHT(UPPER(TRIM(F74)),1)="M",VALUE(SUBSTITUTE(SUBSTITUTE(LEFT(TRIM(F74),LEN(TRIM(F74))-1),"$",""),",",""))*1000000,VALUE(SUBSTITUTE(SUBSTITUTE(TRIM(F74),"$",""),",","")))),"") -> 5728 | R74: =IF(COUNTIF($A$2:A74,A74)=1,Q74,"") -> 5728
A75: DL-00074 | B75: CUST-0175 | D75: WorkHub Enterprise | E75: Prospecting | F75: $73,214 | G75: Content Download | H75: Owen Mane | I75: 2023-09-25 | J75: 45371 | M75: 0 | N75: 1 | P75: Southeast Asia | Q75: =IFERROR(IF(RIGHT(UPPER(TRIM(F75)),1)="K",VALUE(SUBSTITUTE(SUBSTITUTE(LEFT(TRIM(F75),LEN(TRIM(F75))-1),"$",""),",",""))*1000,IF(RIGHT(UPPER(TRIM(F75)),1)="M",VALUE(SUBSTITUTE(SUBSTITUTE(LEFT(TRIM(F75),LEN(TRIM(F75))-1),"$",""),",",""))*1000000,VALUE(SUBSTITUTE(SUBSTITUTE(TRIM(F75),"$",""),",","")))),"") -> 73214 | R75: =IF(COUNTIF($A$2:A75,A75)=1,Q75,"") -> 73214
A76: DL-00075 | B76: CUST-0842 | C76: CMP-137 | D76: WorkHub Core | E76: Proposal | F76: 8,451 | G76: Product-Led Signup | H76: Hemangini Bahri | I76: 2023-07-14 | J76: 45173 | M76: 0 | N76: 1 | O76: 3.3 | P76: South Asia | Q76: =IFERROR(IF(RIGHT(UPPER(TRIM(F76)),1)="K",VALUE(SUBSTITUTE(SUBSTITUTE(LEFT(TRIM(F76),LEN(TRIM(F76))-1),"$",""),",",""))*1000,IF(RIGHT(UPPER(TRIM(F76)),1)="M",VALUE(SUBSTITUTE(SUBSTITUTE(LEFT(TRIM(F76),LEN(TRIM(F76))-1),"$",""),",",""))*1000000,VALUE(SUBSTITUTE(SUBSTITUTE(TRIM(F76),"$",""),",","")))),"") -> 8451 | R76: =IF(COUNTIF($A$2:A76,A76)=1,Q76,"") -> 8451
A77: DL-00076 | B77: CUST-1447 | D77: API Access | E77: Closed Lost | F77: $23,350 | G77: Content Download | H77: Kashish Patla | I77: 2023-08-15 | J77: 45268 | K77: 45308 | L77: 155 | M77: 0 | N77: 1 | O77: 12.1 | P77: Middle East | Q77: =IFERROR(IF(RIGHT(UPPER(TRIM(F77)),1)="K",VALUE(SUBSTITUTE(SUBSTITUTE(LEFT(TRIM(F77),LEN(TRIM(F77))-1),"$",""),",",""))*1000,IF(RIGHT(UPPER(TRIM(F77)),1)="M",VALUE(SUBSTITUTE(SUBSTITUTE(LEFT(TRIM(F77),LEN(TRIM(F77))-1),"$",""),",",""))*1000000,VALUE(SUBSTITUTE(SUBSTITUTE(TRIM(F77),"$",""),",","")))),"") -> 23350 | R77: =IF(COUNTIF($A$2:A77,A77)=1,Q77,"") -> 23350
A78: DL-00077 | B78: CUST-0958 | C78: CMP-072 | D78: WorkHub Pro | E78: Closed Won | F78: 22,827 | G78: Cold Outreach | H78: Owen Mane | I78: 2023-04-01 | J78: 45034 | K78: 45077 | L78: 60 | M78: 0 | N78: 1 | O78: 34.7 | P78: Middle East | Q78: =IFERROR(IF(RIGHT(UPPER(TRIM(F78)),1)="K",VALUE(SUBSTITUTE(SUBSTITUTE(LEFT(TRIM(F78),LEN(TRIM(F78))-1),"$",""),",",""))*1000,IF(RIGHT(UPPER(TRIM(F78)),1)="M",VALUE(SUBSTITUTE(SUBSTITUTE(LEFT(TRIM(F78),LEN(TRIM(F78))-1),"$",""),",",""))*1000000,VALUE(SUBSTITUTE(SUBSTITUTE(TRIM(F78),"$",""),",","")))),"") -> 22827 | R78: =IF(COUNTIF($A$2:A78,A78)=1,Q78,"") -> 22827
A79: DL-00078 | B79: CUST-0238 | D79: Analytics Add-on | E79: Closed Lost | F79: $3,773 | G79: LinkedIn Ads | H79: Owen Mane | I79: 2024-03-25 | J79: 45509 | K79: 45452 | L79: 76 | M79: 0 | N79: 1 | O79: 1.9 | P79: Southeast Asia | Q79: =IFERROR(IF(RIGHT(UPPER(TRIM(F79)),1)="K",VALUE(SUBSTITUTE(SUBSTITUTE(LEFT(TRIM(F79),LEN(TRIM(F79))-1),"$",""),",",""))*1000,IF(RIGHT(UPPER(TRIM(F79)),1)="M",VALUE(SUBSTITUTE(SUBSTITUTE(LEFT(TRIM(F79),LEN(TRIM(F79))-1),"$",""),",",""))*1000000,VALUE(SUBSTITUTE(SUBSTITUTE(TRIM(F79),"$",""),",","")))),"") -> 3773 | R79: =IF(COUNTIF($A$2:A79,A79)=1,Q79,"") -> 3773
A80: DL-00079 | B80: CUST-1070 | C80: CMP-336 | D80: WorkHub Pro | E80: Proposal | F80: 31403 | G80: Inbound Organic | H80: Jasmit Gour | I80: 2022-09-18 | J80: 44997 | M80: 0 | N80: 1 | O80: 12.3 | P80: East Africa | Q80: =IFERROR(IF(RIGHT(UPPER(TRIM(F80)),1)="K",VALUE(SUBSTITUTE(SUBSTITUTE(LEFT(TRIM(F80),LEN(TRIM(F80))-1),"$",""),",",""))*1000,IF(RIGHT(UPPER(TRIM(F80)),1)="M",VALUE(SUBSTITUTE(SUBSTITUTE(LEFT(TRIM(F80),LEN(TRIM(F80))-1),"$",""),",",""))*1000000,VALUE(SUBSTITUTE(SUBSTITUTE(TRIM(F80),"$",""),",","")))),"") -> 31403 | R80: =IF(COUNTIF($A$2:A80,A80)=1,Q80,"") -> 31403
A81: DL-00080 | B81: CUST-0024 | C81: CMP-325 | D81: Analytics Add-on | E81: Closed Won | F81: 6144 | G81: Product-Led Signup | H81: Patrick Sama | I81: 2023-06-14 | J81: 45184 | K81: 45147 | L81: 56 | M81: 0 | N81: 1 | O81: 14.7 | P81: South Asia | Q81: =IFERROR(IF(RIGHT(UPPER(TRIM(F81)),1)="K",VALUE(SUBSTITUTE(SUBSTITUTE(LEFT(TRIM(F81),LEN(TRIM(F81))-1),"$",""),",",""))*1000,IF(RIGHT(UPPER(TRIM(F81)),1)="M",VALUE(SUBSTITUTE(SUBSTITUTE(LEFT(TRIM(F81),LEN(TRIM(F81))-1),"$",""),",",""))*1000000,VALUE(SUBSTITUTE(SUBSTITUTE(TRIM(F81),"$",""),",","")))),"") -> 6144 | R81: =IF(COUNTIF($A$2:A81,A81)=1,Q81,"") -> 6144
A82: DL-00081 | B82: CUST-0181 | C82: CMP-210 | D82: WorkHub Enterprise | E82: Qualification | F82: $130,625 | G82: Cold Outreach | H82: Aachal Soni | I82: 2023-09-26 | J82: 45270 | M82: 0 | N82: 1 | P82: Southeast Asia | Q82: =IFERROR(IF(RIGHT(UPPER(TRIM(F82)),1)="K",VALUE(SUBSTITUTE(SUBSTITUTE(LEFT(TRIM(F82),LEN(TRIM(F82))-1),"$",""),",",""))*1000,IF(RIGHT(UPPER(TRIM(F82)),1)="M",VALUE(SUBSTITUTE(SUBSTITUTE(LEFT(TRIM(F82),LEN(TRIM(F82))-1),"$",""),",",""))*1000000,VALUE(SUBSTITUTE(SUBSTITUTE(TRIM(F82),"$",""),",","")))),"") -> 130625 | R82: =IF(COUNTIF($A$2:A82,A82)=1,Q82,"") -> 130625
A83: DL-00082 | B83: CUST-0208 | C83: CMP-142 | D83: WorkHub Pro | E83: Closed Won | F83: 42136 | G83: LinkedIn Ads | H83: vidhi mital | I83: 2024-03-13 | J83: 45478 | K83: 45562 | L83: 198 | M83: 0 | N83: 1 | O83: 33.3 | P83: East Africa | Q83: =IFERROR(IF(RIGHT(UPPER(TRIM(F83)),1)="K",VALUE(SUBSTITUTE(SUBSTITUTE(LEFT(TRIM(F83),LEN(TRIM(F83))-1),"$",""),",",""))*1000,IF(RIGHT(UPPER(TRIM(F83)),1)="M",VALUE(SUBSTITUTE(SUBSTITUTE(LEFT(TRIM(F83),LEN(TRIM(F83))-1),"$",""),",",""))*1000000,VALUE(SUBSTITUTE(SUBSTITUTE(TRIM(F83),"$",""),",","")))),"") -> 42136 | R83: =IF(COUNTIF($A$2:A83,A83)=1,Q83,"") -> 42136
A84: DL-00083 | B84: CUST-0838 | C84: CMP-262 | D84: API Access | E84: Proposal | F84: 15K | G84: Partner Referral | H84: Jairaj Panchal | I84: 2022-11-23 | M84: 0 | N84: 1 | O84: 14.4 | P84: East Africa | Q84: =IFERROR(IF(RIGHT(UPPER(TRIM(F84)),1)="K",VALUE(SUBSTITUTE(SUBSTITUTE(LEFT(TRIM(F84),LEN(TRIM(F84))-1),"$",""),",",""))*1000,IF(RIGHT(UPPER(TRIM(F84)),1)="M",VALUE(SUBSTITUTE(SUBSTITUTE(LEFT(TRIM(F84),LEN(TRIM(F84))-1),"$",""),",",""))*1000000,VALUE(SUBSTITUTE(SUBSTITUTE(TRIM(F84),"$",""),",","")))),"") -> 15000 | R84: =IF(COUNTIF($A$2:A84,A84)=1,Q84,"") -> 15000
A85: DL-00084 | B85: CUST-0618 | C85: CMP-327 | D85: WorkHub Pro | E85: Qualification | F85: 43342 | G85: Cold Outreach | H85: Lakshmi Hayre | I85: 2024-05-08 | J85: 45575 | M85: 0 | N85: 1 | P85: Middle East | Q85: =IFERROR(IF(RIGHT(UPPER(TRIM(F85)),1)="K",VALUE(SUBSTITUTE(SUBSTITUTE(LEFT(TRIM(F85),LEN(TRIM(F85))-1),"$",""),",",""))*1000,IF(RIGHT(UPPER(TRIM(F85)),1)="M",VALUE(SUBSTITUTE(SUBSTITUTE(LEFT(TRIM(F85),LEN(TRIM(F85))-1),"$",""),",",""))*1000000,VALUE(SUBSTITUTE(SUBSTITUTE(TRIM(F85),"$",""),",","")))),"") -> 43342 | R85: =IF(COUNTIF($A$2:A85,A85)=1,Q85,"") -> 43342
A86: DL-00085 | B86: CUST-0730 | C86: CMP-101 | D86: WorkHub Pro | E86: Demo | F86: $34,284 | G86: LinkedIn Ads | H86: Rachit Lall | I86: 2023-08-03 | J86: 45187 | M86: 0 | N86: 1 | O86: 24.9 | P86: South Asia | Q86: =IFERROR(IF(RIGHT(UPPER(TRIM(F86)),1)="K",VALUE(SUBSTITUTE(SUBSTITUTE(LEFT(TRIM(F86),LEN(TRIM(F86))-1),"$",""),",",""))*1000,IF(RIGHT(UPPER(TRIM(F86)),1)="M",VALUE(SUBSTITUTE(SUBSTITUTE(LEFT(TRIM(F86),LEN(TRIM(F86))-1),"$",""),",",""))*1000000,VALUE(SUBSTITUTE(SUBSTITUTE(TRIM(F86),"$",""),",","")))),"") -> 34284 | R86: =IF(COUNTIF($A$2:A86,A86)=1,Q86,"") -> 34284
A87: DL-00086 | B87: CUST-0950 | C87: CMP-215 | D87: WorkHub Pro | E87: Prospecting | F87: 28817 | G87: Product-Led Signup | H87: Anamika Keer | I87: 2023-08-12 | J87: 45210 | M87: 0 | N87: 1 | O87: 18.5 | P87: ANZ | Q87: =IFERROR(IF(RIGHT(UPPER(TRIM(F87)),1)="K",VALUE(SUBSTITUTE(SUBSTITUTE(LEFT(TRIM(F87),LEN(TRIM(F87))-1),"$",""),",",""))*1000,IF(RIGHT(UPPER(TRIM(F87)),1)="M",VALUE(SUBSTITUTE(SUBSTITUTE(LEFT(TRIM(F87),LEN(TRIM(F87))-1),"$",""),",",""))*1000000,VALUE(SUBSTITUTE(SUBSTITUTE(TRIM(F87),"$",""),",","")))),"") -> 28817 | R87: =IF(COUNTIF($A$2:A87,A87)=1,Q87,"") -> 28817
A88: DL-00087 | B88: CUST-0038 | C88: CMP-160 | D88: WorkHub Enterprise | E88: Closed Won | F88: 80940 | G88: Paid Search | H88: Amruta Sinha | I88: 2023-09-29 | J88: 45234 | K88: 45265 | L88: 67 | M88: 1 | N88: 1 | O88: 4.1 | P88: East Africa | Q88: =IFERROR(IF(RIGHT(UPPER(TRIM(F88)),1)="K",VALUE(SUBSTITUTE(SUBSTITUTE(LEFT(TRIM(F88),LEN(TRIM(F88))-1),"$",""),",",""))*1000,IF(RIGHT(UPPER(TRIM(F88)),1)="M",VALUE(SUBSTITUTE(SUBSTITUTE(LEFT(TRIM(F88),LEN(TRIM(F88))-1),"$",""),",",""))*1000000,VALUE(SUBSTITUTE(SUBSTITUTE(TRIM(F88),"$",""),",","")))),"") -> 80940 | R88: =IF(COUNTIF($A$2:A88,A88)=1,Q88,"") -> 80940
A89: DL-00088 | B89: CUST-0491 | C89: CMP-319 | D89: Analytics Add-on | E89: Qualification | F89: $4,832 | G89: Content Download | H89: VIDHI MITAL | I89: 30/04/2022 | J89: 44747 | M89: 0 | N89: 1 | O89: 15.6 | P89: South Asia | Q89: =IFERROR(IF(RIGHT(UPPER(TRIM(F89)),1)="K",VALUE(SUBSTITUTE(SUBSTITUTE(LEFT(TRIM(F89),LEN(TRIM(F89))-1),"$",""),",",""))*1000,IF(RIGHT(UPPER(TRIM(F89)),1)="M",VALUE(SUBSTITUTE(SUBSTITUTE(LEFT(TRIM(F89),LEN(TRIM(F89))-1),"$",""),",",""))*1000000,VALUE(SUBSTITUTE(SUBSTITUTE(TRIM(F89),"$",""),",","")))),"") -> 4832 | R89: =IF(COUNTIF($A$2:A89,A89)=1,Q89,"") -> 4832
A90: DL-00089 | B90: CUST-0566 | C90: CMP-024 | D90: WorkHub Core | E90: Closed Lost | F90: 7,502 | G90: Webinar | H90: Mason Solanki | I90: 2022-08-08 | J90: 44821 | K90: 44920 | L90: 139 | M90: 0 | N90: 1 | O90: 26.7 | P90: South Asia | Q90: =IFERROR(IF(RIGHT(UPPER(TRIM(F90)),1)="K",VALUE(SUBSTITUTE(SUBSTITUTE(LEFT(TRIM(F90),LEN(TRIM(F90))-1),"$",""),",",""))*1000,IF(RIGHT(UPPER(TRIM(F90)),1)="M",VALUE(SUBSTITUTE(SUBSTITUTE(LEFT(TRIM(F90),LEN(TRIM(F90))-1),"$",""),",",""))*1000000,VALUE(SUBSTITUTE(SUBSTITUTE(TRIM(F90),"$",""),",","")))),"") -> 7502 | R90: =IF(COUNTIF($A$2:A90,A90)=1,Q90,"") -> 7502
A91: DL-00090 | B91: CUST-0795 | C91: CMP-005 | D91: WorkHub Pro | E91: Closed Won | F91: 20K | G91: Cold Outreach | H91: Ekta Uppal | I91: 2024-11-05 | J91: 45688 | K91: 45783 | L91: 182 | M91: 0 | N91: 1 | O91: 18.3 | P91: South Asia | Q91: =IFERROR(IF(RIGHT(UPPER(TRIM(F91)),1)="K",VALUE(SUBSTITUTE(SUBSTITUTE(LEFT(TRIM(F91),LEN(TRIM(F91))-1),"$",""),",",""))*1000,IF(RIGHT(UPPER(TRIM(F91)),1)="M",VALUE(SUBSTITUTE(SUBSTITUTE(LEFT(TRIM(F91),LEN(TRIM(F91))-1),"$",""),",",""))*1000000,VALUE(SUBSTITUTE(SUBSTITUTE(TRIM(F91),"$",""),",","")))),"") -> 20000 | R91: =IF(COUNTIF($A$2:A91,A91)=1,Q91,"") -> 20000
A92: DL-00091 | B92: CUST-0897 | C92: CMP-240 | D92: WorkHub Enterprise | E92: Qualification | F92: 141762 | G92: Content Download | H92: ati seshadri | I92: 2022-12-07 | J92: 45030 | M92: 0 | N92: 1 | O92: 0.1 | P92: South Asia | Q92: =IFERROR(IF(RIGHT(UPPER(TRIM(F92)),1)="K",VALUE(SUBSTITUTE(SUBSTITUTE(LEFT(TRIM(F92),LEN(TRIM(F92))-1),"$",""),",",""))*1000,IF(RIGHT(UPPER(TRIM(F92)),1)="M",VALUE(SUBSTITUTE(SUBSTITUTE(LEFT(TRIM(F92),LEN(TRIM(F92))-1),"$",""),",",""))*1000000,VALUE(SUBSTITUTE(SUBSTITUTE(TRIM(F92),"$",""),",","")))),"") -> 141762 | R92: =IF(COUNTIF($A$2:A92,A92)=1,Q92,"") -> 141762
A93: DL-00092 | B93: CUST-0959 | C93: CMP-302 | D93: WorkHub Core | E93: Closed Lost | F93: 2K | G93: Paid Search | H93: CHAMPAK RAO | I93: 2024-11-14 | J93: 45664 | K93: 45681 | L93: 71 | M93: 0 | N93: 1 | O93: 23.7 | P93: ANZ | Q93: =IFERROR(IF(RIGHT(UPPER(TRIM(F93)),1)="K",VALUE(SUBSTITUTE(SUBSTITUTE(LEFT(TRIM(F93),LEN(TRIM(F93))-1),"$",""),",",""))*1000,IF(RIGHT(UPPER(TRIM(F93)),1)="M",VALUE(SUBSTITUTE(SUBSTITUTE(LEFT(TRIM(F93),LEN(TRIM(F93))-1),"$",""),",",""))*1000000,VALUE(SUBSTITUTE(SUBSTITUTE(TRIM(F93),"$",""),",","")))),"") -> 2000 | R93: =IF(COUNTIF($A$2:A93,A93)=1,Q93,"") -> 2000
A94: DL-00093 | B94: CUST-1005 | C94: CMP-371 | D94: WorkHub Core | E94: Proposal | F94: $5,901 | G94: Event | H94: patrick sama | I94: 2024-05-08 | J94: 45436 | M94: 0 | N94: 1 | P94: Middle East | Q94: =IFERROR(IF(RIGHT(UPPER(TRIM(F94)),1)="K",VALUE(SUBSTITUTE(SUBSTITUTE(LEFT(TRIM(F94),LEN(TRIM(F94))-1),"$",""),",",""))*1000,IF(RIGHT(UPPER(TRIM(F94)),1)="M",VALUE(SUBSTITUTE(SUBSTITUTE(LEFT(TRIM(F94),LEN(TRIM(F94))-1),"$",""),",",""))*1000000,VALUE(SUBSTITUTE(SUBSTITUTE(TRIM(F94),"$",""),",","")))),"") -> 5901 | R94: =IF(COUNTIF($A$2:A94,A94)=1,Q94,"") -> 5901
A95: DL-00094 | B95: CUST-0954 | C95: CMP-020 | D95: API Access | E95: Prospecting | F95: $7,951 | G95: LinkedIn Ads | H95: Owen Mane | I95: 2022-10-04 | J95: 44900 | M95: 0 | N95: 1 | O95: 28.8 | P95: ANZ | Q95: =IFERROR(IF(RIGHT(UPPER(TRIM(F95)),1)="K",VALUE(SUBSTITUTE(SUBSTITUTE(LEFT(TRIM(F95),LEN(TRIM(F95))-1),"$",""),",",""))*1000,IF(RIGHT(UPPER(TRIM(F95)),1)="M",VALUE(SUBSTITUTE(SUBSTITUTE(LEFT(TRIM(F95),LEN(TRIM(F95))-1),"$",""),",",""))*1000000,VALUE(SUBSTITUTE(SUBSTITUTE(TRIM(F95),"$",""),",","")))),"") -> 7951 | R95: =IF(COUNTIF($A$2:A95,A95)=1,Q95,"") -> 7951
A96: DL-00095 | B96: CUST-0784 | C96: CMP-187 | D96: API Access | E96: Demo | F96: $17,518 | G96: Event | H96: Lakshmi Hayre | I96: 25/06/2024 | J96: 45594 | M96: 0 | N96: 1 | O96: 4.1 | P96: Southeast Asia | Q96: =IFERROR(IF(RIGHT(UPPER(TRIM(F96)),1)="K",VALUE(SUBSTITUTE(SUBSTITUTE(LEFT(TRIM(F96),LEN(TRIM(F96))-1),"$",""),",",""))*1000,IF(RIGHT(UPPER(TRIM(F96)),1)="M",VALUE(SUBSTITUTE(SUBSTITUTE(LEFT(TRIM(F96),LEN(TRIM(F96))-1),"$",""),",",""))*1000000,VALUE(SUBSTITUTE(SUBSTITUTE(TRIM(F96),"$",""),",","")))),"") -> 17518 | R96: =IF(COUNTIF($A$2:A96,A96)=1,Q96,"") -> 17518
A97: DL-00096 | B97: CUST-0113 | C97: CMP-318 | D97: WorkHub Core | E97: Closed Won | F97: $3,028 | G97: Partner Referral | H97: kashish patla | I97: 2022-01-20 | J97: 44729 | K97: 44641 | L97: 60 | M97: 1 | N97: 2 | O97: 24.6 | P97: Southeast Asia | Q97: =IFERROR(IF(RIGHT(UPPER(TRIM(F97)),1)="K",VALUE(SUBSTITUTE(SUBSTITUTE(LEFT(TRIM(F97),LEN(TRIM(F97))-1),"$",""),",",""))*1000,IF(RIGHT(UPPER(TRIM(F97)),1)="M",VALUE(SUBSTITUTE(SUBSTITUTE(LEFT(TRIM(F97),LEN(TRIM(F97))-1),"$",""),",",""))*1000000,VALUE(SUBSTITUTE(SUBSTITUTE(TRIM(F97),"$",""),",","")))),"") -> 3028 | R97: =IF(COUNTIF($A$2:A97,A97)=1,Q97,"") -> 3028
A98: DL-00097 | B98: CUST-0591 | C98: CMP-037 | D98: API Access | E98: Closed Won | F98: 19K | G98: Content Download | H98: jasmit gour | I98: 2022-08-08 | J98: 44815 | K98: 44881 | L98: 100 | M98: 0 | N98: 1 | P98: Middle East | Q98: =IFERROR(IF(RIGHT(UPPER(TRIM(F98)),1)="K",VALUE(SUBSTITUTE(SUBSTITUTE(LEFT(TRIM(F98),LEN(TRIM(F98))-1),"$",""),",",""))*1000,IF(RIGHT(UPPER(TRIM(F98)),1)="M",VALUE(SUBSTITUTE(SUBSTITUTE(LEFT(TRIM(F98),LEN(TRIM(F98))-1),"$",""),",",""))*1000000,VALUE(SUBSTITUTE(SUBSTITUTE(TRIM(F98),"$",""),",","")))),"") -> 19000 | R98: =IF(COUNTIF($A$2:A98,A98)=1,Q98,"") -> 19000
A99: DL-00098 | B99: CUST-1463 | C99: CMP-142 | D99: API Access | E99: Closed Lost | F99: 8,347 | G99: Partner Referral | H99: Vidhi Mital | I99: 2023-11-07 | K99: 45261 | L99: 24 | M99: 0 | N99: 1 | O99: 28.7 | P99: ANZ | Q99: =IFERROR(IF(RIGHT(UPPER(TRIM(F99)),1)="K",VALUE(SUBSTITUTE(SUBSTITUTE(LEFT(TRIM(F99),LEN(TRIM(F99))-1),"$",""),",",""))*1000,IF(RIGHT(UPPER(TRIM(F99)),1)="M",VALUE(SUBSTITUTE(SUBSTITUTE(LEFT(TRIM(F99),LEN(TRIM(F99))-1),"$",""),",",""))*1000000,VALUE(SUBSTITUTE(SUBSTITUTE(TRIM(F99),"$",""),",","")))),"") -> 8347 | R99: =IF(COUNTIF($A$2:A99,A99)=1,Q99,"") -> 8347
A100: DL-00099 | B100: CUST-0319 | C100: CMP-120 | D100: Analytics Add-on | E100: Proposal | F100: 4041 | G100: Product-Led Signup | H100: Panini Kade | I100: 2022-08-16 | J100: 44918 | M100: 0 | N100: 1 | P100: East Africa | Q100: =IFERROR(IF(RIGHT(UPPER(TRIM(F100)),1)="K",VALUE(SUBSTITUTE(SUBSTITUTE(LEFT(TRIM(F100),LEN(TRIM(F100))-1),"$",""),",",""))*1000,IF(RIGHT(UPPER(TRIM(F100)),1)="M",VALUE(SUBSTITUTE(SUBSTITUTE(LEFT(TRIM(F100),LEN(TRIM(F100))-1),"$",""),",",""))*1000000,VALUE(SUBSTITUTE(SUBSTITUTE(TRIM(F100),"$",""),",","")))),"") -> 4041 | R100: =IF(COUNTIF($A$2:A100,A100)=1,Q100,"") -> 4041
...

Sheet Customers
A1: Customer_ID | B1: Company_Name | C1: Industry | D1: Company_Size | E1: Customer_Tier | F1: Region | G1: Onboarding_Date | H1: Renewal_Status | I1: MRR_USD | J1: NPS_Score | K1: Subscribed_Plan | L1: CSM_Name | M1: Contract_Months | N1: Churn_Risk_Flag | O1: SLA_Breach_90D
A2: CUST-0001 | B2: Patla-Gaba | C2: Retail | D2: 1–50 | E2: Mid-Market | F2: Southeast Asia | G2: 2024-05-19 | H2: At Risk | I2: 911.36 | J2: 8 | K2: WorkHub Core | L2: Hemangini Lalla | M2: 24 | N2: 1 | O2: =IF(COUNTIF($A$2:A2,A2)>1,"",--(COUNTIFS(Support_Tickets!$B:$B,A2,Support_Tickets!$P:$P,">="&G2,Support_Tickets!$P:$P,"<="&G2+90,Support_Tickets!$K:$K,"No")>0)) -> 0
A3: CUST-0002 | B3: Pant-Kadakia | C3: BFSI | D3: 5000+ | E3: Enterprise | F3: Southeast Asia | G3: 2023-11-27 | H3: Active | I3: 10215.15 | J3: 9 | K3: WorkHub Pro | L3: Tripti Yadav | M3: 24 | N3: 0 | O3: =IF(COUNTIF($A$2:A3,A3)>1,"",--(COUNTIFS(Support_Tickets!$B:$B,A3,Support_Tickets!$P:$P,">="&G3,Support_Tickets!$P:$P,"<="&G3+90,Support_Tickets!$K:$K,"No")>0)) -> 0
A4: CUST-0003 | B4: Loke, Bora and Garg | C4: EdTech | D4: 1–50 | E4: Mid-Market | F4: South Asia | G4: 2024-01-24 | H4: Active | I4: 3723.34 | J4: 15 | K4: WorkHub Core | L4: Janaki Handa | M4: 12 | N4: 0 | O4: =IF(COUNTIF($A$2:A4,A4)>1,"",--(COUNTIFS(Support_Tickets!$B:$B,A4,Support_Tickets!$P:$P,">="&G4,Support_Tickets!$P:$P,"<="&G4+90,Support_Tickets!$K:$K,"No")>0)) -> 0
A5: CUST-0004 | B5: Konda, Gade and Shere | C5: Logistics | D5: 1001–5000 | E5: Mid-Market | F5: Southeast Asia | G5: 2022-05-06 | H5: Active | I5: 1352.5 | J5: 91 | K5: WorkHub Pro | L5: Lajita Chatterjee | M5: 36 | N5: 0 | O5: =IF(COUNTIF($A$2:A5,A5)>1,"",--(COUNTIFS(Support_Tickets!$B:$B,A5,Support_Tickets!$P:$P,">="&G5,Support_Tickets!$P:$P,"<="&G5+90,Support_Tickets!$K:$K,"No")>0)) -> 0
A6: CUST-0005 | B6: Madan-Kanda | C6: Healthcare | D6: 5000+ | E6: SMB | F6: East Africa | G6: 2022-10-25 | H6: At Risk | I6: 598.27 | K6: WorkHub Core | L6: Fariq Kaul | M6: 12 | N6: 1 | O6: =IF(COUNTIF($A$2:A6,A6)>1,"",--(COUNTIFS(Support_Tickets!$B:$B,A6,Support_Tickets!$P:$P,">="&G6,Support_Tickets!$P:$P,"<="&G6+90,Support_Tickets!$K:$K,"No")>0)) -> 0
A7: CUST-0006 | B7: Nair, Bhalla and Karnik | C7: EdTech | D7: 51–200 | E7: SMB | F7: Southeast Asia | G7: 2024-03-20 | H7: Active | I7: 500.59 | J7: 59 | K7: WorkHub Core | L7: Gagan Sami | M7: 12 | N7: 0 | O7: =IF(COUNTIF($A$2:A7,A7)>1,"",--(COUNTIFS(Support_Tickets!$B:$B,A7,Support_Tickets!$P:$P,">="&G7,Support_Tickets!$P:$P,"<="&G7+90,Support_Tickets!$K:$K,"No")>0)) -> 1
A8: CUST-0007 | B8: Mutti Group | C8: Government | D8: 5000+ | E8: SMB | F8: ANZ | G8: 2024-02-27 | H8: Churned | I8: 187.73 | J8: 40 | K8: WorkHub Core | L8: Janaki Handa | M8: 36 | N8: 1 | O8: =IF(COUNTIF($A$2:A8,A8)>1,"",--(COUNTIFS(Support_Tickets!$B:$B,A8,Support_Tickets!$P:$P,">="&G8,Support_Tickets!$P:$P,"<="&G8+90,Support_Tickets!$K:$K,"No")>0)) -> 0
A9: CUST-0008 | B9: Bhatti-Kakar | C9: Retail | D9: 5000+ | E9: Enterprise | F9: East Africa | G9: 2022-07-06 | H9: Active | I9: 11040.09 | J9: 7 | K9: WorkHub Enterprise | L9: Gayathri Chaudry | M9: 12 | N9: 0 | O9: =IF(COUNTIF($A$2:A9,A9)>1,"",--(COUNTIFS(Support_Tickets!$B:$B,A9,Support_Tickets!$P:$P,">="&G9,Support_Tickets!$P:$P,"<="&G9+90,Support_Tickets!$K:$K,"No")>0)) -> 1
A10: CUST-0009 | B10: Murty, Kala and Tata | C10: EdTech | D10: 201–1000 | E10: Mid-Market | F10: East Africa | G10: 2024-07-05 | H10: Active | I10: 1428.17 | J10: 70 | K10: WorkHub Core | L10: Lajita Mall | M10: 12 | N10: 0 | O10: =IF(COUNTIF($A$2:A10,A10)>1,"",--(COUNTIFS(Support_Tickets!$B:$B,A10,Support_Tickets!$P:$P,">="&G10,Support_Tickets!$P:$P,"<="&G10+90,Support_Tickets!$K:$K,"No")>0)) -> 0
A11: CUST-0010 | B11: Shanker-Dhar | C11: Retail | D11: 5000+ | E11: Enterprise | F11: East Africa | G11: 2022-06-07 | H11: Churned | I11: 16628.01 | K11: WorkHub Enterprise | L11: Aryan Maharaj | M11: 12 | N11: 1 | O11: =IF(COUNTIF($A$2:A11,A11)>1,"",--(COUNTIFS(Support_Tickets!$B:$B,A11,Support_Tickets!$P:$P,">="&G11,Support_Tickets!$P:$P,"<="&G11+90,Support_Tickets!$K:$K,"No")>0)) -> 0
A12: CUST-0011 | B12: Dewan-Koshy | C12: Real Estate | D12: 201–1000 | E12: Mid-Market | F12: Southeast Asia | G12: 2024-02-25 | H12: Churned | I12: 896.91 | J12: 80 | K12: WorkHub Core | L12: Chakradev Kari | M12: 12 | N12: 1 | O12: =IF(COUNTIF($A$2:A12,A12)>1,"",--(COUNTIFS(Support_Tickets!$B:$B,A12,Support_Tickets!$P:$P,">="&G12,Support_Tickets!$P:$P,"<="&G12+90,Support_Tickets!$K:$K,"No")>0)) -> 0
A13: CUST-0012 | B13: Yohannan, Lall and Sangha | C13: Media & Entertainment | D13: 201–1000 | E13: Mid-Market | F13: ANZ | G13: 2022-03-16 | H13: Active | I13: 2129.99 | J13: 59 | K13: WorkHub Pro | L13: Lajita Chatterjee | M13: 36 | N13: 0 | O13: =IF(COUNTIF($A$2:A13,A13)>1,"",--(COUNTIFS(Support_Tickets!$B:$B,A13,Support_Tickets!$P:$P,">="&G13,Support_Tickets!$P:$P,"<="&G13+90,Support_Tickets!$K:$K,"No")>0)) -> 0
A14: CUST-0013 | B14: Rastogi, Pathak and Kanda | C14: Manufacturing | D14: 1001–5000 | E14: Enterprise | F14: Southeast Asia | G14: 2024-02-18 | H14: Churned | I14: 8467.62 | K14: WorkHub Pro | L14: Nathaniel Sami | M14: 12 | N14: 1 | O14: =IF(COUNTIF($A$2:A14,A14)>1,"",--(COUNTIFS(Support_Tickets!$B:$B,A14,Support_Tickets!$P:$P,">="&G14,Support_Tickets!$P:$P,"<="&G14+90,Support_Tickets!$K:$K,"No")>0)) -> 0
A15: CUST-0014 | B15: Upadhyay Group | C15: Logistics | D15: 1001–5000 | E15: Enterprise | F15: East Africa | G15: 2023-03-05 | H15: At Risk | I15: 6235.8 | J15: 41 | K15: WorkHub Pro | L15: Saumya Mall | M15: 12 | N15: 1 | O15: =IF(COUNTIF($A$2:A15,A15)>1,"",--(COUNTIFS(Support_Tickets!$B:$B,A15,Support_Tickets!$P:$P,">="&G15,Support_Tickets!$P:$P,"<="&G15+90,Support_Tickets!$K:$K,"No")>0)) -> 0
A16: CUST-0015 | B16: Batta Inc | C16: Telecom | D16: 1001–5000 | E16: Mid-Market | F16: ANZ | G16: 2024-06-19 | H16: Active | I16: 3824.74 | J16: 64 | K16: WorkHub Pro | L16: Saumya Mall | M16: 36 | N16: 0 | O16: =IF(COUNTIF($A$2:A16,A16)>1,"",--(COUNTIFS(Support_Tickets!$B:$B,A16,Support_Tickets!$P:$P,">="&G16,Support_Tickets!$P:$P,"<="&G16+90,Support_Tickets!$K:$K,"No")>0)) -> 0
A17: CUST-0016 | B17: Dutta Ltd | C17: BFSI | D17: 201–1000 | E17: Mid-Market | F17: ANZ | G17: 2023-09-04 | H17: Churned | I17: 2305.88 | K17: WorkHub Pro | L17: Kritika Brar | M17: 12 | N17: 1 | O17: =IF(COUNTIF($A$2:A17,A17)>1,"",--(COUNTIFS(Support_Tickets!$B:$B,A17,Support_Tickets!$P:$P,">="&G17,Support_Tickets!$P:$P,"<="&G17+90,Support_Tickets!$K:$K,"No")>0)) -> 0
A18: CUST-0017 | B18: Bhatt-Rajan | C18: Manufacturing | D18: 1001–5000 | E18: Mid-Market | F18: Middle East | G18: 2022-02-16 | H18: Churned | I18: 1422.9 | J18: 70 | K18: WorkHub Core | L18: Fariq Kaul | M18: 24 | N18: 1 | O18: =IF(COUNTIF($A$2:A18,A18)>1,"",--(COUNTIFS(Support_Tickets!$B:$B,A18,Support_Tickets!$P:$P,">="&G18,Support_Tickets!$P:$P,"<="&G18+90,Support_Tickets!$K:$K,"No")>0)) -> 1
A19: CUST-0018 | B19: Sidhu-Wadhwa | C19: Logistics | D19: 5000+ | E19: Mid-Market | F19: East Africa | G19: 2022-05-02 | H19: Active | I19: 1994.23 | J19: 43 | K19: WorkHub Core | L19: Viraj Tiwari | M19: 12 | N19: 0 | O19: =IF(COUNTIF($A$2:A19,A19)>1,"",--(COUNTIFS(Support_Tickets!$B:$B,A19,Support_Tickets!$P:$P,">="&G19,Support_Tickets!$P:$P,"<="&G19+90,Support_Tickets!$K:$K,"No")>0)) -> 0
A20: CUST-0019 | B20: Apte-Contractor | C20: Media & Entertainment | D20: 5000+ | E20: SMB | F20: South Asia | G20: 16/02/2022 | H20: Churned | I20: 662.78 | J20: 66 | K20: WorkHub Core | L20: Lajita Chatterjee | M20: 36 | N20: 1 | O20: =IF(COUNTIF($A$2:A20,A20)>1,"",--(COUNTIFS(Support_Tickets!$B:$B,A20,Support_Tickets!$P:$P,">="&G20,Support_Tickets!$P:$P,"<="&G20+90,Support_Tickets!$K:$K,"No")>0)) -> 0
A21: CUST-0020 | B21: Yadav, Loke and Oak | C21: Media & Entertainment | D21: 5000+ | E21: Enterprise | F21: Middle East | G21: 2023-08-31 | H21: At Risk | I21: 11452.76 | J21: 90 | K21: WorkHub Pro | L21: Aryan Maharaj | M21: 24 | N21: 1 | O21: =IF(COUNTIF($A$2:A21,A21)>1,"",--(COUNTIFS(Support_Tickets!$B:$B,A21,Support_Tickets!$P:$P,">="&G21,Support_Tickets!$P:$P,"<="&G21+90,Support_Tickets!$K:$K,"No")>0)) -> 0
A22: CUST-0021 | B22: Memon Group | C22: Healthcare | D22: 1001–5000 | E22: SMB | F22: East Africa | G22: 2022-11-12 | H22: Churned | I22: 581.63 | K22: WorkHub Core | L22: Nathaniel Sami | M22: 36 | N22: 1 | O22: =IF(COUNTIF($A$2:A22,A22)>1,"",--(COUNTIFS(Support_Tickets!$B:$B,A22,Support_Tickets!$P:$P,">="&G22,Support_Tickets!$P:$P,"<="&G22+90,Support_Tickets!$K:$K,"No")>0)) -> 0
A23: CUST-0022 | B23: Setty Inc | C23: Government | D23: 51–200 | E23: SMB | F23: East Africa | G23: 2023-10-07 | H23: At Risk | I23: 366.13 | J23: 87 | K23: WorkHub Core | L23: Saumya Mall | M23: 12 | N23: 1 | O23: =IF(COUNTIF($A$2:A23,A23)>1,"",--(COUNTIFS(Support_Tickets!$B:$B,A23,Support_Tickets!$P:$P,">="&G23,Support_Tickets!$P:$P,"<="&G23+90,Support_Tickets!$K:$K,"No")>0)) -> 0
A24: CUST-0023 | B24: Lall, Tella and Gokhale | C24: Media & Entertainment | D24: 51–200 | E24: Mid-Market | F24: ANZ | G24: 2023-12-09 | H24: Active | I24: 2756.73 | J24: 60 | K24: WorkHub Pro | L24: Viraj Tiwari | M24: 36 | N24: 0 | O24: =IF(COUNTIF($A$2:A24,A24)>1,"",--(COUNTIFS(Support_Tickets!$B:$B,A24,Support_Tickets!$P:$P,">="&G24,Support_Tickets!$P:$P,"<="&G24+90,Support_Tickets!$K:$K,"No")>0)) -> 0
A25: CUST-0024 | B25: Cherian, Misra and Tripathi | C25: Manufacturing | D25: 1001–5000 | E25: Enterprise | F25: East Africa | G25: 2023-01-21 | H25: Active | I25: 16769.74 | J25: 43 | K25: WorkHub Pro | L25: Chakradev Kari | M25: 12 | N25: 0 | O25: =IF(COUNTIF($A$2:A25,A25)>1,"",--(COUNTIFS(Support_Tickets!$B:$B,A25,Support_Tickets!$P:$P,">="&G25,Support_Tickets!$P:$P,"<="&G25+90,Support_Tickets!$K:$K,"No")>0)) -> 0
A26: CUST-0025 | B26: Issac, Dua and Prakash | C26: Logistics | D26: 5000+ | E26: SMB | F26: Middle East | G26: 2022-08-19 | H26: Renewed | I26: 639.82 | J26: 90 | K26: WorkHub Core | L26: Lajita Chatterjee | M26: 24 | N26: 0 | O26: =IF(COUNTIF($A$2:A26,A26)>1,"",--(COUNTIFS(Support_Tickets!$B:$B,A26,Support_Tickets!$P:$P,">="&G26,Support_Tickets!$P:$P,"<="&G26+90,Support_Tickets!$K:$K,"No")>0)) -> 0
A27: CUST-0026 | B27: Zacharia PLC | C27: Logistics | D27: 201–1000 | E27: Mid-Market | F27: South Asia | G27: 2023-08-11 | H27: Active | I27: 3936.51 | J27: 44 | K27: WorkHub Pro | L27: Gayathri Chaudry | M27: 12 | N27: 0 | O27: =IF(COUNTIF($A$2:A27,A27)>1,"",--(COUNTIFS(Support_Tickets!$B:$B,A27,Support_Tickets!$P:$P,">="&G27,Support_Tickets!$P:$P,"<="&G27+90,Support_Tickets!$K:$K,"No")>0)) -> 1
A28: CUST-0027 | B28: Naik Group | C28: Healthcare | D28: 201–1000 | E28: Enterprise | F28: ANZ | G28: 2023-11-03 | H28: Active | I28: 6828.95 | J28: 68 | K28: WorkHub Pro | L28: Viraj Tiwari | M28: 12 | N28: 0 | O28: =IF(COUNTIF($A$2:A28,A28)>1,"",--(COUNTIFS(Support_Tickets!$B:$B,A28,Support_Tickets!$P:$P,">="&G28,Support_Tickets!$P:$P,"<="&G28+90,Support_Tickets!$K:$K,"No")>0)) -> 0
A29: CUST-0028 | B29: Choudhury LLC | C29: Real Estate | D29: 51–200 | E29: Enterprise | F29: Southeast Asia | G29: 2022-02-21 | H29: Active | I29: 12931.22 | K29: WorkHub Pro | L29: Chakradev Kari | M29: 12 | N29: 0 | O29: =IF(COUNTIF($A$2:A29,A29)>1,"",--(COUNTIFS(Support_Tickets!$B:$B,A29,Support_Tickets!$P:$P,">="&G29,Support_Tickets!$P:$P,"<="&G29+90,Support_Tickets!$K:$K,"No")>0)) -> 0
A30: CUST-0029 | B30: Khatri-Bhardwaj | C30: Retail | D30: 1–50 | E30: SMB | F30: East Africa | G30: 2024-09-28 | H30: Active | I30: 754.52 | J30: 60 | K30: WorkHub Core | L30: Gayathri Chaudry | M30: 24 | N30: 0 | O30: =IF(COUNTIF($A$2:A30,A30)>1,"",--(COUNTIFS(Support_Tickets!$B:$B,A30,Support_Tickets!$P:$P,">="&G30,Support_Tickets!$P:$P,"<="&G30+90,Support_Tickets!$K:$K,"No")>0)) -> 0
A31: CUST-0030 | B31: Brar Inc | C31: BFSI | D31: 1–50 | E31: Mid-Market | F31: East Africa | G31: 2022-08-26 | H31: Churned | I31: 3797.34 | J31: 22 | K31: WorkHub Pro | L31: Udant Dewan | M31: 24 | N31: 1 | O31: =IF(COUNTIF($A$2:A31,A31)>1,"",--(COUNTIFS(Support_Tickets!$B:$B,A31,Support_Tickets!$P:$P,">="&G31,Support_Tickets!$P:$P,"<="&G31+90,Support_Tickets!$K:$K,"No")>0)) -> 0
A32: CUST-0031 | B32: Sunder, Biswas and Walia | C32: Retail | D32: 201–1000 | E32: SMB | F32: South Asia | G32: 2022-01-10 | H32: Churned | I32: 749.92 | J32: 42 | K32: WorkHub Core | L32: Viraj Tiwari | M32: 36 | N32: 1 | O32: =IF(COUNTIF($A$2:A32,A32)>1,"",--(COUNTIFS(Support_Tickets!$B:$B,A32,Support_Tickets!$P:$P,">="&G32,Support_Tickets!$P:$P,"<="&G32+90,Support_Tickets!$K:$K,"No")>0)) -> 0
A33: CUST-0032 | B33: Dave Ltd | C33: EdTech | D33: 1–50 | E33: SMB | F33: Middle East | G33: 2022-06-16 | H33: Churned | I33: 603.02 | J33: 1 | K33: WorkHub Core | L33: Saumya Mall | M33: 12 | N33: 1 | O33: =IF(COUNTIF($A$2:A33,A33)>1,"",--(COUNTIFS(Support_Tickets!$B:$B,A33,Support_Tickets!$P:$P,">="&G33,Support_Tickets!$P:$P,"<="&G33+90,Support_Tickets!$K:$K,"No")>0)) -> 0
A34: CUST-0033 | B34: Gandhi-Lanka | C34: Media & Entertainment | D34: 1001–5000 | E34: Mid-Market | F34: East Africa | G34: 02/12/2022 | H34: Churned | I34: 1391.3 | J34: 17 | K34: WorkHub Pro | L34: Aryan Maharaj | M34: 24 | N34: 1 | O34: =IF(COUNTIF($A$2:A34,A34)>1,"",--(COUNTIFS(Support_Tickets!$B:$B,A34,Support_Tickets!$P:$P,">="&G34,Support_Tickets!$P:$P,"<="&G34+90,Support_Tickets!$K:$K,"No")>0)) -> 0
A35: CUST-0034 | B35: Sampath, Kakar and Zacharia | C35: Government | D35: 201–1000 | E35: SMB | F35: Middle East | G35: 2022-11-06 | H35: Churned | I35: 283.09 | J35: 46 | K35: WorkHub Core | L35: Ayushman Chander | M35: 24 | N35: 1 | O35: =IF(COUNTIF($A$2:A35,A35)>1,"",--(COUNTIFS(Support_Tickets!$B:$B,A35,Support_Tickets!$P:$P,">="&G35,Support_Tickets!$P:$P,"<="&G35+90,Support_Tickets!$K:$K,"No")>0)) -> 0
A36: CUST-0035 | B36: Iyer, Muni and Rastogi | C36: Media & Entertainment | D36: 5000+ | E36: Mid-Market | F36: Middle East | G36: 08/12/2023 | H36: Renewed | I36: 1744.12 | J36: 78 | K36: WorkHub Pro | L36: Chakradev Kari | M36: 12 | N36: 0 | O36: =IF(COUNTIF($A$2:A36,A36)>1,"",--(COUNTIFS(Support_Tickets!$B:$B,A36,Support_Tickets!$P:$P,">="&G36,Support_Tickets!$P:$P,"<="&G36+90,Support_Tickets!$K:$K,"No")>0)) -> 0
A37: CUST-0036 | B37: Prakash, Sarma and Varughese | C37: Real Estate | D37: 201–1000 | E37: Mid-Market | F37: ANZ | G37: 2023-12-20 | H37: Active | I37: 2520.06 | J37: 85 | K37: WorkHub Pro | L37: Gagan Sami | M37: 36 | N37: 0 | O37: =IF(COUNTIF($A$2:A37,A37)>1,"",--(COUNTIFS(Support_Tickets!$B:$B,A37,Support_Tickets!$P:$P,">="&G37,Support_Tickets!$P:$P,"<="&G37+90,Support_Tickets!$K:$K,"No")>0)) -> 0
A38: CUST-0037 | B38: Dara-Kota | C38: Manufacturing | D38: 1–50 | E38: SMB | F38: East Africa | G38: 25/04/2022 | H38: Active | I38: 453.84 | J38: 73 | K38: WorkHub Core | L38: Lajita Chatterjee | M38: 36 | N38: 0 | O38: =IF(COUNTIF($A$2:A38,A38)>1,"",--(COUNTIFS(Support_Tickets!$B:$B,A38,Support_Tickets!$P:$P,">="&G38,Support_Tickets!$P:$P,"<="&G38+90,Support_Tickets!$K:$K,"No")>0)) -> 0
A39: CUST-0038 | B39: Bhatt LLC | C39: EdTech | D39: 5000+ | E39: Mid-Market | F39: ANZ | G39: 2022-04-04 | H39: Active | I39: 978.03 | J39: 16 | K39: WorkHub Core | L39: Udant Dewan | M39: 36 | N39: 0 | O39: =IF(COUNTIF($A$2:A39,A39)>1,"",--(COUNTIFS(Support_Tickets!$B:$B,A39,Support_Tickets!$P:$P,">="&G39,Support_Tickets!$P:$P,"<="&G39+90,Support_Tickets!$K:$K,"No")>0)) -> 0
A40: CUST-0039 | B40: Karpe PLC | C40: Logistics | D40: 1–50 | E40: SMB | F40: ANZ | G40: 2022-09-18 | H40: At Risk | I40: 504.82 | J40: 5 | K40: WorkHub Core | L40: Lajita Mall | M40: 12 | N40: 1 | O40: =IF(COUNTIF($A$2:A40,A40)>1,"",--(COUNTIFS(Support_Tickets!$B:$B,A40,Support_Tickets!$P:$P,">="&G40,Support_Tickets!$P:$P,"<="&G40+90,Support_Tickets!$K:$K,"No")>0)) -> 0
A41: CUST-0040 | B41: Amble Inc | C41: Healthcare | D41: 1001–5000 | E41: Mid-Market | F41: South Asia | G41: 2022-10-21 | H41: At Risk | I41: 3250.65 | J41: 93 | K41: WorkHub Core | L41: Hemangini Lalla | M41: 24 | N41: 1 | O41: =IF(COUNTIF($A$2:A41,A41)>1,"",--(COUNTIFS(Support_Tickets!$B:$B,A41,Support_Tickets!$P:$P,">="&G41,Support_Tickets!$P:$P,"<="&G41+90,Support_Tickets!$K:$K,"No")>0)) -> 0
A42: CUST-0041 | B42: Bhargava, Karnik and Bir | C42: Media & Entertainment | D42: 1001–5000 | E42: SMB | F42: South Asia | G42: 2023-12-01 | H42: Renewed | I42: 193.09 | K42: WorkHub Core | L42: Fariq Kaul | M42: 12 | N42: 0 | O42: =IF(COUNTIF($A$2:A42,A42)>1,"",--(COUNTIFS(Support_Tickets!$B:$B,A42,Support_Tickets!$P:$P,">="&G42,Support_Tickets!$P:$P,"<="&G42+90,Support_Tickets!$K:$K,"No")>0)) -> 0
A43: CUST-0042 | B43: Narayanan Inc | C43: EdTech | D43: 1–50 | E43: Enterprise | F43: South Asia | G43: 2024-09-28 | H43: Churned | I43: 11622.23 | J43: 68 | K43: WorkHub Enterprise | L43: Nathaniel Sami | M43: 24 | N43: 1 | O43: =IF(COUNTIF($A$2:A43,A43)>1,"",--(COUNTIFS(Support_Tickets!$B:$B,A43,Support_Tickets!$P:$P,">="&G43,Support_Tickets!$P:$P,"<="&G43+90,Support_Tickets!$K:$K,"No")>0)) -> 0
A44: CUST-0043 | B44: Khanna, Mallick and Sunder | C44: Logistics | D44: 51–200 | E44: Mid-Market | F44: South Asia | G44: 2022-02-02 | H44: Active | I44: 3251.37 | K44: WorkHub Pro | L44: Ayushman Chander | M44: 36 | N44: 0 | O44: =IF(COUNTIF($A$2:A44,A44)>1,"",--(COUNTIFS(Support_Tickets!$B:$B,A44,Support_Tickets!$P:$P,">="&G44,Support_Tickets!$P:$P,"<="&G44+90,Support_Tickets!$K:$K,"No")>0)) -> 0
A45: CUST-0044 | B45: Zacharia and Sons | C45: Real Estate | D45: 1–50 | E45: Mid-Market | F45: Southeast Asia | G45: 29/01/2024 | H45: Active | I45: 2527.23 | J45: 96 | K45: WorkHub Pro | L45: Viraj Tiwari | M45: 36 | N45: 0 | O45: =IF(COUNTIF($A$2:A45,A45)>1,"",--(COUNTIFS(Support_Tickets!$B:$B,A45,Support_Tickets!$P:$P,">="&G45,Support_Tickets!$P:$P,"<="&G45+90,Support_Tickets!$K:$K,"No")>0)) -> 1
A46: CUST-0045 | B46: Solanki, Kibe and Solanki | C46: EdTech | D46: 5000+ | E46: Enterprise | F46: Middle East | G46: 2023-08-15 | H46: Churned | I46: 8489.31 | J46: 38 | K46: WorkHub Enterprise | L46: Kritika Brar | M46: 24 | N46: 1 | O46: =IF(COUNTIF($A$2:A46,A46)>1,"",--(COUNTIFS(Support_Tickets!$B:$B,A46,Support_Tickets!$P:$P,">="&G46,Support_Tickets!$P:$P,"<="&G46+90,Support_Tickets!$K:$K,"No")>0)) -> 0
A47: CUST-0046 | B47: Gupta-Chandra | C47: Telecom | D47: 5000+ | E47: Mid-Market | F47: Southeast Asia | G47: 2023-10-04 | H47: Churned | I47: 950.03 | J47: 44 | K47: WorkHub Core | L47: Fariq Kaul | M47: 24 | N47: 1 | O47: =IF(COUNTIF($A$2:A47,A47)>1,"",--(COUNTIFS(Support_Tickets!$B:$B,A47,Support_Tickets!$P:$P,">="&G47,Support_Tickets!$P:$P,"<="&G47+90,Support_Tickets!$K:$K,"No")>0)) -> 1
A48: CUST-0047 | B48: Sankar LLC | C48: Media & Entertainment | D48: 51–200 | E48: Enterprise | F48: Middle East | G48: 2023-01-21 | H48: Active | I48: 7373.55 | J48: 28 | K48: WorkHub Enterprise | L48: Janaki Handa | M48: 12 | N48: 0 | O48: =IF(COUNTIF($A$2:A48,A48)>1,"",--(COUNTIFS(Support_Tickets!$B:$B,A48,Support_Tickets!$P:$P,">="&G48,Support_Tickets!$P:$P,"<="&G48+90,Support_Tickets!$K:$K,"No")>0)) -> 0
A49: CUST-0048 | B49: Roy-Sibal | C49: Media & Entertainment | D49: 5000+ | E49: Mid-Market | F49: East Africa | G49: 2022-05-18 | H49: Active | I49: 1856.84 | J49: 10 | K49: WorkHub Core | L49: Gagan Sami | M49: 36 | N49: 0 | O49: =IF(COUNTIF($A$2:A49,A49)>1,"",--(COUNTIFS(Support_Tickets!$B:$B,A49,Support_Tickets!$P:$P,">="&G49,Support_Tickets!$P:$P,"<="&G49+90,Support_Tickets!$K:$K,"No")>0)) -> 0
A50: CUST-0049 | B50: Bhagat, Chaudhari and Bhat | C50: EdTech | D50: 1–50 | E50: Mid-Market | F50: Middle East | G50: 2023-01-22 | H50: Churned | I50: 3595.59 | J50: 24 | K50: WorkHub Pro | L50: Chakradev Kari | M50: 12 | N50: 1 | O50: =IF(COUNTIF($A$2:A50,A50)>1,"",--(COUNTIFS(Support_Tickets!$B:$B,A50,Support_Tickets!$P:$P,">="&G50,Support_Tickets!$P:$P,"<="&G50+90,Support_Tickets!$K:$K,"No")>0)) -> 0
A51: CUST-0050 | B51: Nori-Chopra | C51: Manufacturing | D51: 201–1000 | E51: Mid-Market | F51: South Asia | G51: 2022-08-05 | H51: Renewed | I51: 1175.41 | J51: 96 | K51: WorkHub Pro | L51: Saumya Mall | M51: 24 | N51: 0 | O51: =IF(COUNTIF($A$2:A51,A51)>1,"",--(COUNTIFS(Support_Tickets!$B:$B,A51,Support_Tickets!$P:$P,">="&G51,Support_Tickets!$P:$P,"<="&G51+90,Support_Tickets!$K:$K,"No")>0)) -> 0
A52: CUST-0051 | B52: Handa and Sons | C52: Telecom | D52: 201–1000 | E52: Mid-Market | F52: Middle East | G52: 2023-01-25 | H52: Churned | I52: 1786.95 | J52: 46 | K52: WorkHub Core | L52: Janaki Handa | M52: 12 | N52: 1 | O52: =IF(COUNTIF($A$2:A52,A52)>1,"",--(COUNTIFS(Support_Tickets!$B:$B,A52,Support_Tickets!$P:$P,">="&G52,Support_Tickets!$P:$P,"<="&G52+90,Support_Tickets!$K:$K,"No")>0)) -> 0
